Workbook

Sheet Freddie REMIC Series 2848!!
A1: Zoom | AB1: Months | AC1: Starting balance | AD1: payment | AE1: interest+Servicing | AF1: principal | AG1: remaining balance | AL1: Date | AM1: 1 | AN1: 2 | AO1: 3 | AP1: 4 | AQ1: 6 | AR1: 12 | AS1: 24 | AT1: 36 | AU1: 60 | AV1: 84 | AW1: 120 | AX1: 240 | AY1: 360 | BA1: Weighted Average Life Sensitivity Analysis | CF1: Reformed for report
E2: Traunches | F2: Par Amount | G2: Coupon Rate | H2: WAL Calc | AB2: 1 | AC2: =F11 -> 206500000 | AD2: =PMT($K$4/12,$K$7-AB2+1,-AC2) -> 1428195.9 | AE2: =AC2*$K$4/12 -> 957815.83 | AF2: =AD2-AE2 -> 470380.09 | AG2: =AC2-AF2 -> 2.0602962e+08 | AI2: Traunches | AJ2: WAL | AL2: 39689 | AM2: 0.0163 | AN2: N/A | AO2: 0.0172 | AP2: N/A | AQ2: 0.0197 | AR2: 0.0217 | AS2: 0.0236 | AT2: 0.026 | AU2: 0.031 | AV2: 0.0345 | AW2: 0.0383 | AX2: 0.0447 | AY2: 0.0443 | BA2: PSA Speed | BB2: Tranche CA | BC2: PSA Speed | BD2: Tranche CG | BE2: PSA Speed | BF2: Tranche CM | BG2: PSA Speed | BH2: Tranche CY | BI2: PSA Speed | BJ2: Tranche CZ | BK2: PSA Speed | BL2: Tranche GZ | BM2: PSA Speed | BN2: Tranche TC | BO2: PSA Speed | BP2: Tranche VE | BQ2: PSA Speed | BR2: Collateral | BU2: CA | BV2: CG | BW2: CM | BX2: CY | BY2: CZ | BZ2: GZ | CA2: TC | CB2: VE | CC2: Collateral | CF2: Weighted Average Life Sensitivity Analysis
E3: CA | F3: 32550000 | G3: 0.05 | H3: =F3*G3 -> 1627500 | J3: Assumptions | L3: Asset Principal Amount | AB3: 2 | AC3: =AG2 -> 2.0602962e+08 | AD3: =PMT($K$4/12,$K$7-AB3+1,-AC3) -> 1428195.9 | AE3: =AC3*$K$4/12 -> 955634.05 | AF3: =AD3-AE3 -> 472561.87 | AG3: =AC3-AF3 -> 2.0555706e+08 | AI3: CA | AJ3: =SUM(BE18:BE252)/(12*F3) -> 9.3643558 | BA3: 0 | BB3: =AJ3 -> 9.3643558 | BC3: 0 | BD3: =AJ4 -> 5.8415175 | BE3: 0 | BF3: =AJ5 -> 8.7321876 | BG3: 0 | BH3: =AJ6 -> 18.118717 | BI3: 0 | BJ3: =AJ7 -> 17.912258 | BK3: 0 | BL3: =AJ8 -> 12.530733 | BM3: 0 | BN3: =AJ9 -> 14.958684 | BO3: 0 | BP3: =AJ10 -> 2.2429547 | BQ3: 0 | BR3: =AJ11 -> 11.573998 | BT3: Value | BU3: =SUMPRODUCT(BD$18:BD$252,BF$18:BF$252) -> 32550000 | BV3: =SUMPRODUCT(AR$18:AR$252,AT$18:AT$252) -> 74800000 | BW3: =SUMPRODUCT(AU$18:AU$252,AW$18:AW$252) -> 14000000 | BX3: =SUMPRODUCT(BG$18:BG$252,BI$18:BI$252) -> 13950000 | BY3: =SUMPRODUCT(BL$18:BL$252,BJ$18:BJ$252) -> 24000000 | BZ3: =SUMPRODUCT(AX$18:AX$252,AZ$18:AZ$252) -> 24000000 | CA3: =SUMPRODUCT(BA$18:BA$252,BC$18:BC$252) -> 20000000 | CB3: =SUMPRODUCT(AO$18:AO$252,AQ$18:AQ$252) -> 5200000 | CC3: =SUMPRODUCT(BM$18:BM$252,BO$18:BO$252) -> 2.065e+08 | CF3: PSA Speed | CG3: Tranche CA | CH3: Tranche CG | CI3: Tranche CM | CJ3: Tranche CY | CK3: Tranche CZ | CL3: Tranche GZ | CM3: Tranche TC | CN3: Tranche VE | CO3: Collateral
E4: CG | F4: 74800000 | G4: 0.05 | H4: =F4*G4 -> 3740000 | J4: WAC | K4: =5.566% -> 0.05566 | L4: CA & CY | M4: 0.2251816 | N4: GROUP A | AB4: 3 | AC4: =AG3 -> 2.0555706e+08 | AD4: =PMT($K$4/12,$K$7-AB4+1,-AC4) -> 1428195.9 | AE4: =AC4*$K$4/12 -> 953442.15 | AF4: =AD4-AE4 -> 474753.77 | AG4: =AC4-AF4 -> 2.050823e+08 | AI4: CG | AJ4: =SUM(AS18:AS252)/(12*F4) -> 5.8415175 | AY4: CA | BA4: 100 | BB4: 5.6659899 | BC4: 100 | BD4: 3.5120336 | BE4: 100 | BF4: 6.6123424 | BG4: 100 | BH4: 15.400692 | BI4: 100 | BJ4: 15.711021 | BK4: 100 | BL4: 8.7081094 | BM4: 100 | BN4: 11.202441 | BO4: 100 | BP4: 2.2429547 | BQ4: 100 | BR4: 8.1697338 | BT4: Difference | BU4: =BU3-F3 -> -0.00059144944 | BV4: =BV3-F4 -> 0.00071665645 | BW4: =BW3-F5 -> 0 | BX4: =BX3-F6 -> -0.00018227659 | BY4: =BY3-F7 -> 9.1589987e-05 | BZ4: =BZ3-F7 -> 0.00018005446 | CA4: =CA3-F9 -> 1.937151e-07 | CB4: =CB3-F10 -> 3.8762577e-05 | CC4: =CC3-F11 -> 0 | CF4: 0 | CG4: =BB3 -> 9.3643558 | CH4: =BD3 -> 5.8415175 | CI4: =BF3 -> 8.7321876 | CJ4: =BH3 -> 18.118717 | CK4: =BJ3 -> 17.912258 | CL4: =BL3 -> 12.530733 | CM4: =BN3 -> 14.958684 | CN4: =BP3 -> 2.2429547 | CO4: =BR3 -> 11.573998
E5: CM | F5: 14000000 | G5: 0.05 | H5: =F5*G5 -> 700000 | J5: PSA | K5: 0 | L5: CG, VE, CM, GZ,TC &CZ | M5: 0.7748184 | N5: GROUP B | AB5: 4 | AC5: =AG4 -> 2.050823e+08 | AD5: =PMT($K$4/12,$K$7-AB5+1,-AC5) -> 1428195.9 | AE5: =AC5*$K$4/12 -> 951240.09 | AF5: =AD5-AE5 -> 476955.84 | AG5: =AC5-AF5 -> 2.0460535e+08 | AI5: CM | AJ5: =SUM(AV18:AV252)/(12*F5) -> 8.7321876 | AY5: CG | BA5: 183 | BB5: 4.2294642 | BC5: 183 | BD5: 2.7577516 | BE5: 183 | BF5: 5.2415728 | BG5: 183 | BH5: 12.803596 | BI5: 183 | BJ5: 13.623822 | BK5: 183 | BL5: 6.7645783 | BM5: 183 | BN5: 8.8796982 | BO5: 183 | BP5: 2.2429547 | BQ5: 183 | BR5: 6.3850369 | BT5: X* | BU5: 0.018698323 | BV5: 0.021949747 | BW5: 0.020333588 | BX5: 0.013531563 | BY5: 0.011023044 | BZ5: 0.0089434935 | CA5: 0.015749795 | CB5: 0.025358489 | CC5: 0.016489902 | CF5: 100 | CG5: 5.6659899 | CH5: 3.5120336 | CI5: 6.6123424 | CJ5: 15.400692 | CK5: 15.711021 | CL5: 8.7081094 | CM5: 11.202441 | CN5: 2.2429547 | CO5: 8.1697338
E6: CY | F6: 13950000 | G6: 0.05 | H6: =F6*G6 -> 697500 | J6: CPR | K6: 0.06 | AB6: 5 | AC6: =AG5 -> 2.0460535e+08 | AD6: =PMT($K$4/12,$K$7-AB6+1,-AC6) -> 1428195.9 | AE6: =AC6*$K$4/12 -> 949027.81 | AF6: =AD6-AE6 -> 479168.12 | AG6: =AC6-AF6 -> 2.0412618e+08 | AI6: CY | AJ6: =SUM(BH18:BH252)/(12*F6) -> 18.118717 | AY6: CM | BA6: 300 | BB6: 3.2045167 | BC6: 300 | BD6: 2.2238214 | BE6: 300 | BF6: 4.0695959 | BG6: 300 | BH6: 9.8504401 | BI6: 300 | BJ6: 10.938476 | BK6: 300 | BL6: 5.1646061 | BM6: 300 | BN6: 6.7897131 | BO6: 300 | BP6: 2.1231628 | BQ6: 300 | BR6: 4.781627 | CF6: 183 | CG6: 4.2294642 | CH6: 2.7577516 | CI6: 5.2415728 | CJ6: 12.803596 | CK6: 13.623822 | CL6: 6.7645783 | CM6: 8.8796982 | CN6: 2.2429547 | CO6: 6.3850369
E7: CZ | F7: 24000000 | G7: 0.05 | H7: =F7*G7 -> 1200000 | J7: Term (m) | K7: 240 | AI7: CZ | AJ7: =SUM(BK18:BK252)/(12*AL12) -> 17.912258 | AY7: CY | BA7: 400 | BB7: 2.7191159 | BC7: 400 | BD7: 1.9634823 | BE7: 400 | BF7: 3.472098 | BG7: 400 | BH7: 8.0637162 | BI7: 400 | BJ7: 9.1532973 | BK7: 400 | BL7: 4.3320606 | BM7: 400 | BN7: 5.6467827 | BO7: 400 | BP7: 1.9474084 | BQ7: 400 | BR7: 3.9058293 | CF7: 300 | CG7: 3.2045167 | CH7: 2.2238214 | CI7: 4.0695959 | CJ7: 9.8504401 | CK7: 10.938476 | CL7: 5.1646061 | CM7: 6.7897131 | CN7: 2.1231628 | CO7: 4.781627
E8: GZ | F8: 22000000 | G8: 0.05 | H8: =F8*G8 -> 1100000 | J8: Term to Maturity | K8: 235 | AI8: GZ | AJ8: =SUM(AY18:AY252)/(12*AL11) -> 12.530733 | AY8: CZ | CF8: 400 | CG8: 2.7191159 | CH8: 1.9634823 | CI8: 3.472098 | CJ8: 8.0637162 | CK8: 9.1532973 | CL8: 4.3320606 | CM8: 5.6467827 | CN8: 1.9474084 | CO8: 3.9058293
E9: TC | F9: 20000000 | G9: 0.05 | H9: =F9*G9 -> 1000000 | AI9: TC | AJ9: =SUM(BB18:BB252)/(12*F9) -> 14.958684 | AY9: GZ
E10: VE | F10: 5200000 | G10: 0.05 | H10: =F10*G10 -> 260000 | K10: Assets | AI10: VE | AJ10: =SUM(AP18:AP252)/(12*F10) -> 2.2429547 | AY10: TC | BT10: PSA & X* Sensitivity Analysis
E11: The Assets | F11: =SUM(F3:F10) -> 206500000 | G11: 0.05 | H11: =SUM(H3:H10) -> 10325000 | J11: Balance | K11: 206500000 | AI11: Collateral | AJ11: =SUM(BN18:BN252)/(12*F11) -> 11.573998 | AK11: Max GZ | AL11: =MAX(Y18:Y252) -> 36759331 | AY11: VE | BT11: PSA Speed | BU11: Tranche CA | BV11: Tranche CG | BW11: Tranche CM | BX11: Tranche CY | BY11: Tranche CZ | BZ11: Tranche GZ | CA11: Tranche TC | CB11: Tranche VE | CC11: Collateral
J12: Term | K12: 235 | AK12: Max CZ | AL12: =MAX(AK18:AK252) -> 51365651 | BT12: 0 | BU12: =BU5 -> 0.018698323 | BV12: =BV5 -> 0.021949747 | BW12: =BW5 -> 0.020333588 | BX12: =BX5 -> 0.013531563 | BY12: =BY5 -> 0.011023044 | BZ12: =BZ5 -> 0.0089434935 | CA12: =CA5 -> 0.015749795 | CB12: =CB5 -> 0.025358489 | CC12: =CC5 -> 0.016489902
J13: WACC | K13: 0.05566 | Q13: Principal Check | T13: Principal Check | W13: Principal Check | Z13: Principal Check | AC13: Principal Check | AF13: Principal Check | AI13: Principal Check | AL13: Principal Check | BT13: 100 | BU13: ='PSA 100 vs X'!BU5 -> 0.02192039 | BV13: ='PSA 100 vs X'!BV5 -> 0.024446806 | BW13: ='PSA 100 vs X'!BW5 -> 0.022364026 | BX13: ='PSA 100 vs X'!BX5 -> 0.015325083 | BY13: ='PSA 100 vs X'!BY5 -> 0.013014966 | BZ13: ='PSA 100 vs X'!BZ5 -> 0.0094330705 | CA13: ='PSA 100 vs X'!CA5 -> 0.018586373 | CB13: ='PSA 100 vs X'!CB5 -> 0.025358489 | CC13: ='PSA 100 vs X'!CC5 -> 0.018573832
Q14: =SUM(Q18:Q252) -> 5200000 | T14: =SUM(T18:T252) -> 74800000 | W14: =SUM(W18:W252) -> 14000000 | Z14: =SUM(Z18:Z252) -> 36759331 | AC14: =SUM(AC18:AC252) -> 20000000 | AF14: =SUM(AF18:AF252) -> 32550000 | AI14: =SUM(AI18:AI252) -> 13950000 | AL14: =SUM(AL18:AL252) -> 51168706 | BT14: 183 | BU14: {='PSA 183 on X'!BU5:CC5} -> 0.023516729 | BV14: 0.025345018 | BW14: 0.023591729 | BX14: 0.017086336 | BY14: 0.014918714 | BZ14: 0.00807609 | CA14: 0.020458943 | CB14: 0.025358489 | CC14: 0.020014572
BT15: 300 | BU15: {='PSA 300 vs X'!BU5:CC5} -> 0.02475377 | BV15: 0.025986937 | BW15: 0.024644633 | BX15: 0.019234935 | BY15: 0.017050756 | BZ15: 0.0050007568 | CA15: 0.022223415 | CB15: 0.025575242 | CC15: 0.021548058
N16: Asset Prinicpal Amount | Q16: Tranche VE | T16: Tranche CG | W16: Tranche CM | Z16: Tranche GZ | AC16: Tranche TC | AF16: Tranche CA | AH16: Tranche CY | AK16: Tranche CZ | AN16: Treasury | AP16: Tranche VE | AS16: Tranche CG | AV16: Tranche CM | AY16: Tranche GZ | BB16: Tranche TC | BE16: Tranche CA | BG16: Tranche CY | BJ16: Tranche CZ | BM16: Collateral | BT16: 400 | BU16: {='PSA 400 on X'!BU5:CC5} -> 0.025355313 | BV16: 0.026294327 | BW16: 0.02519042 | BX16: 0.020661746 | BY16: 0.018584184 | BZ16: 0.001909631 | CA16: 0.023220943 | CB16: 0.025850064 | CC16: 0.022559104
A17: CPR Month | B17: Month | C17: Principal | E17: Asset Principal | F17: Payment | G17: Interest+Servicing | H17: Principal | I17: CPR | J17: SMM | K17: Prepayment | L17: Total Collateral CF | M17: Excess CF | N17: Group A | O17: Group B | P17: Balance | Q17: Principal2 | R17: Interest | S17: Balance5 | T17: Principal6 | U17: Interest7 | V17: Balance8 | W17: Principal9 | X17: Interest | Y17: Balance11 | Z17: Principal12 | AA17: Interest(Z) | AB17: Balance14 | AC17: Principal15 | AD17: Interest16 | AE17: Balance20 | AF17: Principal21 | AG17: Interest22 | AH17: Balance202 | AI17: Principal213 | AJ17: Interest224 | AK17: Balance3 | AL17: Principal4 | AM17: Interest(Z) | AN17: Yield Curve | AO17: Cash Flow | AP17: Average life | AQ17: Discount Factor | AR17: Cash Flow | AS17: Average life | AT17: Discount Factor | AU17: Cash Flow | AV17: Average life | AW17: Discount Factor | AX17: Cash Flow | AY17: Average life | AZ17: Discount Factor | BA17: Cash Flow | BB17: Average life | BC17: Discount Factor | BD17: Cash Flow | BE17: Average life | BF17: Discount Factor | BG17: Cash Flow | BH17: Average life | BI17: Discount Factor | BJ17: Cash Flow | BK17: Average life | BL17: Discount Factor | BM17: Cash Flow | BN17: Average life | BO17: Discount Factor
A18: 6 | B18: 1 | C18: =P18+S18+V18+Y18+AB18+AE18+AH18+AK18 -> 206500000 | D18: =C18-E18 -> 0 | E18: =$F$11 -> 206500000 | F18: =PMT($K$13/12,$K$12-B18+1,-E18,0) -> 1444804.7 | G18: =E18*$K$13/12 -> 957815.83 | H18: =F18-G18 -> 486988.84 | I18: =IF(A18<=(30-(240-$K$8)),((A18+(240-$K$7))/30)*$K$6,$K$6)*($K$5/100) -> 0 | J18: =1-(1-I18)^(1/12) -> 0 | K18: =(E18-H18)*J18 -> 0 | L18: =K18+H18+G18 -> 1444804.7 | M18: =L18-G18 -> 486988.84 | N18: =M18*$M$4 -> 109660.92 | O18: =M18*$M$5 -> 377327.91 | P18: =$F$10 -> 5200000 | Q18: =MIN(IF(S18>O18,0,MIN(P18,O18-S18))+IF(P18>0,MIN(AA18,P18)),P18) -> 91666.667 | R18: =P18*($G$10/12) -> 21666.667 | S18: =$F$4 -> 74800000 | T18: =MIN(IF(S18>O18,O18,S18)+IF(S18>0,AM18,0),S18) -> 477327.91 | U18: =S18*($G$4/12) -> 311666.67 | V18: =$F$5 -> 14000000 | W18: =IF(T18+P18<=O18+AM18+AA18,MIN(V18,O18-Q18+AA18-T18+AM18),0) -> 0 | X18: =V18*($G$5/12) -> 58333.333 | Y18: =$F$8 -> 22000000 | Z18: =IF(V18>O18,0,MIN(Y18,O18-V18)) -> 0 | AA18: =Y18*($G$8/12) -> 91666.667 | AB18: =F9 -> 20000000 | AC18: =MIN(IF(Y18>O18,0,MIN(AB18,O18+AM18-Y18))) -> 0 | AD18: =AB18*($G$9/12) -> 83333.333 | AE18: =F3 -> 32550000 | AF18: =IF(AE18>N18,N18,AE18) -> 109660.92 | AG18: =AE18*($G$3/12) -> 135625 | AH18: =F6 -> 13950000 | AI18: =IF(AE18>N18,0,MIN(AH18,N18-AE18)) -> 0 | AJ18: =AH18*($G$6/12) -> 58125 | AK18: =F7 -> 24000000 | AL18: =IF(AB18>0,IF(AB18>O18,0,MIN(AK18,O18-AB18)),O18) -> 0 | AM18: =AK18*($G$7/12) -> 100000 | AN18: =FORECAST(B18, $AM$2:$AY$2,$AM$1:$AY$1) -> 0.022010844 | AO18: =Q18+R18 -> 113333.33 | AP18: =Q18*B18 -> 91666.667 | AQ18: =1/(1+(AN18+$CB$5)/12)^$B18 -> 0.99606808 | AR18: =T18+U18 -> 788994.58 | AS18: =T18*A18 -> 2863967.5 | AT18: =1/(1+(AN18+$BV$5)/12)^$B18 -> 0.99634999 | AU18: =W18+X18 -> 58333.333 | AV18: =W18*A18 -> 0 | AW18: =1/(1+(AN18+$BW$5)/12)^$B18 -> 0.99648371 | AX18: =IF(Y19>Y18,0,Z18+AA18) -> 0 | AY18: =A18*Z18 -> 0 | AZ18: =1/(1+(AN18+$BZ$5)/12)^$B18 -> 0.99742711 | BA18: =AC18+AD18 -> 83333.333 | BB18: =AC18*A18 -> 0 | BC18: =1/(1+(AN18+$CA$5)/12)^$B18 -> 0.99686315 | BD18: =AF18+AG18 -> 245285.92 | BE18: =AF18*A18 -> 657965.55 | BF18: =1/(1+(AN18+$BU$5)/12)^$B18 -> 0.99661904 | BG18: =AI18+AJ18 -> 58125 | BH18: =AI18*A18 -> 0 | BI18: =1/(1+(AN18+$BX$5)/12)^$B18 -> 0.99704688 | BJ18: =IF(AK19>AK18,0,AL18+AM18) -> 0 | BK18: =A18*AL18 -> 0 | BL18: =1/(1+(AN18+$BY$5)/12)^$B18 -> 0.99725473 | BM18: =AO18+AR18+AU18+AX18+BA18+BD18+BG18+BJ18 -> 1347405.5 | BN18: =M18*B18 -> 486988.84 | BO18: =1/(1+(AN18+$CC$5)/12)^$B18 -> 0.99680187
A19: 7 | B19: 2 | C19: =P19+S19+V19+Y19+AB19+AE19+AH19+AK19 -> 2.0601301e+08 | D19: =C19-E19 -> 0 | E19: =E18-H18-K18 -> 2.0601301e+08 | F19: =PMT($K$13/12,$K$12-B19+1,-E19,0) -> 1444804.7 | G19: =E19*$K$13/12 -> 955557.02 | H19: =F19-G19 -> 489247.66 | I19: =IF(A19<=(30-(240-$K$8)),((A19+(240-$K$7))/30)*$K$6,$K$6)*($K$5/100) -> 0 | J19: =1-(1-I19)^(1/12) -> 0 | K19: =(E19-H19)*J19 -> 0 | L19: =K19+H19+G19 -> 1444804.7 | M19: =L19-G19 -> 489247.66 | N19: =M19*$M$4 -> 110169.57 | O19: =M19*$M$5 -> 379078.09 | P19: =P18-Q18 -> 5108333.3 | Q19: =MIN(IF(S19>O19,0,MIN(P19,O19-S19))+IF(P19>0,MIN(AA19,P19)),P19) -> 92048.611 | R19: =P19*($G$10/12) -> 21284.722 | S19: =S18-T18 -> 74322672 | T19: =MIN(IF(S19>O19,O19,S19)+IF(S19>0,AM19,0),S19) -> 479494.75 | U19: =S19*($G$4/12) -> 309677.8 | V19: =V18-W18 -> 14000000 | W19: =IF(T19+P19<=O19+AM19+AA19,MIN(V19,O19-Q19+AA19-T19+AM19),0) -> 0 | X19: =V19*($G$5/12) -> 58333.333 | Y19: =IF(V18>O18,(IF(V18>AA18+O18+AM18,Y18+AA18,Y18+AA18-((AA18+O18+AM18)-V18))),Y18-Z18) -> 22091667 | Z19: =MIN(IF(V19>O19,0,MIN(Y19,O19-V19))+IF(AM18>V18,AM18,0),Y19) -> 0 | AA19: =Y19*($G$8/12) -> 92048.611 | AB19: =AB18-AC18 -> 20000000 | AC19: =MIN(IF(Y19>O19,0,MIN(AB19,O19+AM19-Y19))) -> 0 | AD19: =AB19*($G$9/12) -> 83333.333 | AE19: =AE18-AF18 -> 32440339 | AF19: =IF(AE19>N19,N19,AE19) -> 110169.57 | AG19: =AE19*($G$3/12) -> 135168.08 | AH19: =AH18-AI18 -> 13950000 | AI19: =IF(AE19>N19,0,MIN(AH19,N19-AE19)) -> 0 | AJ19: =AH19*($G$6/12) -> 58125 | AK19: =IF(AL18=0,AK18+AM18,AK18-AL18) -> 24100000 | AL19: =MIN(IF(AB19>0,IF(AB19>O19,0,MIN(AK19,O19-AB19)),O19),AK19) -> 0 | AM19: =AK19*($G$7/12) -> 100416.67 | AN19: =FORECAST(B19, $AM$2:$AY$2,$AM$1:$AY$1) -> 0.022091251 | AO19: =Q19+R19 -> 113333.33 | AP19: =Q19*B19 -> 184097.22 | AQ19: =1/(1+(AN19+$CB$5)/12)^$B19 -> 0.99213837 | AR19: =T19+U19 -> 789172.55 | AS19: =T19*A19 -> 3356463.3 | AT19: =1/(1+(AN19+$BV$5)/12)^$B19 -> 0.99270005 | AU19: =W19+X19 -> 58333.333 | AV19: =W19*A19 -> 0 | AW19: =1/(1+(AN19+$BW$5)/12)^$B19 -> 0.99296651 | AX19: =IF(Y20>Y19,0,Z19+AA19) -> 0 | AY19: =A19*Z19 -> 0 | AZ19: =1/(1+(AN19+$BZ$5)/12)^$B19 -> 0.99484754 | BA19: =AC19+AD19 -> 83333.333 | BB19: =AC19*A19 -> 0 | BC19: =1/(1+(AN19+$CA$5)/12)^$B19 -> 0.99372287 | BD19: =AF19+AG19 -> 245337.65 | BE19: =AF19*A19 -> 771186.98 | BF19: =1/(1+(AN19+$BU$5)/12)^$B19 -> 0.99323624 | BG19: =AI19+AJ19 -> 58125 | BH19: =AI19*A19 -> 0 | BI19: =1/(1+(AN19+$BX$5)/12)^$B19 -> 0.9940892 | BJ19: =IF(AK20>AK19,0,AL19+AM19) -> 0 | BK19: =A19*AL19 -> 0 | BL19: =1/(1+(AN19+$BY$5)/12)^$B19 -> 0.99450371 | BM19: =AO19+AR19+AU19+AX19+BA19+BD19+BG19+BJ19 -> 1347635.2 | BN19: =M19*B19 -> 978495.31 | BO19: =1/(1+(AN19+$CC$5)/12)^$B19 -> 0.99360069 | BT19: Changes in Yield Curve and X* Sensitivity Analysis (assuming 183 PSA)
A20: 8 | B20: 3 | C20: =P20+S20+V20+Y20+AB20+AE20+AH20+AK20 -> 2.0552376e+08 | D20: =C20-E20 -> 0 | E20: =E19-H19-K19 -> 2.0552376e+08 | F20: =PMT($K$13/12,$K$12-B20+1,-E20,0) -> 1444804.7 | G20: =E20*$K$13/12 -> 953287.72 | H20: =F20-G20 -> 491516.95 | I20: =IF(A20<=(30-(240-$K$8)),((A20+(240-$K$7))/30)*$K$6,$K$6)*($K$5/100) -> 0 | J20: =1-(1-I20)^(1/12) -> 0 | K20: =(E20-H20)*J20 -> 0 | L20: =K20+H20+G20 -> 1444804.7 | M20: =L20-G20 -> 491516.95 | N20: =M20*$M$4 -> 110680.57 | O20: =M20*$M$5 -> 380836.38 | P20: =P19-Q19 -> 5016284.7 | Q20: =MIN(IF(S20>O20,0,MIN(P20,O20-S20))+IF(P20>0,MIN(AA20,P20)),P20) -> 92432.147 | R20: =P20*($G$10/12) -> 20901.186 | S20: =S19-T19 -> 73843177 | T20: =MIN(IF(S20>O20,O20,S20)+IF(S20>0,AM20,0),S20) -> 481671.45 | U20: =S20*($G$4/12) -> 307679.91 | V20: =V19-W19 -> 14000000 | W20: =IF(T20+P20<=O20+AM20+AA20,MIN(V20,O20-Q20+AA20-T20+AM20),0) -> 0 | X20: =V20*($G$5/12) -> 58333.333 | Y20: =IF(V19>O19,(IF(V19>AA19+O19+AM19,Y19+AA19,Y19+AA19-((AA19+O19+AM19)-V19))),Y19-Z19) -> 22183715 | Z20: =MIN(IF(V20>O20,0,MIN(Y20,O20-V20))+IF(AM19>V19,AM19,0),Y20) -> 0 | AA20: =Y20*($G$8/12) -> 92432.147 | AB20: =AB19-AC19 -> 20000000 | AC20: =MIN(IF(Y20>O20,0,MIN(AB20,O20+AM20-Y20))) -> 0 | AD20: =AB20*($G$9/12) -> 83333.333 | AE20: =AE19-AF19 -> 32330170 | AF20: =IF(AE20>N20,N20,AE20) -> 110680.57 | AG20: =AE20*($G$3/12) -> 134709.04 | AH20: =AH19-AI19 -> 13950000 | AI20: =IF(AE20>N20,0,MIN(AH20,N20-AE20)) -> 0 | AJ20: =AH20*($G$6/12) -> 58125 | AK20: =IF(AL19=0,AK19+AM19,AK19-AL19) -> 24200417 | AL20: =MIN(IF(AB20>0,IF(AB20>O20,0,MIN(AK20,O20-AB20)),O20),AK20) -> 0 | AM20: =AK20*($G$7/12) -> 100835.07 | AN20: =FORECAST(B20, $AM$2:$AY$2,$AM$1:$AY$1) -> 0.022171658 | AO20: =Q20+R20 -> 113333.33 | AP20: =Q20*B20 -> 277296.44 | AQ20: =1/(1+(AN20+$CB$5)/12)^$B20 -> 0.98821098 | AR20: =T20+U20 -> 789351.35 | AS20: =T20*A20 -> 3853371.6 | AT20: =1/(1+(AN20+$BV$5)/12)^$B20 -> 0.98905027 | AU20: =W20+X20 -> 58333.333 | AV20: =W20*A20 -> 0 | AW20: =1/(1+(AN20+$BW$5)/12)^$B20 -> 0.98944853 | AX20: =IF(Y21>Y20,0,Z20+AA20) -> 0 | AY20: =A20*Z20 -> 0 | AZ20: =1/(1+(AN20+$BZ$5)/12)^$B20 -> 0.99226138 | BA20: =AC20+AD20 -> 83333.333 | BB20: =AC20*A20 -> 0 | BC20: =1/(1+(AN20+$CA$5)/12)^$B20 -> 0.99057924 | BD20: =AF20+AG20 -> 245389.61 | BE20: =AF20*A20 -> 885444.58 | BF20: =1/(1+(AN20+$BU$5)/12)^$B20 -> 0.98985171 | BG20: =AI20+AJ20 -> 58125 | BH20: =AI20*A20 -> 0 | BI20: =1/(1+(AN20+$BX$5)/12)^$B20 -> 0.99112705 | BJ20: =IF(AK21>AK20,0,AL20+AM20) -> 0 | BK20: =A20*AL20 -> 0 | BL20: =1/(1+(AN20+$BY$5)/12)^$B20 -> 0.99174703 | BM20: =AO20+AR20+AU20+AX20+BA20+BD20+BG20+BJ20 -> 1347866 | BN20: =M20*B20 -> 1474550.8 | BO20: =1/(1+(AN20+$CC$5)/12)^$B20 -> 0.99039656 | BU20: Tranche CA | BV20: Tranche CG | BW20: Tranche CM | BX20: Tranche CY | BY20: Tranche CZ | BZ20: Tranche GZ | CA20: Tranche TC | CB20: Tranche VE | CC20: Collateral
A21: 9 | B21: 4 | C21: =P21+S21+V21+Y21+AB21+AE21+AH21+AK21 -> 2.0503225e+08 | D21: =C21-E21 -> 0 | E21: =E20-H20-K20 -> 2.0503225e+08 | F21: =PMT($K$13/12,$K$12-B21+1,-E21,0) -> 1444804.7 | G21: =E21*$K$13/12 -> 951007.9 | H21: =F21-G21 -> 493796.77 | I21: =IF(A21<=(30-(240-$K$8)),((A21+(240-$K$7))/30)*$K$6,$K$6)*($K$5/100) -> 0 | J21: =1-(1-I21)^(1/12) -> 0 | K21: =(E21-H21)*J21 -> 0 | L21: =K21+H21+G21 -> 1444804.7 | M21: =L21-G21 -> 493796.77 | N21: =M21*$M$4 -> 111193.95 | O21: =M21*$M$5 -> 382602.82 | P21: =P20-Q20 -> 4923852.6 | Q21: =MIN(IF(S21>O21,0,MIN(P21,O21-S21))+IF(P21>0,MIN(AA21,P21)),P21) -> 92817.281 | R21: =P21*($G$10/12) -> 20516.052 | S21: =S20-T20 -> 73361506 | T21: =MIN(IF(S21>O21,O21,S21)+IF(S21>0,AM21,0),S21) -> 483858.04 | U21: =S21*($G$4/12) -> 305672.94 | V21: =V20-W20 -> 14000000 | W21: =IF(T21+P21<=O21+AM21+AA21,MIN(V21,O21-Q21+AA21-T21+AM21),0) -> 0 | X21: =V21*($G$5/12) -> 58333.333 | Y21: =IF(V20>O20,(IF(V20>AA20+O20+AM20,Y20+AA20,Y20+AA20-((AA20+O20+AM20)-V20))),Y20-Z20) -> 22276147 | Z21: =MIN(IF(V21>O21,0,MIN(Y21,O21-V21))+IF(AM20>V20,AM20,0),Y21) -> 0 | AA21: =Y21*($G$8/12) -> 92817.281 | AB21: =AB20-AC20 -> 20000000 | AC21: =MIN(IF(Y21>O21,0,MIN(AB21,O21+AM21-Y21))) -> 0 | AD21: =AB21*($G$9/12) -> 83333.333 | AE21: =AE20-AF20 -> 32219489 | AF21: =IF(AE21>N21,N21,AE21) -> 111193.95 | AG21: =AE21*($G$3/12) -> 134247.87 | AH21: =AH20-AI20 -> 13950000 | AI21: =IF(AE21>N21,0,MIN(AH21,N21-AE21)) -> 0 | AJ21: =AH21*($G$6/12) -> 58125 | AK21: =IF(AL20=0,AK20+AM20,AK20-AL20) -> 24301252 | AL21: =MIN(IF(AB21>0,IF(AB21>O21,0,MIN(AK21,O21-AB21)),O21),AK21) -> 0 | AM21: =AK21*($G$7/12) -> 101255.22 | AN21: =FORECAST(B21, $AM$2:$AY$2,$AM$1:$AY$1) -> 0.022252065 | AO21: =Q21+R21 -> 113333.33 | AP21: =Q21*B21 -> 371269.12 | AQ21: =1/(1+(AN21+$CB$5)/12)^$B21 -> 0.98428599 | AR21: =T21+U21 -> 789530.98 | AS21: =T21*A21 -> 4354722.3 | AT21: =1/(1+(AN21+$BV$5)/12)^$B21 -> 0.98540075 | AU21: =W21+X21 -> 58333.333 | AV21: =W21*A21 -> 0 | AW21: =1/(1+(AN21+$BW$5)/12)^$B21 -> 0.98592983 | AX21: =IF(Y22>Y21,0,Z21+AA21) -> 0 | AY21: =A21*Z21 -> 0 | AZ21: =1/(1+(AN21+$BZ$5)/12)^$B21 -> 0.98966871 | BA21: =AC21+AD21 -> 83333.333 | BB21: =AC21*A21 -> 0 | BC21: =1/(1+(AN21+$CA$5)/12)^$B21 -> 0.98743237 | BD21: =AF21+AG21 -> 245441.82 | BE21: =AF21*A21 -> 1000745.5 | BF21: =1/(1+(AN21+$BU$5)/12)^$B21 -> 0.98646553 | BG21: =AI21+AJ21 -> 58125 | BH21: =AI21*A21 -> 0 | BI21: =1/(1+(AN21+$BX$5)/12)^$B21 -> 0.98816052 | BJ21: =IF(AK22>AK21,0,AL21+AM21) -> 0 | BK21: =A21*AL21 -> 0 | BL21: =1/(1+(AN21+$BY$5)/12)^$B21 -> 0.98898476 | BM21: =AO21+AR21+AU21+AX21+BA21+BD21+BG21+BJ21 -> 1348097.8 | BN21: =M21*B21 -> 1975187.1 | BO21: =1/(1+(AN21+$CC$5)/12)^$B21 -> 0.98718957 | BT21: Original Yield Curve (Normal) | BU21: =BU14 -> 0.023516729 | BV21: =BV14 -> 0.025345018 | BW21: =BW14 -> 0.023591729 | BX21: =BX14 -> 0.017086336 | BY21: =BY14 -> 0.014918714 | BZ21: =BZ14 -> 0.00807609 | CA21: =CA14 -> 0.020458943 | CB21: =CB14 -> 0.025358489 | CC21: =CC14 -> 0.020014572
A22: 10 | B22: 5 | C22: =P22+S22+V22+Y22+AB22+AE22+AH22+AK22 -> 2.0453845e+08 | D22: =C22-E22 -> 0 | E22: =E21-H21-K21 -> 2.0453845e+08 | F22: =PMT($K$13/12,$K$12-B22+1,-E22,0) -> 1444804.7 | G22: =E22*$K$13/12 -> 948717.51 | H22: =F22-G22 -> 496087.16 | I22: =IF(A22<=(30-(240-$K$8)),((A22+(240-$K$7))/30)*$K$6,$K$6)*($K$5/100) -> 0 | J22: =1-(1-I22)^(1/12) -> 0 | K22: =(E22-H22)*J22 -> 0 | L22: =K22+H22+G22 -> 1444804.7 | M22: =L22-G22 -> 496087.16 | N22: =M22*$M$4 -> 111709.7 | O22: =M22*$M$5 -> 384377.46 | P22: =P21-Q21 -> 4831035.3 | Q22: =MIN(IF(S22>O22,0,MIN(P22,O22-S22))+IF(P22>0,MIN(AA22,P22)),P22) -> 93204.02 | R22: =P22*($G$10/12) -> 20129.314 | S22: =S21-T21 -> 72877648 | T22: =MIN(IF(S22>O22,O22,S22)+IF(S22>0,AM22,0),S22) -> 486054.57 | U22: =S22*($G$4/12) -> 303656.87 | V22: =V21-W21 -> 14000000 | W22: =IF(T22+P22<=O22+AM22+AA22,MIN(V22,O22-Q22+AA22-T22+AM22),0) -> 0 | X22: =V22*($G$5/12) -> 58333.333 | Y22: =IF(V21>O21,(IF(V21>AA21+O21+AM21,Y21+AA21,Y21+AA21-((AA21+O21+AM21)-V21))),Y21-Z21) -> 22368965 | Z22: =MIN(IF(V22>O22,0,MIN(Y22,O22-V22))+IF(AM21>V21,AM21,0),Y22) -> 0 | AA22: =Y22*($G$8/12) -> 93204.02 | AB22: =AB21-AC21 -> 20000000 | AC22: =MIN(IF(Y22>O22,0,MIN(AB22,O22+AM22-Y22))) -> 0 | AD22: =AB22*($G$9/12) -> 83333.333 | AE22: =AE21-AF21 -> 32108295 | AF22: =IF(AE22>N22,N22,AE22) -> 111709.7 | AG22: =AE22*($G$3/12) -> 133784.56 | AH22: =AH21-AI21 -> 13950000 | AI22: =IF(AE22>N22,0,MIN(AH22,N22-AE22)) -> 0 | AJ22: =AH22*($G$6/12) -> 58125 | AK22: =IF(AL21=0,AK21+AM21,AK21-AL21) -> 24402507 | AL22: =MIN(IF(AB22>0,IF(AB22>O22,0,MIN(AK22,O22-AB22)),O22),AK22) -> 0 | AM22: =AK22*($G$7/12) -> 101677.11 | AN22: =FORECAST(B22, $AM$2:$AY$2,$AM$1:$AY$1) -> 0.022332473 | AO22: =Q22+R22 -> 113333.33 | AP22: =Q22*B22 -> 466020.1 | AQ22: =1/(1+(AN22+$CB$5)/12)^$B22 -> 0.98036351 | AR22: =T22+U22 -> 789711.44 | AS22: =T22*A22 -> 4860545.7 | AT22: =1/(1+(AN22+$BV$5)/12)^$B22 -> 0.98175159 | AU22: =W22+X22 -> 58333.333 | AV22: =W22*A22 -> 0 | AW22: =1/(1+(AN22+$BW$5)/12)^$B22 -> 0.98241054 | AX22: =IF(Y23>Y22,0,Z22+AA22) -> 0 | AY22: =A22*Z22 -> 0 | AZ22: =1/(1+(AN22+$BZ$5)/12)^$B22 -> 0.98706963 | BA22: =AC22+AD22 -> 83333.333 | BB22: =AC22*A22 -> 0 | BC22: =1/(1+(AN22+$CA$5)/12)^$B22 -> 0.98428235 | BD22: =AF22+AG22 -> 245494.26 | BE22: =AF22*A22 -> 1117097 | BF22: =1/(1+(AN22+$BU$5)/12)^$B22 -> 0.98307781 | BG22: =AI22+AJ22 -> 58125 | BH22: =AI22*A22 -> 0 | BI22: =1/(1+(AN22+$BX$5)/12)^$B22 -> 0.98518971 | BJ22: =IF(AK23>AK22,0,AL22+AM22) -> 0 | BK22: =A22*AL22 -> 0 | BL22: =1/(1+(AN22+$BY$5)/12)^$B22 -> 0.98621702 | BM22: =AO22+AR22+AU22+AX22+BA22+BD22+BG22+BJ22 -> 1348330.7 | BN22: =M22*B22 -> 2480435.8 | BO22: =1/(1+(AN22+$CC$5)/12)^$B22 -> 0.98397983 | BT22: Inverse Yield Curve | BU22: ='Inverse Yield Curve'!BU5 -> 0.018578899 | BV22: ='Inverse Yield Curve'!BV5 -> 0.018946407 | BW22: ='Inverse Yield Curve'!BW5 -> 0.018595214 | BX22: ='Inverse Yield Curve'!BX5 -> 0.017279956 | BY22: ='Inverse Yield Curve'!BY5 -> 0.016580002 | BZ22: ='Inverse Yield Curve'!BZ5 -> 0.0044188321 | CA22: ='Inverse Yield Curve'!CA5 -> 0.017966763 | CB22: ='Inverse Yield Curve'!CB5 -> 0.018949117 | CC22: ='Inverse Yield Curve'!CC5 -> 0.017784164
A23: 11 | B23: 6 | C23: =P23+S23+V23+Y23+AB23+AE23+AH23+AK23 -> 2.0404236e+08 | D23: =C23-E23 -> 0 | E23: =E22-H22-K22 -> 2.0404236e+08 | F23: =PMT($K$13/12,$K$12-B23+1,-E23,0) -> 1444804.7 | G23: =E23*$K$13/12 -> 946416.49 | H23: =F23-G23 -> 498388.18 | I23: =IF(A23<=(30-(240-$K$8)),((A23+(240-$K$7))/30)*$K$6,$K$6)*($K$5/100) -> 0 | J23: =1-(1-I23)^(1/12) -> 0 | K23: =(E23-H23)*J23 -> 0 | L23: =K23+H23+G23 -> 1444804.7 | M23: =L23-G23 -> 498388.18 | N23: =M23*$M$4 -> 112227.85 | O23: =M23*$M$5 -> 386160.33 | P23: =P22-Q22 -> 4737831.3 | Q23: =MIN(IF(S23>O23,0,MIN(P23,O23-S23))+IF(P23>0,MIN(AA23,P23)),P23) -> 93592.37 | R23: =P23*($G$10/12) -> 19740.964 | S23: =S22-T22 -> 72391593 | T23: =MIN(IF(S23>O23,O23,S23)+IF(S23>0,AM23,0),S23) -> 488261.1 | U23: =S23*($G$4/12) -> 301631.64 | V23: =V22-W22 -> 14000000 | W23: =IF(T23+P23<=O23+AM23+AA23,MIN(V23,O23-Q23+AA23-T23+AM23),0) -> 0 | X23: =V23*($G$5/12) -> 58333.333 | Y23: =IF(V22>O22,(IF(V22>AA22+O22+AM22,Y22+AA22,Y22+AA22-((AA22+O22+AM22)-V22))),Y22-Z22) -> 22462169 | Z23: =MIN(IF(V23>O23,0,MIN(Y23,O23-V23))+IF(AM22>V22,AM22,0),Y23) -> 0 | AA23: =Y23*($G$8/12) -> 93592.37 | AB23: =AB22-AC22 -> 20000000 | AC23: =MIN(IF(Y23>O23,0,MIN(AB23,O23+AM23-Y23))) -> 0 | AD23: =AB23*($G$9/12) -> 83333.333 | AE23: =AE22-AF22 -> 31996585 | AF23: =IF(AE23>N23,N23,AE23) -> 112227.85 | AG23: =AE23*($G$3/12) -> 133319.11 | AH23: =AH22-AI22 -> 13950000 | AI23: =IF(AE23>N23,0,MIN(AH23,N23-AE23)) -> 0 | AJ23: =AH23*($G$6/12) -> 58125 | AK23: =IF(AL22=0,AK22+AM22,AK22-AL22) -> 24504184 | AL23: =MIN(IF(AB23>0,IF(AB23>O23,0,MIN(AK23,O23-AB23)),O23),AK23) -> 0 | AM23: =AK23*($G$7/12) -> 102100.77 | AN23: =FORECAST(B23, $AM$2:$AY$2,$AM$1:$AY$1) -> 0.02241288 | AO23: =Q23+R23 -> 113333.33 | AP23: =Q23*B23 -> 561554.22 | AQ23: =1/(1+(AN23+$CB$5)/12)^$B23 -> 0.97644362 | AR23: =T23+U23 -> 789892.74 | AS23: =T23*A23 -> 5370872.1 | AT23: =1/(1+(AN23+$BV$5)/12)^$B23 -> 0.97810289 | AU23: =W23+X23 -> 58333.333 | AV23: =W23*A23 -> 0 | AW23: =1/(1+(AN23+$BW$5)/12)^$B23 -> 0.97889073 | AX23: =IF(Y24>Y23,0,Z23+AA23) -> 0 | AY23: =A23*Z23 -> 0 | AZ23: =1/(1+(AN23+$BZ$5)/12)^$B23 -> 0.98446421 | BA23: =AC23+AD23 -> 83333.333 | BB23: =AC23*A23 -> 0 | BC23: =1/(1+(AN23+$CA$5)/12)^$B23 -> 0.98112926 | BD23: =AF23+AG23 -> 245546.95 | BE23: =AF23*A23 -> 1234506.3 | BF23: =1/(1+(AN23+$BU$5)/12)^$B23 -> 0.97968864 | BG23: =AI23+AJ23 -> 58125 | BH23: =AI23*A23 -> 0 | BI23: =1/(1+(AN23+$BX$5)/12)^$B23 -> 0.9822147 | BJ23: =IF(AK24>AK23,0,AL23+AM23) -> 0 | BK23: =A23*AL23 -> 0 | BL23: =1/(1+(AN23+$BY$5)/12)^$B23 -> 0.98344387 | BM23: =AO23+AR23+AU23+AX23+BA23+BD23+BG23+BJ23 -> 1348564.7 | BN23: =M23*B23 -> 2990329.1 | BO23: =1/(1+(AN23+$CC$5)/12)^$B23 -> 0.98076742 | BT23: Flatter Yield Curve | BU23: ='Flatter Yield Curve'!BU5 -> 0.024528739 | BV23: ='Flatter Yield Curve'!BV5 -> 0.025417296 | BW23: ='Flatter Yield Curve'!BW5 -> 0.02456712 | BX23: ='Flatter Yield Curve'!BX5 -> 0.021393673 | BY23: ='Flatter Yield Curve'!BY5 -> 0.02017482 | BZ23: ='Flatter Yield Curve'!BZ5 -> 0.0099139265 | CA23: ='Flatter Yield Curve'!CA5 -> 0.023046558 | CB23: ='Flatter Yield Curve'!CB5 -> 0.025423847 | CC23: ='Flatter Yield Curve'!CC5 -> 0.022756985
A24: 12 | B24: 7 | C24: =P24+S24+V24+Y24+AB24+AE24+AH24+AK24 -> 2.0354397e+08 | D24: =C24-E24 -> 0 | E24: =E23-H23-K23 -> 2.0354397e+08 | F24: =PMT($K$13/12,$K$12-B24+1,-E24,0) -> 1444804.7 | G24: =E24*$K$13/12 -> 944104.8 | H24: =F24-G24 -> 500699.87 | I24: =IF(A24<=(30-(240-$K$8)),((A24+(240-$K$7))/30)*$K$6,$K$6)*($K$5/100) -> 0 | J24: =1-(1-I24)^(1/12) -> 0 | K24: =(E24-H24)*J24 -> 0 | L24: =K24+H24+G24 -> 1444804.7 | M24: =L24-G24 -> 500699.87 | N24: =M24*$M$4 -> 112748.4 | O24: =M24*$M$5 -> 387951.47 | P24: =P23-Q23 -> 4644238.9 | Q24: =MIN(IF(S24>O24,0,MIN(P24,O24-S24))+IF(P24>0,MIN(AA24,P24)),P24) -> 93982.338 | R24: =P24*($G$10/12) -> 19350.995 | S24: =S23-T23 -> 71903332 | T24: =MIN(IF(S24>O24,O24,S24)+IF(S24>0,AM24,0),S24) -> 490477.66 | U24: =S24*($G$4/12) -> 299597.22 | V24: =V23-W23 -> 14000000 | W24: =IF(T24+P24<=O24+AM24+AA24,MIN(V24,O24-Q24+AA24-T24+AM24),0) -> 0 | X24: =V24*($G$5/12) -> 58333.333 | Y24: =IF(V23>O23,(IF(V23>AA23+O23+AM23,Y23+AA23,Y23+AA23-((AA23+O23+AM23)-V23))),Y23-Z23) -> 22555761 | Z24: =MIN(IF(V24>O24,0,MIN(Y24,O24-V24))+IF(AM23>V23,AM23,0),Y24) -> 0 | AA24: =Y24*($G$8/12) -> 93982.338 | AB24: =AB23-AC23 -> 20000000 | AC24: =MIN(IF(Y24>O24,0,MIN(AB24,O24+AM24-Y24))) -> 0 | AD24: =AB24*($G$9/12) -> 83333.333 | AE24: =AE23-AF23 -> 31884357 | AF24: =IF(AE24>N24,N24,AE24) -> 112748.4 | AG24: =AE24*($G$3/12) -> 132851.49 | AH24: =AH23-AI23 -> 13950000 | AI24: =IF(AE24>N24,0,MIN(AH24,N24-AE24)) -> 0 | AJ24: =AH24*($G$6/12) -> 58125 | AK24: =IF(AL23=0,AK23+AM23,AK23-AL23) -> 24606285 | AL24: =MIN(IF(AB24>0,IF(AB24>O24,0,MIN(AK24,O24-AB24)),O24),AK24) -> 0 | AM24: =AK24*($G$7/12) -> 102526.19 | AN24: =FORECAST(B24, $AM$2:$AY$2,$AM$1:$AY$1) -> 0.022493287 | AO24: =Q24+R24 -> 113333.33 | AP24: =Q24*B24 -> 657876.37 | AQ24: =1/(1+(AN24+$CB$5)/12)^$B24 -> 0.97252643 | AR24: =T24+U24 -> 790074.88 | AS24: =T24*A24 -> 5885731.9 | AT24: =1/(1+(AN24+$BV$5)/12)^$B24 -> 0.97445473 | AU24: =W24+X24 -> 58333.333 | AV24: =W24*A24 -> 0 | AW24: =1/(1+(AN24+$BW$5)/12)^$B24 -> 0.97537051 | AX24: =IF(Y25>Y24,0,Z24+AA24) -> 0 | AY24: =A24*Z24 -> 0 | AZ24: =1/(1+(AN24+$BZ$5)/12)^$B24 -> 0.98185254 | BA24: =AC24+AD24 -> 83333.333 | BB24: =AC24*A24 -> 0 | BC24: =1/(1+(AN24+$CA$5)/12)^$B24 -> 0.97797322 | BD24: =AF24+AG24 -> 245599.89 | BE24: =AF24*A24 -> 1352980.8 | BF24: =1/(1+(AN24+$BU$5)/12)^$B24 -> 0.97629812 | BG24: =AI24+AJ24 -> 58125 | BH24: =AI24*A24 -> 0 | BI24: =1/(1+(AN24+$BX$5)/12)^$B24 -> 0.9792356 | BJ24: =IF(AK25>AK24,0,AL24+AM24) -> 0 | BK24: =A24*AL24 -> 0 | BL24: =1/(1+(AN24+$BY$5)/12)^$B24 -> 0.98066542 | BM24: =AO24+AR24+AU24+AX24+BA24+BD24+BG24+BJ24 -> 1348799.8 | BN24: =M24*B24 -> 3504899.1 | BO24: =1/(1+(AN24+$CC$5)/12)^$B24 -> 0.97755244
A25: 13 | B25: 8 | C25: =P25+S25+V25+Y25+AB25+AE25+AH25+AK25 -> 2.0304327e+08 | D25: =C25-E25 -> 0 | E25: =E24-H24-K24 -> 2.0304327e+08 | F25: =PMT($K$13/12,$K$12-B25+1,-E25,0) -> 1444804.7 | G25: =E25*$K$13/12 -> 941782.39 | H25: =F25-G25 -> 503022.28 | I25: =IF(A25<=(30-(240-$K$8)),((A25+(240-$K$7))/30)*$K$6,$K$6)*($K$5/100) -> 0 | J25: =1-(1-I25)^(1/12) -> 0 | K25: =(E25-H25)*J25 -> 0 | L25: =K25+H25+G25 -> 1444804.7 | M25: =L25-G25 -> 503022.28 | N25: =M25*$M$4 -> 113271.36 | O25: =M25*$M$5 -> 389750.92 | P25: =P24-Q24 -> 4550256.6 | Q25: =MIN(IF(S25>O25,0,MIN(P25,O25-S25))+IF(P25>0,MIN(AA25,P25)),P25) -> 94373.931 | R25: =P25*($G$10/12) -> 18959.402 | S25: =S24-T24 -> 71412855 | T25: =MIN(IF(S25>O25,O25,S25)+IF(S25>0,AM25,0),S25) -> 492704.3 | U25: =S25*($G$4/12) -> 297553.56 | V25: =V24-W24 -> 14000000 | W25: =IF(T25+P25<=O25+AM25+AA25,MIN(V25,O25-Q25+AA25-T25+AM25),0) -> 0 | X25: =V25*($G$5/12) -> 58333.333 | Y25: =IF(V24>O24,(IF(V24>AA24+O24+AM24,Y24+AA24,Y24+AA24-((AA24+O24+AM24)-V24))),Y24-Z24) -> 22649743 | Z25: =MIN(IF(V25>O25,0,MIN(Y25,O25-V25))+IF(AM24>V24,AM24,0),Y25) -> 0 | AA25: =Y25*($G$8/12) -> 94373.931 | AB25: =AB24-AC24 -> 20000000 | AC25: =MIN(IF(Y25>O25,0,MIN(AB25,O25+AM25-Y25))) -> 0 | AD25: =AB25*($G$9/12) -> 83333.333 | AE25: =AE24-AF24 -> 31771609 | AF25: =IF(AE25>N25,N25,AE25) -> 113271.36 | AG25: =AE25*($G$3/12) -> 132381.7 | AH25: =AH24-AI24 -> 13950000 | AI25: =IF(AE25>N25,0,MIN(AH25,N25-AE25)) -> 0 | AJ25: =AH25*($G$6/12) -> 58125 | AK25: =IF(AL24=0,AK24+AM24,AK24-AL24) -> 24708811 | AL25: =MIN(IF(AB25>0,IF(AB25>O25,0,MIN(AK25,O25-AB25)),O25),AK25) -> 0 | AM25: =AK25*($G$7/12) -> 102953.38 | AN25: =FORECAST(B25, $AM$2:$AY$2,$AM$1:$AY$1) -> 0.022573694 | AO25: =Q25+R25 -> 113333.33 | AP25: =Q25*B25 -> 754991.45 | AQ25: =1/(1+(AN25+$CB$5)/12)^$B25 -> 0.96861202 | AR25: =T25+U25 -> 790257.86 | AS25: =T25*A25 -> 6405155.9 | AT25: =1/(1+(AN25+$BV$5)/12)^$B25 -> 0.97080722 | AU25: =W25+X25 -> 58333.333 | AV25: =W25*A25 -> 0 | AW25: =1/(1+(AN25+$BW$5)/12)^$B25 -> 0.97184997 | AX25: =IF(Y26>Y25,0,Z25+AA25) -> 0 | AY25: =A25*Z25 -> 0 | AZ25: =1/(1+(AN25+$BZ$5)/12)^$B25 -> 0.97923472 | BA25: =AC25+AD25 -> 83333.333 | BB25: =AC25*A25 -> 0 | BC25: =1/(1+(AN25+$CA$5)/12)^$B25 -> 0.9748143 | BD25: =AF25+AG25 -> 245653.07 | BE25: =AF25*A25 -> 1472527.7 | BF25: =1/(1+(AN25+$BU$5)/12)^$B25 -> 0.97290633 | BG25: =AI25+AJ25 -> 58125 | BH25: =AI25*A25 -> 0 | BI25: =1/(1+(AN25+$BX$5)/12)^$B25 -> 0.97625248 | BJ25: =IF(AK26>AK25,0,AL25+AM25) -> 0 | BK25: =A25*AL25 -> 0 | BL25: =1/(1+(AN25+$BY$5)/12)^$B25 -> 0.97788175 | BM25: =AO25+AR25+AU25+AX25+BA25+BD25+BG25+BJ25 -> 1349035.9 | BN25: =M25*B25 -> 4024178.3 | BO25: =1/(1+(AN25+$CC$5)/12)^$B25 -> 0.97433499
A26: 14 | B26: 9 | C26: =P26+S26+V26+Y26+AB26+AE26+AH26+AK26 -> 2.0254025e+08 | D26: =C26-E26 -> 0 | E26: =E25-H25-K25 -> 2.0254025e+08 | F26: =PMT($K$13/12,$K$12-B26+1,-E26,0) -> 1444804.7 | G26: =E26*$K$13/12 -> 939449.2 | H26: =F26-G26 -> 505355.47 | I26: =IF(A26<=(30-(240-$K$8)),((A26+(240-$K$7))/30)*$K$6,$K$6)*($K$5/100) -> 0 | J26: =1-(1-I26)^(1/12) -> 0 | K26: =(E26-H26)*J26 -> 0 | L26: =K26+H26+G26 -> 1444804.7 | M26: =L26-G26 -> 505355.47 | N26: =M26*$M$4 -> 113796.75 | O26: =M26*$M$5 -> 391558.72 | P26: =P25-Q25 -> 4455882.6 | Q26: =MIN(IF(S26>O26,0,MIN(P26,O26-S26))+IF(P26>0,MIN(AA26,P26)),P26) -> 94767.156 | R26: =P26*($G$10/12) -> 18566.178 | S26: =S25-T25 -> 70920150 | T26: =MIN(IF(S26>O26,O26,S26)+IF(S26>0,AM26,0),S26) -> 494941.07 | U26: =S26*($G$4/12) -> 295500.63 | V26: =V25-W25 -> 14000000 | W26: =IF(T26+P26<=O26+AM26+AA26,MIN(V26,O26-Q26+AA26-T26+AM26),0) -> 0 | X26: =V26*($G$5/12) -> 58333.333 | Y26: =IF(V25>O25,(IF(V25>AA25+O25+AM25,Y25+AA25,Y25+AA25-((AA25+O25+AM25)-V25))),Y25-Z25) -> 22744117 | Z26: =MIN(IF(V26>O26,0,MIN(Y26,O26-V26))+IF(AM25>V25,AM25,0),Y26) -> 0 | AA26: =Y26*($G$8/12) -> 94767.156 | AB26: =AB25-AC25 -> 20000000 | AC26: =MIN(IF(Y26>O26,0,MIN(AB26,O26+AM26-Y26))) -> 0 | AD26: =AB26*($G$9/12) -> 83333.333 | AE26: =AE25-AF25 -> 31658338 | AF26: =IF(AE26>N26,N26,AE26) -> 113796.75 | AG26: =AE26*($G$3/12) -> 131909.74 | AH26: =AH25-AI25 -> 13950000 | AI26: =IF(AE26>N26,0,MIN(AH26,N26-AE26)) -> 0 | AJ26: =AH26*($G$6/12) -> 58125 | AK26: =IF(AL25=0,AK25+AM25,AK25-AL25) -> 24811764 | AL26: =MIN(IF(AB26>0,IF(AB26>O26,0,MIN(AK26,O26-AB26)),O26),AK26) -> 0 | AM26: =AK26*($G$7/12) -> 103382.35 | AN26: =FORECAST(B26, $AM$2:$AY$2,$AM$1:$AY$1) -> 0.022654101 | AO26: =Q26+R26 -> 113333.33 | AP26: =Q26*B26 -> 852904.4 | AQ26: =1/(1+(AN26+$CB$5)/12)^$B26 -> 0.96470049 | AR26: =T26+U26 -> 790441.69 | AS26: =T26*A26 -> 6929175 | AT26: =1/(1+(AN26+$BV$5)/12)^$B26 -> 0.96716045 | AU26: =W26+X26 -> 58333.333 | AV26: =W26*A26 -> 0 | AW26: =1/(1+(AN26+$BW$5)/12)^$B26 -> 0.96832921 | AX26: =IF(Y27>Y26,0,Z26+AA26) -> 0 | AY26: =A26*Z26 -> 0 | AZ26: =1/(1+(AN26+$BZ$5)/12)^$B26 -> 0.97661082 | BA26: =AC26+AD26 -> 83333.333 | BB26: =AC26*A26 -> 0 | BC26: =1/(1+(AN26+$CA$5)/12)^$B26 -> 0.97165261 | BD26: =AF26+AG26 -> 245706.49 | BE26: =AF26*A26 -> 1593154.5 | BF26: =1/(1+(AN26+$BU$5)/12)^$B26 -> 0.96951338 | BG26: =AI26+AJ26 -> 58125 | BH26: =AI26*A26 -> 0 | BI26: =1/(1+(AN26+$BX$5)/12)^$B26 -> 0.97326546 | BJ26: =IF(AK27>AK26,0,AL26+AM26) -> 0 | BK26: =A26*AL26 -> 0 | BL26: =1/(1+(AN26+$BY$5)/12)^$B26 -> 0.97509295 | BM26: =AO26+AR26+AU26+AX26+BA26+BD26+BG26+BJ26 -> 1349273.2 | BN26: =M26*B26 -> 4548199.2 | BO26: =1/(1+(AN26+$CC$5)/12)^$B26 -> 0.97111515
A27: 15 | B27: 10 | C27: =P27+S27+V27+Y27+AB27+AE27+AH27+AK27 -> 2.020349e+08 | D27: =C27-E27 -> 0 | E27: =E26-H26-K26 -> 2.020349e+08 | F27: =PMT($K$13/12,$K$12-B27+1,-E27,0) -> 1444804.7 | G27: =E27*$K$13/12 -> 937105.2 | H27: =F27-G27 -> 507699.48 | I27: =IF(A27<=(30-(240-$K$8)),((A27+(240-$K$7))/30)*$K$6,$K$6)*($K$5/100) -> 0 | J27: =1-(1-I27)^(1/12) -> 0 | K27: =(E27-H27)*J27 -> 0 | L27: =K27+H27+G27 -> 1444804.7 | M27: =L27-G27 -> 507699.48 | N27: =M27*$M$4 -> 114324.58 | O27: =M27*$M$5 -> 393374.9 | P27: =P26-Q26 -> 4361115.5 | Q27: =MIN(IF(S27>O27,0,MIN(P27,O27-S27))+IF(P27>0,MIN(AA27,P27)),P27) -> 95162.019 | R27: =P27*($G$10/12) -> 18171.315 | S27: =S26-T26 -> 70425209 | T27: =MIN(IF(S27>O27,O27,S27)+IF(S27>0,AM27,0),S27) -> 497188.01 | U27: =S27*($G$4/12) -> 293438.37 | V27: =V26-W26 -> 14000000 | W27: =IF(T27+P27<=O27+AM27+AA27,MIN(V27,O27-Q27+AA27-T27+AM27),0) -> 0 | X27: =V27*($G$5/12) -> 58333.333 | Y27: =IF(V26>O26,(IF(V26>AA26+O26+AM26,Y26+AA26,Y26+AA26-((AA26+O26+AM26)-V26))),Y26-Z26) -> 22838885 | Z27: =MIN(IF(V27>O27,0,MIN(Y27,O27-V27))+IF(AM26>V26,AM26,0),Y27) -> 0 | AA27: =Y27*($G$8/12) -> 95162.019 | AB27: =AB26-AC26 -> 20000000 | AC27: =MIN(IF(Y27>O27,0,MIN(AB27,O27+AM27-Y27))) -> 0 | AD27: =AB27*($G$9/12) -> 83333.333 | AE27: =AE26-AF26 -> 31544541 | AF27: =IF(AE27>N27,N27,AE27) -> 114324.58 | AG27: =AE27*($G$3/12) -> 131435.59 | AH27: =AH26-AI26 -> 13950000 | AI27: =IF(AE27>N27,0,MIN(AH27,N27-AE27)) -> 0 | AJ27: =AH27*($G$6/12) -> 58125 | AK27: =IF(AL26=0,AK26+AM26,AK26-AL26) -> 24915147 | AL27: =MIN(IF(AB27>0,IF(AB27>O27,0,MIN(AK27,O27-AB27)),O27),AK27) -> 0 | AM27: =AK27*($G$7/12) -> 103813.11 | AN27: =FORECAST(B27, $AM$2:$AY$2,$AM$1:$AY$1) -> 0.022734509 | AO27: =Q27+R27 -> 113333.33 | AP27: =Q27*B27 -> 951620.19 | AQ27: =1/(1+(AN27+$CB$5)/12)^$B27 -> 0.96079194 | AR27: =T27+U27 -> 790626.38 | AS27: =T27*A27 -> 7457820.1 | AT27: =1/(1+(AN27+$BV$5)/12)^$B27 -> 0.96351452 | AU27: =W27+X27 -> 58333.333 | AV27: =W27*A27 -> 0 | AW27: =1/(1+(AN27+$BW$5)/12)^$B27 -> 0.96480832 | AX27: =IF(Y28>Y27,0,Z27+AA27) -> 0 | AY27: =A27*Z27 -> 0 | AZ27: =1/(1+(AN27+$BZ$5)/12)^$B27 -> 0.97398093 | BA27: =AC27+AD27 -> 83333.333 | BB27: =AC27*A27 -> 0 | BC27: =1/(1+(AN27+$CA$5)/12)^$B27 -> 0.96848824 | BD27: =AF27+AG27 -> 245760.17 | BE27: =AF27*A27 -> 1714868.7 | BF27: =1/(1+(AN27+$BU$5)/12)^$B27 -> 0.96611936 | BG27: =AI27+AJ27 -> 58125 | BH27: =AI27*A27 -> 0 | BI27: =1/(1+(AN27+$BX$5)/12)^$B27 -> 0.9702746 | BJ27: =IF(AK28>AK27,0,AL27+AM27) -> 0 | BK27: =A27*AL27 -> 0 | BL27: =1/(1+(AN27+$BY$5)/12)^$B27 -> 0.97229911 | BM27: =AO27+AR27+AU27+AX27+BA27+BD27+BG27+BJ27 -> 1349511.5 | BN27: =M27*B27 -> 5076994.8 | BO27: =1/(1+(AN27+$CC$5)/12)^$B27 -> 0.96789303
A28: 16 | B28: 11 | C28: =P28+S28+V28+Y28+AB28+AE28+AH28+AK28 -> 2.015272e+08 | D28: =C28-E28 -> 0 | E28: =E27-H27-K27 -> 2.015272e+08 | F28: =PMT($K$13/12,$K$12-B28+1,-E28,0) -> 1444804.7 | G28: =E28*$K$13/12 -> 934750.32 | H28: =F28-G28 -> 510054.35 | I28: =IF(A28<=(30-(240-$K$8)),((A28+(240-$K$7))/30)*$K$6,$K$6)*($K$5/100) -> 0 | J28: =1-(1-I28)^(1/12) -> 0 | K28: =(E28-H28)*J28 -> 0 | L28: =K28+H28+G28 -> 1444804.7 | M28: =L28-G28 -> 510054.35 | N28: =M28*$M$4 -> 114854.85 | O28: =M28*$M$5 -> 395199.5 | P28: =P27-Q27 -> 4265953.5 | Q28: =MIN(IF(S28>O28,0,MIN(P28,O28-S28))+IF(P28>0,MIN(AA28,P28)),P28) -> 95558.527 | R28: =P28*($G$10/12) -> 17774.806 | S28: =S27-T27 -> 69928021 | T28: =MIN(IF(S28>O28,O28,S28)+IF(S28>0,AM28,0),S28) -> 499445.17 | U28: =S28*($G$4/12) -> 291366.75 | V28: =V27-W27 -> 14000000 | W28: =IF(T28+P28<=O28+AM28+AA28,MIN(V28,O28-Q28+AA28-T28+AM28),0) -> 0 | X28: =V28*($G$5/12) -> 58333.333 | Y28: =IF(V27>O27,(IF(V27>AA27+O27+AM27,Y27+AA27,Y27+AA27-((AA27+O27+AM27)-V27))),Y27-Z27) -> 22934047 | Z28: =MIN(IF(V28>O28,0,MIN(Y28,O28-V28))+IF(AM27>V27,AM27,0),Y28) -> 0 | AA28: =Y28*($G$8/12) -> 95558.527 | AB28: =AB27-AC27 -> 20000000 | AC28: =MIN(IF(Y28>O28,0,MIN(AB28,O28+AM28-Y28))) -> 0 | AD28: =AB28*($G$9/12) -> 83333.333 | AE28: =AE27-AF27 -> 31430216 | AF28: =IF(AE28>N28,N28,AE28) -> 114854.85 | AG28: =AE28*($G$3/12) -> 130959.23 | AH28: =AH27-AI27 -> 13950000 | AI28: =IF(AE28>N28,0,MIN(AH28,N28-AE28)) -> 0 | AJ28: =AH28*($G$6/12) -> 58125 | AK28: =IF(AL27=0,AK27+AM27,AK27-AL27) -> 25018960 | AL28: =MIN(IF(AB28>0,IF(AB28>O28,0,MIN(AK28,O28-AB28)),O28),AK28) -> 0 | AM28: =AK28*($G$7/12) -> 104245.67 | AN28: =FORECAST(B28, $AM$2:$AY$2,$AM$1:$AY$1) -> 0.022814916 | AO28: =Q28+R28 -> 113333.33 | AP28: =Q28*B28 -> 1051143.8 | AQ28: =1/(1+(AN28+$CB$5)/12)^$B28 -> 0.95688644 | AR28: =T28+U28 -> 790811.92 | AS28: =T28*A28 -> 7991122.7 | AT28: =1/(1+(AN28+$BV$5)/12)^$B28 -> 0.95986951 | AU28: =W28+X28 -> 58333.333 | AV28: =W28*A28 -> 0 | AW28: =1/(1+(AN28+$BW$5)/12)^$B28 -> 0.9612874 | AX28: =IF(Y29>Y28,0,Z28+AA28) -> 0 | AY28: =A28*Z28 -> 0 | AZ28: =1/(1+(AN28+$BZ$5)/12)^$B28 -> 0.97134515 | BA28: =AC28+AD28 -> 83333.333 | BB28: =AC28*A28 -> 0 | BC28: =1/(1+(AN28+$CA$5)/12)^$B28 -> 0.96532128 | BD28: =AF28+AG28 -> 245814.09 | BE28: =AF28*A28 -> 1837677.7 | BF28: =1/(1+(AN28+$BU$5)/12)^$B28 -> 0.96272437 | BG28: =AI28+AJ28 -> 58125 | BH28: =AI28*A28 -> 0 | BI28: =1/(1+(AN28+$BX$5)/12)^$B28 -> 0.96728002 | BJ28: =IF(AK29>AK28,0,AL28+AM28) -> 0 | BK28: =A28*AL28 -> 0 | BL28: =1/(1+(AN28+$BY$5)/12)^$B28 -> 0.96950032 | BM28: =AO28+AR28+AU28+AX28+BA28+BD28+BG28+BJ28 -> 1349751 | BN28: =M28*B28 -> 5610597.9 | BO28: =1/(1+(AN28+$CC$5)/12)^$B28 -> 0.96466871
A29: 17 | B29: 12 | C29: =P29+S29+V29+Y29+AB29+AE29+AH29+AK29 -> 2.0101714e+08 | D29: =C29-E29 -> 0 | E29: =E28-H28-K28 -> 2.0101714e+08 | F29: =PMT($K$13/12,$K$12-B29+1,-E29,0) -> 1444804.7 | G29: =E29*$K$13/12 -> 932384.51 | H29: =F29-G29 -> 512420.16 | I29: =IF(A29<=(30-(240-$K$8)),((A29+(240-$K$7))/30)*$K$6,$K$6)*($K$5/100) -> 0 | J29: =1-(1-I29)^(1/12) -> 0 | K29: =(E29-H29)*J29 -> 0 | L29: =K29+H29+G29 -> 1444804.7 | M29: =L29-G29 -> 512420.16 | N29: =M29*$M$4 -> 115387.59 | O29: =M29*$M$5 -> 397032.57 | P29: =P28-Q28 -> 4170394.9 | Q29: =MIN(IF(S29>O29,0,MIN(P29,O29-S29))+IF(P29>0,MIN(AA29,P29)),P29) -> 95956.688 | R29: =P29*($G$10/12) -> 17376.646 | S29: =S28-T28 -> 69428576 | T29: =MIN(IF(S29>O29,O29,S29)+IF(S29>0,AM29,0),S29) -> 501712.59 | U29: =S29*($G$4/12) -> 289285.73 | V29: =V28-W28 -> 14000000 | W29: =IF(T29+P29<=O29+AM29+AA29,MIN(V29,O29-Q29+AA29-T29+AM29),0) -> 0 | X29: =V29*($G$5/12) -> 58333.333 | Y29: =IF(V28>O28,(IF(V28>AA28+O28+AM28,Y28+AA28,Y28+AA28-((AA28+O28+AM28)-V28))),Y28-Z28) -> 23029605 | Z29: =MIN(IF(V29>O29,0,MIN(Y29,O29-V29))+IF(AM28>V28,AM28,0),Y29) -> 0 | AA29: =Y29*($G$8/12) -> 95956.688 | AB29: =AB28-AC28 -> 20000000 | AC29: =MIN(IF(Y29>O29,0,MIN(AB29,O29+AM29-Y29))) -> 0 | AD29: =AB29*($G$9/12) -> 83333.333 | AE29: =AE28-AF28 -> 31315361 | AF29: =IF(AE29>N29,N29,AE29) -> 115387.59 | AG29: =AE29*($G$3/12) -> 130480.67 | AH29: =AH28-AI28 -> 13950000 | AI29: =IF(AE29>N29,0,MIN(AH29,N29-AE29)) -> 0 | AJ29: =AH29*($G$6/12) -> 58125 | AK29: =IF(AL28=0,AK28+AM28,AK28-AL28) -> 25123206 | AL29: =MIN(IF(AB29>0,IF(AB29>O29,0,MIN(AK29,O29-AB29)),O29),AK29) -> 0 | AM29: =AK29*($G$7/12) -> 104680.02 | AN29: =FORECAST(B29, $AM$2:$AY$2,$AM$1:$AY$1) -> 0.022895323 | AO29: =Q29+R29 -> 113333.33 | AP29: =Q29*B29 -> 1151480.3 | AQ29: =1/(1+(AN29+$CB$5)/12)^$B29 -> 0.95298411 | AR29: =T29+U29 -> 790998.32 | AS29: =T29*A29 -> 8529114 | AT29: =1/(1+(AN29+$BV$5)/12)^$B29 -> 0.95622553 | AU29: =W29+X29 -> 58333.333 | AV29: =W29*A29 -> 0 | AW29: =1/(1+(AN29+$BW$5)/12)^$B29 -> 0.95776653 | AX29: =IF(Y30>Y29,0,Z29+AA29) -> 0 | AY29: =A29*Z29 -> 0 | AZ29: =1/(1+(AN29+$BZ$5)/12)^$B29 -> 0.96870354 | BA29: =AC29+AD29 -> 83333.333 | BB29: =AC29*A29 -> 0 | BC29: =1/(1+(AN29+$CA$5)/12)^$B29 -> 0.96215182 | BD29: =AF29+AG29 -> 245868.26 | BE29: =AF29*A29 -> 1961589 | BF29: =1/(1+(AN29+$BU$5)/12)^$B29 -> 0.95932849 | BG29: =AI29+AJ29 -> 58125 | BH29: =AI29*A29 -> 0 | BI29: =1/(1+(AN29+$BX$5)/12)^$B29 -> 0.96428179 | BJ29: =IF(AK30>AK29,0,AL29+AM29) -> 0 | BK29: =A29*AL29 -> 0 | BL29: =1/(1+(AN29+$BY$5)/12)^$B29 -> 0.96669666 | BM29: =AO29+AR29+AU29+AX29+BA29+BD29+BG29+BJ29 -> 1349991.6 | BN29: =M29*B29 -> 6149041.9 | BO29: =1/(1+(AN29+$CC$5)/12)^$B29 -> 0.96144229
A30: 18 | B30: 13 | C30: =P30+S30+V30+Y30+AB30+AE30+AH30+AK30 -> 2.0050472e+08 | D30: =C30-E30 -> 0 | E30: =E29-H29-K29 -> 2.0050472e+08 | F30: =PMT($K$13/12,$K$12-B30+1,-E30,0) -> 1444804.7 | G30: =E30*$K$13/12 -> 930007.74 | H30: =F30-G30 -> 514796.93 | I30: =IF(A30<=(30-(240-$K$8)),((A30+(240-$K$7))/30)*$K$6,$K$6)*($K$5/100) -> 0 | J30: =1-(1-I30)^(1/12) -> 0 | K30: =(E30-H30)*J30 -> 0 | L30: =K30+H30+G30 -> 1444804.7 | M30: =L30-G30 -> 514796.93 | N30: =M30*$M$4 -> 115922.8 | O30: =M30*$M$5 -> 398874.14 | P30: =P29-Q29 -> 4074438.2 | Q30: =MIN(IF(S30>O30,0,MIN(P30,O30-S30))+IF(P30>0,MIN(AA30,P30)),P30) -> 96356.507 | R30: =P30*($G$10/12) -> 16976.826 | S30: =S29-T29 -> 68926863 | T30: =MIN(IF(S30>O30,O30,S30)+IF(S30>0,AM30,0),S30) -> 503990.33 | U30: =S30*($G$4/12) -> 287195.26 | V30: =V29-W29 -> 14000000 | W30: =IF(T30+P30<=O30+AM30+AA30,MIN(V30,O30-Q30+AA30-T30+AM30),0) -> 0 | X30: =V30*($G$5/12) -> 58333.333 | Y30: =IF(V29>O29,(IF(V29>AA29+O29+AM29,Y29+AA29,Y29+AA29-((AA29+O29+AM29)-V29))),Y29-Z29) -> 23125562 | Z30: =MIN(IF(V30>O30,0,MIN(Y30,O30-V30))+IF(AM29>V29,AM29,0),Y30) -> 0 | AA30: =Y30*($G$8/12) -> 96356.507 | AB30: =AB29-AC29 -> 20000000 | AC30: =MIN(IF(Y30>O30,0,MIN(AB30,O30+AM30-Y30))) -> 0 | AD30: =AB30*($G$9/12) -> 83333.333 | AE30: =AE29-AF29 -> 31199974 | AF30: =IF(AE30>N30,N30,AE30) -> 115922.8 | AG30: =AE30*($G$3/12) -> 129999.89 | AH30: =AH29-AI29 -> 13950000 | AI30: =IF(AE30>N30,0,MIN(AH30,N30-AE30)) -> 0 | AJ30: =AH30*($G$6/12) -> 58125 | AK30: =IF(AL29=0,AK29+AM29,AK29-AL29) -> 25227886 | AL30: =MIN(IF(AB30>0,IF(AB30>O30,0,MIN(AK30,O30-AB30)),O30),AK30) -> 0 | AM30: =AK30*($G$7/12) -> 105116.19 | AN30: =FORECAST(B30, $AM$2:$AY$2,$AM$1:$AY$1) -> 0.02297573 | AO30: =Q30+R30 -> 113333.33 | AP30: =Q30*B30 -> 1252634.6 | AQ30: =1/(1+(AN30+$CB$5)/12)^$B30 -> 0.94908502 | AR30: =T30+U30 -> 791185.59 | AS30: =T30*A30 -> 9071825.9 | AT30: =1/(1+(AN30+$BV$5)/12)^$B30 -> 0.95258266 | AU30: =W30+X30 -> 58333.333 | AV30: =W30*A30 -> 0 | AW30: =1/(1+(AN30+$BW$5)/12)^$B30 -> 0.95424582 | AX30: =IF(Y31>Y30,0,Z30+AA30) -> 0 | AY30: =A30*Z30 -> 0 | AZ30: =1/(1+(AN30+$BZ$5)/12)^$B30 -> 0.96605622 | BA30: =AC30+AD30 -> 83333.333 | BB30: =AC30*A30 -> 0 | BC30: =1/(1+(AN30+$CA$5)/12)^$B30 -> 0.95897996 | BD30: =AF30+AG30 -> 245922.69 | BE30: =AF30*A30 -> 2086610.3 | BF30: =1/(1+(AN30+$BU$5)/12)^$B30 -> 0.95593183 | BG30: =AI30+AJ30 -> 58125 | BH30: =AI30*A30 -> 0 | BI30: =1/(1+(AN30+$BX$5)/12)^$B30 -> 0.96128002 | BJ30: =IF(AK31>AK30,0,AL30+AM30) -> 0 | BK30: =A30*AL30 -> 0 | BL30: =1/(1+(AN30+$BY$5)/12)^$B30 -> 0.96388824 | BM30: =AO30+AR30+AU30+AX30+BA30+BD30+BG30+BJ30 -> 1350233.3 | BN30: =M30*B30 -> 6692360.1 | BO30: =1/(1+(AN30+$CC$5)/12)^$B30 -> 0.95821387
A31: 19 | B31: 14 | C31: =P31+S31+V31+Y31+AB31+AE31+AH31+AK31 -> 1.9998993e+08 | D31: =C31-E31 -> 0 | E31: =E30-H30-K30 -> 1.9998993e+08 | F31: =PMT($K$13/12,$K$12-B31+1,-E31,0) -> 1444804.7 | G31: =E31*$K$13/12 -> 927619.94 | H31: =F31-G31 -> 517184.73 | I31: =IF(A31<=(30-(240-$K$8)),((A31+(240-$K$7))/30)*$K$6,$K$6)*($K$5/100) -> 0 | J31: =1-(1-I31)^(1/12) -> 0 | K31: =(E31-H31)*J31 -> 0 | L31: =K31+H31+G31 -> 1444804.7 | M31: =L31-G31 -> 517184.73 | N31: =M31*$M$4 -> 116460.48 | O31: =M31*$M$5 -> 400724.25 | P31: =P30-Q30 -> 3978081.7 | Q31: =MIN(IF(S31>O31,0,MIN(P31,O31-S31))+IF(P31>0,MIN(AA31,P31)),P31) -> 96757.993 | R31: =P31*($G$10/12) -> 16575.341 | S31: =S30-T30 -> 68422873 | T31: =MIN(IF(S31>O31,O31,S31)+IF(S31>0,AM31,0),S31) -> 506278.42 | U31: =S31*($G$4/12) -> 285095.3 | V31: =V30-W30 -> 14000000 | W31: =IF(T31+P31<=O31+AM31+AA31,MIN(V31,O31-Q31+AA31-T31+AM31),0) -> 0 | X31: =V31*($G$5/12) -> 58333.333 | Y31: =IF(V30>O30,(IF(V30>AA30+O30+AM30,Y30+AA30,Y30+AA30-((AA30+O30+AM30)-V30))),Y30-Z30) -> 23221918 | Z31: =MIN(IF(V31>O31,0,MIN(Y31,O31-V31))+IF(AM30>V30,AM30,0),Y31) -> 0 | AA31: =Y31*($G$8/12) -> 96757.993 | AB31: =AB30-AC30 -> 20000000 | AC31: =MIN(IF(Y31>O31,0,MIN(AB31,O31+AM31-Y31))) -> 0 | AD31: =AB31*($G$9/12) -> 83333.333 | AE31: =AE30-AF30 -> 31084051 | AF31: =IF(AE31>N31,N31,AE31) -> 116460.48 | AG31: =AE31*($G$3/12) -> 129516.88 | AH31: =AH30-AI30 -> 13950000 | AI31: =IF(AE31>N31,0,MIN(AH31,N31-AE31)) -> 0 | AJ31: =AH31*($G$6/12) -> 58125 | AK31: =IF(AL30=0,AK30+AM30,AK30-AL30) -> 25333002 | AL31: =MIN(IF(AB31>0,IF(AB31>O31,0,MIN(AK31,O31-AB31)),O31),AK31) -> 0 | AM31: =AK31*($G$7/12) -> 105554.17 | AN31: =FORECAST(B31, $AM$2:$AY$2,$AM$1:$AY$1) -> 0.023056137 | AO31: =Q31+R31 -> 113333.33 | AP31: =Q31*B31 -> 1354611.9 | AQ31: =1/(1+(AN31+$CB$5)/12)^$B31 -> 0.94518926 | AR31: =T31+U31 -> 791373.73 | AS31: =T31*A31 -> 9619290 | AT31: =1/(1+(AN31+$BV$5)/12)^$B31 -> 0.94894101 | AU31: =W31+X31 -> 58333.333 | AV31: =W31*A31 -> 0 | AW31: =1/(1+(AN31+$BW$5)/12)^$B31 -> 0.95072536 | AX31: =IF(Y32>Y31,0,Z31+AA31) -> 0 | AY31: =A31*Z31 -> 0 | AZ31: =1/(1+(AN31+$BZ$5)/12)^$B31 -> 0.96340325 | BA31: =AC31+AD31 -> 83333.333 | BB31: =AC31*A31 -> 0 | BC31: =1/(1+(AN31+$CA$5)/12)^$B31 -> 0.95580578 | BD31: =AF31+AG31 -> 245977.36 | BE31: =AF31*A31 -> 2212749.2 | BF31: =1/(1+(AN31+$BU$5)/12)^$B31 -> 0.95253447 | BG31: =AI31+AJ31 -> 58125 | BH31: =AI31*A31 -> 0 | BI31: =1/(1+(AN31+$BX$5)/12)^$B31 -> 0.95827479 | BJ31: =IF(AK32>AK31,0,AL31+AM31) -> 0 | BK31: =A31*AL31 -> 0 | BL31: =1/(1+(AN31+$BY$5)/12)^$B31 -> 0.96107513 | BM31: =AO31+AR31+AU31+AX31+BA31+BD31+BG31+BJ31 -> 1350476.1 | BN31: =M31*B31 -> 7240586.3 | BO31: =1/(1+(AN31+$CC$5)/12)^$B31 -> 0.95498352
A32: 20 | B32: 15 | C32: =P32+S32+V32+Y32+AB32+AE32+AH32+AK32 -> 1.9947274e+08 | D32: =C32-E32 -> 0 | E32: =E31-H31-K31 -> 1.9947274e+08 | F32: =PMT($K$13/12,$K$12-B32+1,-E32,0) -> 1444804.7 | G32: =E32*$K$13/12 -> 925221.06 | H32: =F32-G32 -> 519583.61 | I32: =IF(A32<=(30-(240-$K$8)),((A32+(240-$K$7))/30)*$K$6,$K$6)*($K$5/100) -> 0 | J32: =1-(1-I32)^(1/12) -> 0 | K32: =(E32-H32)*J32 -> 0 | L32: =K32+H32+G32 -> 1444804.7 | M32: =L32-G32 -> 519583.61 | N32: =M32*$M$4 -> 117000.67 | O32: =M32*$M$5 -> 402582.94 | P32: =P31-Q31 -> 3881323.7 | Q32: =MIN(IF(S32>O32,0,MIN(P32,O32-S32))+IF(P32>0,MIN(AA32,P32)),P32) -> 97161.151 | R32: =P32*($G$10/12) -> 16172.182 | S32: =S31-T31 -> 67916595 | T32: =MIN(IF(S32>O32,O32,S32)+IF(S32>0,AM32,0),S32) -> 508576.92 | U32: =S32*($G$4/12) -> 282985.81 | V32: =V31-W31 -> 14000000 | W32: =IF(T32+P32<=O32+AM32+AA32,MIN(V32,O32-Q32+AA32-T32+AM32),0) -> 0 | X32: =V32*($G$5/12) -> 58333.333 | Y32: =IF(V31>O31,(IF(V31>AA31+O31+AM31,Y31+AA31,Y31+AA31-((AA31+O31+AM31)-V31))),Y31-Z31) -> 23318676 | Z32: =MIN(IF(V32>O32,0,MIN(Y32,O32-V32))+IF(AM31>V31,AM31,0),Y32) -> 0 | AA32: =Y32*($G$8/12) -> 97161.151 | AB32: =AB31-AC31 -> 20000000 | AC32: =MIN(IF(Y32>O32,0,MIN(AB32,O32+AM32-Y32))) -> 0 | AD32: =AB32*($G$9/12) -> 83333.333 | AE32: =AE31-AF31 -> 30967591 | AF32: =IF(AE32>N32,N32,AE32) -> 117000.67 | AG32: =AE32*($G$3/12) -> 129031.63 | AH32: =AH31-AI31 -> 13950000 | AI32: =IF(AE32>N32,0,MIN(AH32,N32-AE32)) -> 0 | AJ32: =AH32*($G$6/12) -> 58125 | AK32: =IF(AL31=0,AK31+AM31,AK31-AL31) -> 25438556 | AL32: =MIN(IF(AB32>0,IF(AB32>O32,0,MIN(AK32,O32-AB32)),O32),AK32) -> 0 | AM32: =AK32*($G$7/12) -> 105993.98 | AN32: =FORECAST(B32, $AM$2:$AY$2,$AM$1:$AY$1) -> 0.023136544 | AO32: =Q32+R32 -> 113333.33 | AP32: =Q32*B32 -> 1457417.3 | AQ32: =1/(1+(AN32+$CB$5)/12)^$B32 -> 0.94129694 | AR32: =T32+U32 -> 791562.73 | AS32: =T32*A32 -> 10171538 | AT32: =1/(1+(AN32+$BV$5)/12)^$B32 -> 0.94530065 | AU32: =W32+X32 -> 58333.333 | AV32: =W32*A32 -> 0 | AW32: =1/(1+(AN32+$BW$5)/12)^$B32 -> 0.94720524 | AX32: =IF(Y33>Y32,0,Z32+AA32) -> 0 | AY32: =A32*Z32 -> 0 | AZ32: =1/(1+(AN32+$BZ$5)/12)^$B32 -> 0.96074472 | BA32: =AC32+AD32 -> 83333.333 | BB32: =AC32*A32 -> 0 | BC32: =1/(1+(AN32+$CA$5)/12)^$B32 -> 0.95262939 | BD32: =AF32+AG32 -> 246032.29 | BE32: =AF32*A32 -> 2340013.3 | BF32: =1/(1+(AN32+$BU$5)/12)^$B32 -> 0.94913651 | BG32: =AI32+AJ32 -> 58125 | BH32: =AI32*A32 -> 0 | BI32: =1/(1+(AN32+$BX$5)/12)^$B32 -> 0.95526619 | BJ32: =IF(AK33>AK32,0,AL32+AM32) -> 0 | BK32: =A32*AL32 -> 0 | BL32: =1/(1+(AN32+$BY$5)/12)^$B32 -> 0.95825743 | BM32: =AO32+AR32+AU32+AX32+BA32+BD32+BG32+BJ32 -> 1350720 | BN32: =M32*B32 -> 7793754.1 | BO32: =1/(1+(AN32+$CC$5)/12)^$B32 -> 0.95175136
A33: 21 | B33: 16 | C33: =P33+S33+V33+Y33+AB33+AE33+AH33+AK33 -> 1.9895316e+08 | D33: =C33-E33 -> 0 | E33: =E32-H32-K32 -> 1.9895316e+08 | F33: =PMT($K$13/12,$K$12-B33+1,-E33,0) -> 1444804.7 | G33: =E33*$K$13/12 -> 922811.06 | H33: =F33-G33 -> 521993.61 | I33: =IF(A33<=(30-(240-$K$8)),((A33+(240-$K$7))/30)*$K$6,$K$6)*($K$5/100) -> 0 | J33: =1-(1-I33)^(1/12) -> 0 | K33: =(E33-H33)*J33 -> 0 | L33: =K33+H33+G33 -> 1444804.7 | M33: =L33-G33 -> 521993.61 | N33: =M33*$M$4 -> 117543.36 | O33: =M33*$M$5 -> 404450.25 | P33: =P32-Q32 -> 3784162.6 | Q33: =MIN(IF(S33>O33,0,MIN(P33,O33-S33))+IF(P33>0,MIN(AA33,P33)),P33) -> 97565.989 | R33: =P33*($G$10/12) -> 15767.344 | S33: =S32-T32 -> 67408018 | T33: =MIN(IF(S33>O33,O33,S33)+IF(S33>0,AM33,0),S33) -> 510885.88 | U33: =S33*($G$4/12) -> 280866.74 | V33: =V32-W32 -> 14000000 | W33: =IF(T33+P33<=O33+AM33+AA33,MIN(V33,O33-Q33+AA33-T33+AM33),0) -> 0 | X33: =V33*($G$5/12) -> 58333.333 | Y33: =IF(V32>O32,(IF(V32>AA32+O32+AM32,Y32+AA32,Y32+AA32-((AA32+O32+AM32)-V32))),Y32-Z32) -> 23415837 | Z33: =MIN(IF(V33>O33,0,MIN(Y33,O33-V33))+IF(AM32>V32,AM32,0),Y33) -> 0 | AA33: =Y33*($G$8/12) -> 97565.989 | AB33: =AB32-AC32 -> 20000000 | AC33: =MIN(IF(Y33>O33,0,MIN(AB33,O33+AM33-Y33))) -> 0 | AD33: =AB33*($G$9/12) -> 83333.333 | AE33: =AE32-AF32 -> 30850590 | AF33: =IF(AE33>N33,N33,AE33) -> 117543.36 | AG33: =AE33*($G$3/12) -> 128544.12 | AH33: =AH32-AI32 -> 13950000 | AI33: =IF(AE33>N33,0,MIN(AH33,N33-AE33)) -> 0 | AJ33: =AH33*($G$6/12) -> 58125 | AK33: =IF(AL32=0,AK32+AM32,AK32-AL32) -> 25544550 | AL33: =MIN(IF(AB33>0,IF(AB33>O33,0,MIN(AK33,O33-AB33)),O33),AK33) -> 0 | AM33: =AK33*($G$7/12) -> 106435.62 | AN33: =FORECAST(B33, $AM$2:$AY$2,$AM$1:$AY$1) -> 0.023216952 | AO33: =Q33+R33 -> 113333.33 | AP33: =Q33*B33 -> 1561055.8 | AQ33: =1/(1+(AN33+$CB$5)/12)^$B33 -> 0.93740813 | AR33: =T33+U33 -> 791752.62 | AS33: =T33*A33 -> 10728603 | AT33: =1/(1+(AN33+$BV$5)/12)^$B33 -> 0.94166169 | AU33: =W33+X33 -> 58333.333 | AV33: =W33*A33 -> 0 | AW33: =1/(1+(AN33+$BW$5)/12)^$B33 -> 0.94368555 | AX33: =IF(Y34>Y33,0,Z33+AA33) -> 0 | AY33: =A33*Z33 -> 0 | AZ33: =1/(1+(AN33+$BZ$5)/12)^$B33 -> 0.95808073 | BA33: =AC33+AD33 -> 83333.333 | BB33: =AC33*A33 -> 0 | BC33: =1/(1+(AN33+$CA$5)/12)^$B33 -> 0.94945087 | BD33: =AF33+AG33 -> 246087.48 | BE33: =AF33*A33 -> 2468410.5 | BF33: =1/(1+(AN33+$BU$5)/12)^$B33 -> 0.94573805 | BG33: =AI33+AJ33 -> 58125 | BH33: =AI33*A33 -> 0 | BI33: =1/(1+(AN33+$BX$5)/12)^$B33 -> 0.95225431 | BJ33: =IF(AK34>AK33,0,AL33+AM33) -> 0 | BK33: =A33*AL33 -> 0 | BL33: =1/(1+(AN33+$BY$5)/12)^$B33 -> 0.95543522 | BM33: =AO33+AR33+AU33+AX33+BA33+BD33+BG33+BJ33 -> 1350965.1 | BN33: =M33*B33 -> 8351897.8 | BO33: =1/(1+(AN33+$CC$5)/12)^$B33 -> 0.94851747
A34: 22 | B34: 17 | C34: =P34+S34+V34+Y34+AB34+AE34+AH34+AK34 -> 1.9843116e+08 | D34: =C34-E34 -> 0 | E34: =E33-H33-K33 -> 1.9843116e+08 | F34: =PMT($K$13/12,$K$12-B34+1,-E34,0) -> 1444804.7 | G34: =E34*$K$13/12 -> 920389.88 | H34: =F34-G34 -> 524414.79 | I34: =IF(A34<=(30-(240-$K$8)),((A34+(240-$K$7))/30)*$K$6,$K$6)*($K$5/100) -> 0 | J34: =1-(1-I34)^(1/12) -> 0 | K34: =(E34-H34)*J34 -> 0 | L34: =K34+H34+G34 -> 1444804.7 | M34: =L34-G34 -> 524414.79 | N34: =M34*$M$4 -> 118088.56 | O34: =M34*$M$5 -> 406326.23 | P34: =P33-Q33 -> 3686596.6 | Q34: =MIN(IF(S34>O34,0,MIN(P34,O34-S34))+IF(P34>0,MIN(AA34,P34)),P34) -> 97972.514 | R34: =P34*($G$10/12) -> 15360.819 | S34: =S33-T33 -> 66897132 | T34: =MIN(IF(S34>O34,O34,S34)+IF(S34>0,AM34,0),S34) -> 513205.34 | U34: =S34*($G$4/12) -> 278738.05 | V34: =V33-W33 -> 14000000 | W34: =IF(T34+P34<=O34+AM34+AA34,MIN(V34,O34-Q34+AA34-T34+AM34),0) -> 0 | X34: =V34*($G$5/12) -> 58333.333 | Y34: =IF(V33>O33,(IF(V33>AA33+O33+AM33,Y33+AA33,Y33+AA33-((AA33+O33+AM33)-V33))),Y33-Z33) -> 23513403 | Z34: =MIN(IF(V34>O34,0,MIN(Y34,O34-V34))+IF(AM33>V33,AM33,0),Y34) -> 0 | AA34: =Y34*($G$8/12) -> 97972.514 | AB34: =AB33-AC33 -> 20000000 | AC34: =MIN(IF(Y34>O34,0,MIN(AB34,O34+AM34-Y34))) -> 0 | AD34: =AB34*($G$9/12) -> 83333.333 | AE34: =AE33-AF33 -> 30733047 | AF34: =IF(AE34>N34,N34,AE34) -> 118088.56 | AG34: =AE34*($G$3/12) -> 128054.36 | AH34: =AH33-AI33 -> 13950000 | AI34: =IF(AE34>N34,0,MIN(AH34,N34-AE34)) -> 0 | AJ34: =AH34*($G$6/12) -> 58125 | AK34: =IF(AL33=0,AK33+AM33,AK33-AL33) -> 25650986 | AL34: =MIN(IF(AB34>0,IF(AB34>O34,0,MIN(AK34,O34-AB34)),O34),AK34) -> 0 | AM34: =AK34*($G$7/12) -> 106879.11 | AN34: =FORECAST(B34, $AM$2:$AY$2,$AM$1:$AY$1) -> 0.023297359 | AO34: =Q34+R34 -> 113333.33 | AP34: =Q34*B34 -> 1665532.7 | AQ34: =1/(1+(AN34+$CB$5)/12)^$B34 -> 0.93352293 | AR34: =T34+U34 -> 791943.39 | AS34: =T34*A34 -> 11290517 | AT34: =1/(1+(AN34+$BV$5)/12)^$B34 -> 0.93802421 | AU34: =W34+X34 -> 58333.333 | AV34: =W34*A34 -> 0 | AW34: =1/(1+(AN34+$BW$5)/12)^$B34 -> 0.94016639 | AX34: =IF(Y35>Y34,0,Z34+AA34) -> 0 | AY34: =A34*Z34 -> 0 | AZ34: =1/(1+(AN34+$BZ$5)/12)^$B34 -> 0.95541136 | BA34: =AC34+AD34 -> 83333.333 | BB34: =AC34*A34 -> 0 | BC34: =1/(1+(AN34+$CA$5)/12)^$B34 -> 0.94627032 | BD34: =AF34+AG34 -> 246142.92 | BE34: =AF34*A34 -> 2597948.3 | BF34: =1/(1+(AN34+$BU$5)/12)^$B34 -> 0.94233917 | BG34: =AI34+AJ34 -> 58125 | BH34: =AI34*A34 -> 0 | BI34: =1/(1+(AN34+$BX$5)/12)^$B34 -> 0.94923925 | BJ34: =IF(AK35>AK34,0,AL34+AM34) -> 0 | BK34: =A34*AL34 -> 0 | BL34: =1/(1+(AN34+$BY$5)/12)^$B34 -> 0.95260859 | BM34: =AO34+AR34+AU34+AX34+BA34+BD34+BG34+BJ34 -> 1351211.3 | BN34: =M34*B34 -> 8915051.4 | BO34: =1/(1+(AN34+$CC$5)/12)^$B34 -> 0.94528194
A35: 23 | B35: 18 | C35: =P35+S35+V35+Y35+AB35+AE35+AH35+AK35 -> 1.9790675e+08 | D35: =C35-E35 -> 0 | E35: =E34-H34-K34 -> 1.9790675e+08 | F35: =PMT($K$13/12,$K$12-B35+1,-E35,0) -> 1444804.7 | G35: =E35*$K$13/12 -> 917957.47 | H35: =F35-G35 -> 526847.2 | I35: =IF(A35<=(30-(240-$K$8)),((A35+(240-$K$7))/30)*$K$6,$K$6)*($K$5/100) -> 0 | J35: =1-(1-I35)^(1/12) -> 0 | K35: =(E35-H35)*J35 -> 0 | L35: =K35+H35+G35 -> 1444804.7 | M35: =L35-G35 -> 526847.2 | N35: =M35*$M$4 -> 118636.29 | O35: =M35*$M$5 -> 408210.91 | P35: =P34-Q34 -> 3588624.1 | Q35: =MIN(IF(S35>O35,0,MIN(P35,O35-S35))+IF(P35>0,MIN(AA35,P35)),P35) -> 98380.733 | R35: =P35*($G$10/12) -> 14952.6 | S35: =S34-T34 -> 66383926 | T35: =MIN(IF(S35>O35,O35,S35)+IF(S35>0,AM35,0),S35) -> 515535.34 | U35: =S35*($G$4/12) -> 276599.69 | V35: =V34-W34 -> 14000000 | W35: =IF(T35+P35<=O35+AM35+AA35,MIN(V35,O35-Q35+AA35-T35+AM35),0) -> 0 | X35: =V35*($G$5/12) -> 58333.333 | Y35: =IF(V34>O34,(IF(V34>AA34+O34+AM34,Y34+AA34,Y34+AA34-((AA34+O34+AM34)-V34))),Y34-Z34) -> 23611376 | Z35: =MIN(IF(V35>O35,0,MIN(Y35,O35-V35))+IF(AM34>V34,AM34,0),Y35) -> 0 | AA35: =Y35*($G$8/12) -> 98380.733 | AB35: =AB34-AC34 -> 20000000 | AC35: =MIN(IF(Y35>O35,0,MIN(AB35,O35+AM35-Y35))) -> 0 | AD35: =AB35*($G$9/12) -> 83333.333 | AE35: =AE34-AF34 -> 30614958 | AF35: =IF(AE35>N35,N35,AE35) -> 118636.29 | AG35: =AE35*($G$3/12) -> 127562.33 | AH35: =AH34-AI34 -> 13950000 | AI35: =IF(AE35>N35,0,MIN(AH35,N35-AE35)) -> 0 | AJ35: =AH35*($G$6/12) -> 58125 | AK35: =IF(AL34=0,AK34+AM34,AK34-AL34) -> 25757865 | AL35: =MIN(IF(AB35>0,IF(AB35>O35,0,MIN(AK35,O35-AB35)),O35),AK35) -> 0 | AM35: =AK35*($G$7/12) -> 107324.44 | AN35: =FORECAST(B35, $AM$2:$AY$2,$AM$1:$AY$1) -> 0.023377766 | AO35: =Q35+R35 -> 113333.33 | AP35: =Q35*B35 -> 1770853.2 | AQ35: =1/(1+(AN35+$CB$5)/12)^$B35 -> 0.92964142 | AR35: =T35+U35 -> 792135.04 | AS35: =T35*A35 -> 11857313 | AT35: =1/(1+(AN35+$BV$5)/12)^$B35 -> 0.93438831 | AU35: =W35+X35 -> 58333.333 | AV35: =W35*A35 -> 0 | AW35: =1/(1+(AN35+$BW$5)/12)^$B35 -> 0.93664784 | AX35: =IF(Y36>Y35,0,Z35+AA35) -> 0 | AY35: =A35*Z35 -> 0 | AZ35: =1/(1+(AN35+$BZ$5)/12)^$B35 -> 0.95273668 | BA35: =AC35+AD35 -> 83333.333 | BB35: =AC35*A35 -> 0 | BC35: =1/(1+(AN35+$CA$5)/12)^$B35 -> 0.94308783 | BD35: =AF35+AG35 -> 246198.62 | BE35: =AF35*A35 -> 2728634.8 | BF35: =1/(1+(AN35+$BU$5)/12)^$B35 -> 0.93893996 | BG35: =AI35+AJ35 -> 58125 | BH35: =AI35*A35 -> 0 | BI35: =1/(1+(AN35+$BX$5)/12)^$B35 -> 0.94622109 | BJ35: =IF(AK36>AK35,0,AL35+AM35) -> 0 | BK35: =A35*AL35 -> 0 | BL35: =1/(1+(AN35+$BY$5)/12)^$B35 -> 0.94977763 | BM35: =AO35+AR35+AU35+AX35+BA35+BD35+BG35+BJ35 -> 1351458.7 | BN35: =M35*B35 -> 9483249.6 | BO35: =1/(1+(AN35+$CC$5)/12)^$B35 -> 0.94204486
... A69: 57 | B69: 52 | C69: =P69+S69+V69+Y69+AB69+AE69+AH69+AK69 -> 1.785527e+08 | D69: =C69-E69 -> 0 | E69: =E68-H68-K68 -> 1.785527e+08 | F69: =PMT($K$13/12,$K$12-B69+1,-E69,0) -> 1444804.7 | G69: =E69*$K$13/12 -> 828186.93 | H69: =F69-G69 -> 616617.74 | I69: =IF(A69<=(30-(240-$K$8)),((A69+(240-$K$7))/30)*$K$6,$K$6)*($K$5/100) -> 0 | J69: =1-(1-I69)^(1/12) -> 0 | K69: =(E69-H69)*J69 -> 0 | L69: =K69+H69+G69 -> 1444804.7 | M69: =L69-G69 -> 616617.74 | N69: =M69*$M$4 -> 138850.97 | O69: =M69*$M$5 -> 477766.77 | P69: =P68-Q68 -> 3155.0812 | Q69: =MIN(IF(S69>O69,0,MIN(P69,O69-S69))+IF(P69>0,MIN(AA69,P69)),P69) -> 3155.0812 | R69: =P69*($G$10/12) -> 13.146172 | S69: =S68-T68 -> 47476631 | T69: =MIN(IF(S69>O69,O69,S69)+IF(S69>0,AM69,0),S69) -> 601388.79 | U69: =S69*($G$4/12) -> 197819.3 | V69: =V68-W68 -> 14000000 | W69: =IF(T69+P69<=O69+AM69+AA69,MIN(V69,O69-Q69+AA69-T69+AM69),0) -> 110165.11 | X69: =V69*($G$5/12) -> 58333.333 | Y69: =IF(V68>O68,(IF(V68>AA68+O68+AM68,Y68+AA68,Y68+AA68-((AA68+O68+AM68)-V68))),Y68-Z68) -> 27196845 | Z69: =MIN(IF(V69>O69,0,MIN(Y69,O69-V69))+IF(AM68>V68,AM68,0),Y69) -> 0 | AA69: =Y69*($G$8/12) -> 113320.19 | AB69: =AB68-AC68 -> 20000000 | AC69: =MIN(IF(Y69>O69,0,MIN(AB69,O69+AM69-Y69))) -> 0 | AD69: =AB69*($G$9/12) -> 83333.333 | AE69: =AE68-AF68 -> 26256782 | AF69: =IF(AE69>N69,N69,AE69) -> 138850.97 | AG69: =AE69*($G$3/12) -> 109403.26 | AH69: =AH68-AI68 -> 13950000 | AI69: =IF(AE69>N69,0,MIN(AH69,N69-AE69)) -> 0 | AJ69: =AH69*($G$6/12) -> 58125 | AK69: =IF(AL68=0,AK68+AM68,AK68-AL68) -> 29669285 | AL69: =MIN(IF(AB69>0,IF(AB69>O69,0,MIN(AK69,O69-AB69)),O69),AK69) -> 0 | AM69: =AK69*($G$7/12) -> 123622.02 | AN69: =FORECAST(B69, $AM$2:$AY$2,$AM$1:$AY$1) -> 0.02611161 | AO69: =Q69+R69 -> 3168.2274 | AP69: =Q69*B69 -> 164064.22 | AQ69: =1/(1+(AN69+$CB$5)/12)^$B69 -> 0.80046687 | AR69: =T69+U69 -> 799208.09 | AS69: =T69*A69 -> 34279161 | AT69: =1/(1+(AN69+$BV$5)/12)^$B69 -> 0.81232894 | AU69: =W69+X69 -> 168498.44 | AV69: =W69*A69 -> 6279411 | AW69: =1/(1+(AN69+$BW$5)/12)^$B69 -> 0.81801546 | AX69: =IF(Y70>Y69,0,Z69+AA69) -> 0 | AY69: =A69*Z69 -> 0 | AZ69: =1/(1+(AN69+$BZ$5)/12)^$B69 -> 0.85925976 | BA69: =AC69+AD69 -> 83333.333 | BB69: =AC69*A69 -> 0 | BC69: =1/(1+(AN69+$CA$5)/12)^$B69 -> 0.83436547 | BD69: =AF69+AG69 -> 248254.23 | BE69: =AF69*A69 -> 7914505.2 | BF69: =1/(1+(AN69+$BU$5)/12)^$B69 -> 0.82381051 | BG69: =AI69+AJ69 -> 58125 | BH69: =AI69*A69 -> 0 | BI69: =1/(1+(AN69+$BX$5)/12)^$B69 -> 0.84239694 | BJ69: =IF(AK70>AK69,0,AL69+AM69) -> 0 | BK69: =A69*AL69 -> 0 | BL69: =1/(1+(AN69+$BY$5)/12)^$B69 -> 0.85157444 | BM69: =AO69+AR69+AU69+AX69+BA69+BD69+BG69+BJ69 -> 1360587.3 | BN69: =M69*B69 -> 32064122 | BO69: =1/(1+(AN69+$CC$5)/12)^$B69 -> 0.83170319
A70: 58 | B70: 53 | C70: =P70+S70+V70+Y70+AB70+AE70+AH70+AK70 -> 1.7793608e+08 | D70: =C70-E70 -> 0 | E70: =E69-H69-K69 -> 1.7793608e+08 | F70: =PMT($K$13/12,$K$12-B70+1,-E70,0) -> 1444804.7 | G70: =E70*$K$13/12 -> 825326.85 | H70: =F70-G70 -> 619477.82 | I70: =IF(A70<=(30-(240-$K$8)),((A70+(240-$K$7))/30)*$K$6,$K$6)*($K$5/100) -> 0 | J70: =1-(1-I70)^(1/12) -> 0 | K70: =(E70-H70)*J70 -> 0 | L70: =K70+H70+G70 -> 1444804.7 | M70: =L70-G70 -> 619477.82 | N70: =M70*$M$4 -> 139495 | O70: =M70*$M$5 -> 479982.81 | P70: =P69-Q69 -> 0 | Q70: =MIN(IF(S70>O70,0,MIN(P70,O70-S70))+IF(P70>0,MIN(AA70,P70)),P70) -> 0 | R70: =P70*($G$10/12) -> 0 | S70: =S69-T69 -> 46875242 | T70: =MIN(IF(S70>O70,O70,S70)+IF(S70>0,AM70,0),S70) -> 604119.93 | U70: =S70*($G$4/12) -> 195313.51 | V70: =V69-W69 -> 13889835 | W70: =IF(T70+P70<=O70+AM70,MIN(V70,O70-Q70+AA70-T70+AM70),0) -> 113792.35 | X70: =V70*($G$5/12) -> 57874.312 | Y70: =IF(V69>O69,(IF(V69>AA69+O69+AM69,Y69+AA69,Y69+AA69-((AA69+O69+AM69)-V69))),Y69-Z69) -> 27310165 | Z70: =MIN(IF(V70>O70,0,MIN(Y70,O70-V70))+IF(AM69>V69,AM69,0),Y70) -> 0 | AA70: =Y70*($G$8/12) -> 113792.35 | AB70: =AB69-AC69 -> 20000000 | AC70: =MIN(IF(Y70>O70,0,MIN(AB70,O70+AM70-Y70))) -> 0 | AD70: =AB70*($G$9/12) -> 83333.333 | AE70: =AE69-AF69 -> 26117931 | AF70: =IF(AE70>N70,N70,AE70) -> 139495 | AG70: =AE70*($G$3/12) -> 108824.71 | AH70: =AH69-AI69 -> 13950000 | AI70: =IF(AE70>N70,0,MIN(AH70,N70-AE70)) -> 0 | AJ70: =AH70*($G$6/12) -> 58125 | AK70: =IF(AL69=0,AK69+AM69,AK69-AL69) -> 29792907 | AL70: =MIN(IF(AB70>0,IF(AB70>O70,0,MIN(AK70,O70-AB70)),O70),AK70) -> 0 | AM70: =AK70*($G$7/12) -> 124137.11 | AN70: =FORECAST(B70, $AM$2:$AY$2,$AM$1:$AY$1) -> 0.026192017 | AO70: =Q70+R70 -> 0 | AP70: =Q70*B70 -> 0 | AQ70: =1/(1+(AN70+$CB$5)/12)^$B70 -> 0.79676639 | AR70: =T70+U70 -> 799433.44 | AS70: =T70*A70 -> 35038956 | AT70: =1/(1+(AN70+$BV$5)/12)^$B70 -> 0.80880231 | AU70: =W70+X70 -> 171666.67 | AV70: =W70*A70 -> 6599956.6 | AW70: =1/(1+(AN70+$BW$5)/12)^$B70 -> 0.81457338 | AX70: =IF(Y71>Y70,0,Z70+AA70) -> 0 | AY70: =A70*Z70 -> 0 | AZ70: =1/(1+(AN70+$BZ$5)/12)^$B70 -> 0.85645363 | BA70: =AC70+AD70 -> 83333.333 | BB70: =AC70*A70 -> 0 | BC70: =1/(1+(AN70+$CA$5)/12)^$B70 -> 0.83117075 | BD70: =AF70+AG70 -> 248319.72 | BE70: =AF70*A70 -> 8090710.3 | BF70: =1/(1+(AN70+$BU$5)/12)^$B70 -> 0.82045538 | BG70: =AI70+AJ70 -> 58125 | BH70: =AI70*A70 -> 0 | BI70: =1/(1+(AN70+$BX$5)/12)^$B70 -> 0.83932602 | BJ70: =IF(AK71>AK70,0,AL70+AM70) -> 0 | BK70: =A70*AL70 -> 0 | BL70: =1/(1+(AN70+$BY$5)/12)^$B70 -> 0.84864682 | BM70: =AO70+AR70+AU70+AX70+BA70+BD70+BG70+BJ70 -> 1360878.2 | BN70: =M70*B70 -> 32832324 | BO70: =1/(1+(AN70+$CC$5)/12)^$B70 -> 0.82846776
A71: 59 | B71: 54 | C71: =P71+S71+V71+Y71+AB71+AE71+AH71+AK71 -> 1.773166e+08 | D71: =C71-E71 -> 0 | E71: =E70-H70-K70 -> 1.773166e+08 | F71: =PMT($K$13/12,$K$12-B71+1,-E71,0) -> 1444804.7 | G71: =E71*$K$13/12 -> 822453.51 | H71: =F71-G71 -> 622351.16 | I71: =IF(A71<=(30-(240-$K$8)),((A71+(240-$K$7))/30)*$K$6,$K$6)*($K$5/100) -> 0 | J71: =1-(1-I71)^(1/12) -> 0 | K71: =(E71-H71)*J71 -> 0 | L71: =K71+H71+G71 -> 1444804.7 | M71: =L71-G71 -> 622351.16 | N71: =M71*$M$4 -> 140142.03 | O71: =M71*$M$5 -> 482209.13 | P71: =P70-Q70 -> 0 | Q71: =MIN(IF(S71>O71,0,MIN(P71,O71-S71))+IF(P71>0,MIN(AA71,P71)),P71) -> 0 | R71: =P71*($G$10/12) -> 0 | S71: =S70-T70 -> 46271122 | T71: =MIN(IF(S71>O71,O71,S71)+IF(S71>0,AM71,0),S71) -> 606863.49 | U71: =S71*($G$4/12) -> 192796.34 | V71: =V70-W70 -> 13776043 | W71: =IF(T71+P71<=O71+AM71,MIN(V71,O71-Q71+AA71-T71+AM71),0) -> 114266.49 | X71: =V71*($G$5/12) -> 57400.177 | Y71: =IF(V70>O70,(IF(V70>AA70+O70+AM70,Y70+AA70,Y70+AA70-((AA70+O70+AM70)-V70))),Y70-Z70) -> 27423957 | Z71: =MIN(IF(V71>O71,0,MIN(Y71,O71-V71))+IF(AM70>V70,AM70,0),Y71) -> 0 | AA71: =Y71*($G$8/12) -> 114266.49 | AB71: =AB70-AC70 -> 20000000 | AC71: =MIN(IF(Y71>O71,0,MIN(AB71,O71+AM71-Y71))) -> 0 | AD71: =AB71*($G$9/12) -> 83333.333 | AE71: =AE70-AF70 -> 25978436 | AF71: =IF(AE71>N71,N71,AE71) -> 140142.03 | AG71: =AE71*($G$3/12) -> 108243.48 | AH71: =AH70-AI70 -> 13950000 | AI71: =IF(AE71>N71,0,MIN(AH71,N71-AE71)) -> 0 | AJ71: =AH71*($G$6/12) -> 58125 | AK71: =IF(AL70=0,AK70+AM70,AK70-AL70) -> 29917045 | AL71: =MIN(IF(AB71>0,IF(AB71>O71,0,MIN(AK71,O71-AB71)),O71),AK71) -> 0 | AM71: =AK71*($G$7/12) -> 124654.35 | AN71: =FORECAST(B71, $AM$2:$AY$2,$AM$1:$AY$1) -> 0.026272425 | AO71: =Q71+R71 -> 0 | AP71: =Q71*B71 -> 0 | AQ71: =1/(1+(AN71+$CB$5)/12)^$B71 -> 0.79307244 | AR71: =T71+U71 -> 799659.83 | AS71: =T71*A71 -> 35804946 | AT71: =1/(1+(AN71+$BV$5)/12)^$B71 -> 0.80528025 | AU71: =W71+X71 -> 171666.67 | AV71: =W71*A71 -> 6741722.9 | AW71: =1/(1+(AN71+$BW$5)/12)^$B71 -> 0.81113495 | AX71: =IF(Y72>Y71,0,Z71+AA71) -> 0 | AY71: =A71*Z71 -> 0 | AZ71: =1/(1+(AN71+$BZ$5)/12)^$B71 -> 0.85364526 | BA71: =AC71+AD71 -> 83333.333 | BB71: =AC71*A71 -> 0 | BC71: =1/(1+(AN71+$CA$5)/12)^$B71 -> 0.8279772 | BD71: =AF71+AG71 -> 248385.51 | BE71: =AF71*A71 -> 8268379.7 | BF71: =1/(1+(AN71+$BU$5)/12)^$B71 -> 0.817103 | BG71: =AI71+AJ71 -> 58125 | BH71: =AI71*A71 -> 0 | BI71: =1/(1+(AN71+$BX$5)/12)^$B71 -> 0.83625513 | BJ71: =IF(AK72>AK71,0,AL71+AM71) -> 0 | BK71: =A71*AL71 -> 0 | BL71: =1/(1+(AN71+$BY$5)/12)^$B71 -> 0.84571797 | BM71: =AO71+AR71+AU71+AX71+BA71+BD71+BG71+BJ71 -> 1361170.3 | BN71: =M71*B71 -> 33606963 | BO71: =1/(1+(AN71+$CC$5)/12)^$B71 -> 0.8252339
A72: 60 | B72: 55 | C72: =P72+S72+V72+Y72+AB72+AE72+AH72+AK72 -> 1.7669425e+08 | D72: =C72-E72 -> 0 | E72: =E71-H71-K71 -> 1.7669425e+08 | F72: =PMT($K$13/12,$K$12-B72+1,-E72,0) -> 1444804.7 | G72: =E72*$K$13/12 -> 819566.84 | H72: =F72-G72 -> 625237.83 | I72: =IF(A72<=(30-(240-$K$8)),((A72+(240-$K$7))/30)*$K$6,$K$6)*($K$5/100) -> 0 | J72: =1-(1-I72)^(1/12) -> 0 | K72: =(E72-H72)*J72 -> 0 | L72: =K72+H72+G72 -> 1444804.7 | M72: =L72-G72 -> 625237.83 | N72: =M72*$M$4 -> 140792.05 | O72: =M72*$M$5 -> 484445.78 | P72: =P71-Q71 -> 0 | Q72: =MIN(IF(S72>O72,0,MIN(P72,O72-S72))+IF(P72>0,MIN(AA72,P72)),P72) -> 0 | R72: =P72*($G$10/12) -> 0 | S72: =S71-T71 -> 45664259 | T72: =MIN(IF(S72>O72,O72,S72)+IF(S72>0,AM72,0),S72) -> 609619.52 | U72: =S72*($G$4/12) -> 190267.75 | V72: =V71-W71 -> 13661776 | W72: =IF(T72+P72<=O72+AM72,MIN(V72,O72-Q72+AA72-T72+AM72),0) -> 114742.6 | X72: =V72*($G$5/12) -> 56924.067 | Y72: =IF(V71>O71,(IF(V71>AA71+O71+AM71,Y71+AA71,Y71+AA71-((AA71+O71+AM71)-V71))),Y71-Z71) -> 27538224 | Z72: =MIN(IF(V72>O72,0,MIN(Y72,O72-V72))+IF(AM71>V71,AM71,0),Y72) -> 0 | AA72: =Y72*($G$8/12) -> 114742.6 | AB72: =AB71-AC71 -> 20000000 | AC72: =MIN(IF(Y72>O72,0,MIN(AB72,O72+AM72-Y72))) -> 0 | AD72: =AB72*($G$9/12) -> 83333.333 | AE72: =AE71-AF71 -> 25838294 | AF72: =IF(AE72>N72,N72,AE72) -> 140792.05 | AG72: =AE72*($G$3/12) -> 107659.56 | AH72: =AH71-AI71 -> 13950000 | AI72: =IF(AE72>N72,0,MIN(AH72,N72-AE72)) -> 0 | AJ72: =AH72*($G$6/12) -> 58125 | AK72: =IF(AL71=0,AK71+AM71,AK71-AL71) -> 30041699 | AL72: =MIN(IF(AB72>0,IF(AB72>O72,0,MIN(AK72,O72-AB72)),O72),AK72) -> 0 | AM72: =AK72*($G$7/12) -> 125173.75 | AN72: =FORECAST(B72, $AM$2:$AY$2,$AM$1:$AY$1) -> 0.026352832 | AO72: =Q72+R72 -> 0 | AP72: =Q72*B72 -> 0 | AQ72: =1/(1+(AN72+$CB$5)/12)^$B72 -> 0.78938508 | AR72: =T72+U72 -> 799887.27 | AS72: =T72*A72 -> 36577171 | AT72: =1/(1+(AN72+$BV$5)/12)^$B72 -> 0.80176282 | AU72: =W72+X72 -> 171666.67 | AV72: =W72*A72 -> 6884556 | AW72: =1/(1+(AN72+$BW$5)/12)^$B72 -> 0.80770026 | AX72: =IF(Y73>Y72,0,Z72+AA72) -> 0 | AY72: =A72*Z72 -> 0 | AZ72: =1/(1+(AN72+$BZ$5)/12)^$B72 -> 0.85083473 | BA72: =AC72+AD72 -> 83333.333 | BB72: =AC72*A72 -> 0 | BC72: =1/(1+(AN72+$CA$5)/12)^$B72 -> 0.82478491 | BD72: =AF72+AG72 -> 248451.61 | BE72: =AF72*A72 -> 8447523.3 | BF72: =1/(1+(AN72+$BU$5)/12)^$B72 -> 0.81375346 | BG72: =AI72+AJ72 -> 58125 | BH72: =AI72*A72 -> 0 | BI72: =1/(1+(AN72+$BX$5)/12)^$B72 -> 0.83318435 | BJ72: =IF(AK73>AK72,0,AL72+AM72) -> 0 | BK72: =A72*AL72 -> 0 | BL72: =1/(1+(AN72+$BY$5)/12)^$B72 -> 0.84278797 | BM72: =AO72+AR72+AU72+AX72+BA72+BD72+BG72+BJ72 -> 1361463.9 | BN72: =M72*B72 -> 34388081 | BO72: =1/(1+(AN72+$CC$5)/12)^$B72 -> 0.82200168
A73: 61 | B73: 56 | C73: =P73+S73+V73+Y73+AB73+AE73+AH73+AK73 -> 1.7606901e+08 | D73: =C73-E73 -> 0 | E73: =E72-H72-K72 -> 1.7606901e+08 | F73: =PMT($K$13/12,$K$12-B73+1,-E73,0) -> 1444804.7 | G73: =E73*$K$13/12 -> 816666.78 | H73: =F73-G73 -> 628137.9 | I73: =IF(A73<=(30-(240-$K$8)),((A73+(240-$K$7))/30)*$K$6,$K$6)*($K$5/100) -> 0 | J73: =1-(1-I73)^(1/12) -> 0 | K73: =(E73-H73)*J73 -> 0 | L73: =K73+H73+G73 -> 1444804.7 | M73: =L73-G73 -> 628137.9 | N73: =M73*$M$4 -> 141445.1 | O73: =M73*$M$5 -> 486692.8 | P73: =P72-Q72 -> 0 | Q73: =MIN(IF(S73>O73,0,MIN(P73,O73-S73))+IF(P73>0,MIN(AA73,P73)),P73) -> 0 | R73: =P73*($G$10/12) -> 0 | S73: =S72-T72 -> 45054639 | T73: =MIN(IF(S73>O73,O73,S73)+IF(S73>0,AM73,0),S73) -> 612388.1 | U73: =S73*($G$4/12) -> 187727.66 | V73: =V72-W72 -> 13547033 | W73: =IF(T73+P73<=O73+AM73,MIN(V73,O73-Q73+AA73-T73+AM73),0) -> 115220.69 | X73: =V73*($G$5/12) -> 56445.973 | Y73: =IF(V72>O72,(IF(V72>AA72+O72+AM72,Y72+AA72,Y72+AA72-((AA72+O72+AM72)-V72))),Y72-Z72) -> 27652967 | Z73: =MIN(IF(V73>O73,0,MIN(Y73,O73-V73))+IF(AM72>V72,AM72,0),Y73) -> 0 | AA73: =Y73*($G$8/12) -> 115220.69 | AB73: =AB72-AC72 -> 20000000 | AC73: =MIN(IF(Y73>O73,0,MIN(AB73,O73+AM73-Y73))) -> 0 | AD73: =AB73*($G$9/12) -> 83333.333 | AE73: =AE72-AF72 -> 25697502 | AF73: =IF(AE73>N73,N73,AE73) -> 141445.1 | AG73: =AE73*($G$3/12) -> 107072.92 | AH73: =AH72-AI72 -> 13950000 | AI73: =IF(AE73>N73,0,MIN(AH73,N73-AE73)) -> 0 | AJ73: =AH73*($G$6/12) -> 58125 | AK73: =IF(AL72=0,AK72+AM72,AK72-AL72) -> 30166873 | AL73: =MIN(IF(AB73>0,IF(AB73>O73,0,MIN(AK73,O73-AB73)),O73),AK73) -> 0 | AM73: =AK73*($G$7/12) -> 125695.3 | AN73: =FORECAST(B73, $AM$2:$AY$2,$AM$1:$AY$1) -> 0.026433239 | AO73: =Q73+R73 -> 0 | AP73: =Q73*B73 -> 0 | AQ73: =1/(1+(AN73+$CB$5)/12)^$B73 -> 0.78570439 | AR73: =T73+U73 -> 800115.77 | AS73: =T73*A73 -> 37355674 | AT73: =1/(1+(AN73+$BV$5)/12)^$B73 -> 0.79825011 | AU73: =W73+X73 -> 171666.67 | AV73: =W73*A73 -> 7028462.3 | AW73: =1/(1+(AN73+$BW$5)/12)^$B73 -> 0.80426938 | AX73: =IF(Y74>Y73,0,Z73+AA73) -> 0 | AY73: =A73*Z73 -> 0 | AZ73: =1/(1+(AN73+$BZ$5)/12)^$B73 -> 0.84802213 | BA73: =AC73+AD73 -> 83333.333 | BB73: =AC73*A73 -> 0 | BC73: =1/(1+(AN73+$CA$5)/12)^$B73 -> 0.82159396 | BD73: =AF73+AG73 -> 248518.02 | BE73: =AF73*A73 -> 8628150.8 | BF73: =1/(1+(AN73+$BU$5)/12)^$B73 -> 0.81040684 | BG73: =AI73+AJ73 -> 58125 | BH73: =AI73*A73 -> 0 | BI73: =1/(1+(AN73+$BX$5)/12)^$B73 -> 0.83011376 | BJ73: =IF(AK74>AK73,0,AL73+AM73) -> 0 | BK73: =A73*AL73 -> 0 | BL73: =1/(1+(AN73+$BY$5)/12)^$B73 -> 0.83985691 | BM73: =AO73+AR73+AU73+AX73+BA73+BD73+BG73+BJ73 -> 1361758.8 | BN73: =M73*B73 -> 35175722 | BO73: =1/(1+(AN73+$CC$5)/12)^$B73 -> 0.8187712
A74: 62 | B74: 57 | C74: =P74+S74+V74+Y74+AB74+AE74+AH74+AK74 -> 1.7544088e+08 | D74: =C74-E74 -> 0 | E74: =E73-H73-K73 -> 1.7544088e+08 | F74: =PMT($K$13/12,$K$12-B74+1,-E74,0) -> 1444804.7 | G74: =E74*$K$13/12 -> 813753.26 | H74: =F74-G74 -> 631051.41 | I74: =IF(A74<=(30-(240-$K$8)),((A74+(240-$K$7))/30)*$K$6,$K$6)*($K$5/100) -> 0 | J74: =1-(1-I74)^(1/12) -> 0 | K74: =(E74-H74)*J74 -> 0 | L74: =K74+H74+G74 -> 1444804.7 | M74: =L74-G74 -> 631051.41 | N74: =M74*$M$4 -> 142101.16 | O74: =M74*$M$5 -> 488950.24 | P74: =P73-Q73 -> 0 | Q74: =MIN(IF(S74>O74,0,MIN(P74,O74-S74))+IF(P74>0,MIN(AA74,P74)),P74) -> 0 | R74: =P74*($G$10/12) -> 0 | S74: =S73-T73 -> 44442251 | T74: =MIN(IF(S74>O74,O74,S74)+IF(S74>0,AM74,0),S74) -> 615169.28 | U74: =S74*($G$4/12) -> 185176.05 | V74: =V73-W73 -> 13431813 | W74: =IF(T74+P74<=O74+AM74,MIN(V74,O74-Q74+AA74-T74+AM74),0) -> 115700.78 | X74: =V74*($G$5/12) -> 55965.886 | Y74: =IF(V73>O73,(IF(V73>AA73+O73+AM73,Y73+AA73,Y73+AA73-((AA73+O73+AM73)-V73))),Y73-Z73) -> 27768187 | Z74: =MIN(IF(V74>O74,0,MIN(Y74,O74-V74))+IF(AM73>V73,AM73,0),Y74) -> 0 | AA74: =Y74*($G$8/12) -> 115700.78 | AB74: =AB73-AC73 -> 20000000 | AC74: =MIN(IF(Y74>O74,0,MIN(AB74,O74+AM74-Y74))) -> 0 | AD74: =AB74*($G$9/12) -> 83333.333 | AE74: =AE73-AF73 -> 25556057 | AF74: =IF(AE74>N74,N74,AE74) -> 142101.16 | AG74: =AE74*($G$3/12) -> 106483.57 | AH74: =AH73-AI73 -> 13950000 | AI74: =IF(AE74>N74,0,MIN(AH74,N74-AE74)) -> 0 | AJ74: =AH74*($G$6/12) -> 58125 | AK74: =IF(AL73=0,AK73+AM73,AK73-AL73) -> 30292568 | AL74: =MIN(IF(AB74>0,IF(AB74>O74,0,MIN(AK74,O74-AB74)),O74),AK74) -> 0 | AM74: =AK74*($G$7/12) -> 126219.03 | AN74: =FORECAST(B74, $AM$2:$AY$2,$AM$1:$AY$1) -> 0.026513646 | AO74: =Q74+R74 -> 0 | AP74: =Q74*B74 -> 0 | AQ74: =1/(1+(AN74+$CB$5)/12)^$B74 -> 0.78203042 | AR74: =T74+U74 -> 800345.32 | AS74: =T74*A74 -> 38140495 | AT74: =1/(1+(AN74+$BV$5)/12)^$B74 -> 0.79474218 | AU74: =W74+X74 -> 171666.67 | AV74: =W74*A74 -> 7173448.4 | AW74: =1/(1+(AN74+$BW$5)/12)^$B74 -> 0.80084238 | AX74: =IF(Y75>Y74,0,Z74+AA74) -> 0 | AY74: =A74*Z74 -> 0 | AZ74: =1/(1+(AN74+$BZ$5)/12)^$B74 -> 0.84520753 | BA74: =AC74+AD74 -> 83333.333 | BB74: =AC74*A74 -> 0 | BC74: =1/(1+(AN74+$CA$5)/12)^$B74 -> 0.81840443 | BD74: =AF74+AG74 -> 248584.73 | BE74: =AF74*A74 -> 8810272.2 | BF74: =1/(1+(AN74+$BU$5)/12)^$B74 -> 0.8070632 | BG74: =AI74+AJ74 -> 58125 | BH74: =AI74*A74 -> 0 | BI74: =1/(1+(AN74+$BX$5)/12)^$B74 -> 0.82704343 | BJ74: =IF(AK75>AK74,0,AL74+AM74) -> 0 | BK74: =A74*AL74 -> 0 | BL74: =1/(1+(AN74+$BY$5)/12)^$B74 -> 0.83692485 | BM74: =AO74+AR74+AU74+AX74+BA74+BD74+BG74+BJ74 -> 1362055.1 | BN74: =M74*B74 -> 35969930 | BO74: =1/(1+(AN74+$CC$5)/12)^$B74 -> 0.81554252
A75: 63 | B75: 58 | C75: =P75+S75+V75+Y75+AB75+AE75+AH75+AK75 -> 1.7480982e+08 | D75: =C75-E75 -> 0 | E75: =E74-H74-K74 -> 1.7480982e+08 | F75: =PMT($K$13/12,$K$12-B75+1,-E75,0) -> 1444804.7 | G75: =E75*$K$13/12 -> 810826.24 | H75: =F75-G75 -> 633978.44 | I75: =IF(A75<=(30-(240-$K$8)),((A75+(240-$K$7))/30)*$K$6,$K$6)*($K$5/100) -> 0 | J75: =1-(1-I75)^(1/12) -> 0 | K75: =(E75-H75)*J75 -> 0 | L75: =K75+H75+G75 -> 1444804.7 | M75: =L75-G75 -> 633978.44 | N75: =M75*$M$4 -> 142760.28 | O75: =M75*$M$5 -> 491218.16 | P75: =P74-Q74 -> 0 | Q75: =MIN(IF(S75>O75,0,MIN(P75,O75-S75))+IF(P75>0,MIN(AA75,P75)),P75) -> 0 | R75: =P75*($G$10/12) -> 0 | S75: =S74-T74 -> 43827082 | T75: =MIN(IF(S75>O75,O75,S75)+IF(S75>0,AM75,0),S75) -> 617963.1 | U75: =S75*($G$4/12) -> 182612.84 | V75: =V74-W74 -> 13316112 | W75: =IF(T75+P75<=O75+AM75,MIN(V75,O75-Q75+AA75-T75+AM75),0) -> 116182.87 | X75: =V75*($G$5/12) -> 55483.8 | Y75: =IF(V74>O74,(IF(V74>AA74+O74+AM74,Y74+AA74,Y74+AA74-((AA74+O74+AM74)-V74))),Y74-Z74) -> 27883888 | Z75: =MIN(IF(V75>O75,0,MIN(Y75,O75-V75))+IF(AM74>V74,AM74,0),Y75) -> 0 | AA75: =Y75*($G$8/12) -> 116182.87 | AB75: =AB74-AC74 -> 20000000 | AC75: =MIN(IF(Y75>O75,0,MIN(AB75,O75+AM75-Y75))) -> 0 | AD75: =AB75*($G$9/12) -> 83333.333 | AE75: =AE74-AF74 -> 25413956 | AF75: =IF(AE75>N75,N75,AE75) -> 142760.28 | AG75: =AE75*($G$3/12) -> 105891.48 | AH75: =AH74-AI74 -> 13950000 | AI75: =IF(AE75>N75,0,MIN(AH75,N75-AE75)) -> 0 | AJ75: =AH75*($G$6/12) -> 58125 | AK75: =IF(AL74=0,AK74+AM74,AK74-AL74) -> 30418787 | AL75: =MIN(IF(AB75>0,IF(AB75>O75,0,MIN(AK75,O75-AB75)),O75),AK75) -> 0 | AM75: =AK75*($G$7/12) -> 126744.95 | AN75: =FORECAST(B75, $AM$2:$AY$2,$AM$1:$AY$1) -> 0.026594053 | AO75: =Q75+R75 -> 0 | AP75: =Q75*B75 -> 0 | AQ75: =1/(1+(AN75+$CB$5)/12)^$B75 -> 0.77836325 | AR75: =T75+U75 -> 800575.95 | AS75: =T75*A75 -> 38931676 | AT75: =1/(1+(AN75+$BV$5)/12)^$B75 -> 0.79123911 | AU75: =W75+X75 -> 171666.67 | AV75: =W75*A75 -> 7319520.6 | AW75: =1/(1+(AN75+$BW$5)/12)^$B75 -> 0.79741934 | AX75: =IF(Y76>Y75,0,Z75+AA75) -> 0 | AY75: =A75*Z75 -> 0 | AZ75: =1/(1+(AN75+$BZ$5)/12)^$B75 -> 0.84239102 | BA75: =AC75+AD75 -> 83333.333 | BB75: =AC75*A75 -> 0 | BC75: =1/(1+(AN75+$CA$5)/12)^$B75 -> 0.81521639 | BD75: =AF75+AG75 -> 248651.76 | BE75: =AF75*A75 -> 8993897.5 | BF75: =1/(1+(AN75+$BU$5)/12)^$B75 -> 0.80372263 | BG75: =AI75+AJ75 -> 58125 | BH75: =AI75*A75 -> 0 | BI75: =1/(1+(AN75+$BX$5)/12)^$B75 -> 0.82397347 | BJ75: =IF(AK76>AK75,0,AL75+AM75) -> 0 | BK75: =A75*AL75 -> 0 | BL75: =1/(1+(AN75+$BY$5)/12)^$B75 -> 0.8339919 | BM75: =AO75+AR75+AU75+AX75+BA75+BD75+BG75+BJ75 -> 1362352.7 | BN75: =M75*B75 -> 36770749 | BO75: =1/(1+(AN75+$CC$5)/12)^$B75 -> 0.81231573
A76: 64 | B76: 59 | C76: =P76+S76+V76+Y76+AB76+AE76+AH76+AK76 -> 1.7417585e+08 | D76: =C76-E76 -> 0 | E76: =E75-H75-K75 -> 1.7417585e+08 | F76: =PMT($K$13/12,$K$12-B76+1,-E76,0) -> 1444804.7 | G76: =E76*$K$13/12 -> 807885.63 | H76: =F76-G76 -> 636919.04 | I76: =IF(A76<=(30-(240-$K$8)),((A76+(240-$K$7))/30)*$K$6,$K$6)*($K$5/100) -> 0 | J76: =1-(1-I76)^(1/12) -> 0 | K76: =(E76-H76)*J76 -> 0 | L76: =K76+H76+G76 -> 1444804.7 | M76: =L76-G76 -> 636919.04 | N76: =M76*$M$4 -> 143422.45 | O76: =M76*$M$5 -> 493496.59 | P76: =P75-Q75 -> 0 | Q76: =MIN(IF(S76>O76,0,MIN(P76,O76-S76))+IF(P76>0,MIN(AA76,P76)),P76) -> 0 | R76: =P76*($G$10/12) -> 0 | S76: =S75-T75 -> 43209119 | T76: =MIN(IF(S76>O76,O76,S76)+IF(S76>0,AM76,0),S76) -> 620769.64 | U76: =S76*($G$4/12) -> 180038 | V76: =V75-W75 -> 13199929 | W76: =IF(T76+P76<=O76+AM76,MIN(V76,O76-Q76+AA76-T76+AM76),0) -> 116666.96 | X76: =V76*($G$5/12) -> 54999.705 | Y76: =IF(V75>O75,(IF(V75>AA75+O75+AM75,Y75+AA75,Y75+AA75-((AA75+O75+AM75)-V75))),Y75-Z75) -> 28000071 | Z76: =MIN(IF(V76>O76,0,MIN(Y76,O76-V76))+IF(AM75>V75,AM75,0),Y76) -> 0 | AA76: =Y76*($G$8/12) -> 116666.96 | AB76: =AB75-AC75 -> 20000000 | AC76: =MIN(IF(Y76>O76,0,MIN(AB76,O76+AM76-Y76))) -> 0 | AD76: =AB76*($G$9/12) -> 83333.333 | AE76: =AE75-AF75 -> 25271195 | AF76: =IF(AE76>N76,N76,AE76) -> 143422.45 | AG76: =AE76*($G$3/12) -> 105296.65 | AH76: =AH75-AI75 -> 13950000 | AI76: =IF(AE76>N76,0,MIN(AH76,N76-AE76)) -> 0 | AJ76: =AH76*($G$6/12) -> 58125 | AK76: =IF(AL75=0,AK75+AM75,AK75-AL75) -> 30545532 | AL76: =MIN(IF(AB76>0,IF(AB76>O76,0,MIN(AK76,O76-AB76)),O76),AK76) -> 0 | AM76: =AK76*($G$7/12) -> 127273.05 | AN76: =FORECAST(B76, $AM$2:$AY$2,$AM$1:$AY$1) -> 0.026674461 | AO76: =Q76+R76 -> 0 | AP76: =Q76*B76 -> 0 | AQ76: =1/(1+(AN76+$CB$5)/12)^$B76 -> 0.77470294 | AR76: =T76+U76 -> 800807.64 | AS76: =T76*A76 -> 39729257 | AT76: =1/(1+(AN76+$BV$5)/12)^$B76 -> 0.78774096 | AU76: =W76+X76 -> 171666.67 | AV76: =W76*A76 -> 7466685.6 | AW76: =1/(1+(AN76+$BW$5)/12)^$B76 -> 0.79400034 | AX76: =IF(Y77>Y76,0,Z76+AA76) -> 0 | AY76: =A76*Z76 -> 0 | AZ76: =1/(1+(AN76+$BZ$5)/12)^$B76 -> 0.83957268 | BA76: =AC76+AD76 -> 83333.333 | BB76: =AC76*A76 -> 0 | BC76: =1/(1+(AN76+$CA$5)/12)^$B76 -> 0.81202993 | BD76: =AF76+AG76 -> 248719.09 | BE76: =AF76*A76 -> 9179036.6 | BF76: =1/(1+(AN76+$BU$5)/12)^$B76 -> 0.8003852 | BG76: =AI76+AJ76 -> 58125 | BH76: =AI76*A76 -> 0 | BI76: =1/(1+(AN76+$BX$5)/12)^$B76 -> 0.82090393 | BJ76: =IF(AK77>AK76,0,AL76+AM76) -> 0 | BK76: =A76*AL76 -> 0 | BL76: =1/(1+(AN76+$BY$5)/12)^$B76 -> 0.83105812 | BM76: =AO76+AR76+AU76+AX76+BA76+BD76+BG76+BJ76 -> 1362651.7 | BN76: =M76*B76 -> 37578223 | BO76: =1/(1+(AN76+$CC$5)/12)^$B76 -> 0.8090909
A77: 65 | B77: 60 | C77: =P77+S77+V77+Y77+AB77+AE77+AH77+AK77 -> 1.7353893e+08 | D77: =C77-E77 -> 0 | E77: =E76-H76-K76 -> 1.7353893e+08 | F77: =PMT($K$13/12,$K$12-B77+1,-E77,0) -> 1444804.7 | G77: =E77*$K$13/12 -> 804931.39 | H77: =F77-G77 -> 639873.28 | I77: =IF(A77<=(30-(240-$K$8)),((A77+(240-$K$7))/30)*$K$6,$K$6)*($K$5/100) -> 0 | J77: =1-(1-I77)^(1/12) -> 0 | K77: =(E77-H77)*J77 -> 0 | L77: =K77+H77+G77 -> 1444804.7 | M77: =L77-G77 -> 639873.28 | N77: =M77*$M$4 -> 144087.69 | O77: =M77*$M$5 -> 495785.59 | P77: =P76-Q76 -> 0 | Q77: =MIN(IF(S77>O77,0,MIN(P77,O77-S77))+IF(P77>0,MIN(AA77,P77)),P77) -> 0 | R77: =P77*($G$10/12) -> 0 | S77: =S76-T76 -> 42588349 | T77: =MIN(IF(S77>O77,O77,S77)+IF(S77>0,AM77,0),S77) -> 623588.95 | U77: =S77*($G$4/12) -> 177451.46 | V77: =V76-W76 -> 13083262 | W77: =IF(T77+P77<=O77+AM77,MIN(V77,O77-Q77+AA77-T77+AM77),0) -> 117153.07 | X77: =V77*($G$5/12) -> 54513.592 | Y77: =IF(V76>O76,(IF(V76>AA76+O76+AM76,Y76+AA76,Y76+AA76-((AA76+O76+AM76)-V76))),Y76-Z76) -> 28116738 | Z77: =MIN(IF(V77>O77,0,MIN(Y77,O77-V77))+IF(AM76>V76,AM76,0),Y77) -> 0 | AA77: =Y77*($G$8/12) -> 117153.07 | AB77: =AB76-AC76 -> 20000000 | AC77: =MIN(IF(Y77>O77,0,MIN(AB77,O77+AM77-Y77))) -> 0 | AD77: =AB77*($G$9/12) -> 83333.333 | AE77: =AE76-AF76 -> 25127773 | AF77: =IF(AE77>N77,N77,AE77) -> 144087.69 | AG77: =AE77*($G$3/12) -> 104699.05 | AH77: =AH76-AI76 -> 13950000 | AI77: =IF(AE77>N77,0,MIN(AH77,N77-AE77)) -> 0 | AJ77: =AH77*($G$6/12) -> 58125 | AK77: =IF(AL76=0,AK76+AM76,AK76-AL76) -> 30672805 | AL77: =MIN(IF(AB77>0,IF(AB77>O77,0,MIN(AK77,O77-AB77)),O77),AK77) -> 0 | AM77: =AK77*($G$7/12) -> 127803.35 | AN77: =FORECAST(B77, $AM$2:$AY$2,$AM$1:$AY$1) -> 0.026754868 | AO77: =Q77+R77 -> 0 | AP77: =Q77*B77 -> 0 | AQ77: =1/(1+(AN77+$CB$5)/12)^$B77 -> 0.77104956 | AR77: =T77+U77 -> 801040.4 | AS77: =T77*A77 -> 40533282 | AT77: =1/(1+(AN77+$BV$5)/12)^$B77 -> 0.78424782 | AU77: =W77+X77 -> 171666.67 | AV77: =W77*A77 -> 7614949.8 | AW77: =1/(1+(AN77+$BW$5)/12)^$B77 -> 0.79058544 | AX77: =IF(Y78>Y77,0,Z77+AA77) -> 0 | AY77: =A77*Z77 -> 0 | AZ77: =1/(1+(AN77+$BZ$5)/12)^$B77 -> 0.8367526 | BA77: =AC77+AD77 -> 83333.333 | BB77: =AC77*A77 -> 0 | BC77: =1/(1+(AN77+$CA$5)/12)^$B77 -> 0.80884513 | BD77: =AF77+AG77 -> 248786.74 | BE77: =AF77*A77 -> 9365699.7 | BF77: =1/(1+(AN77+$BU$5)/12)^$B77 -> 0.79705099 | BG77: =AI77+AJ77 -> 58125 | BH77: =AI77*A77 -> 0 | BI77: =1/(1+(AN77+$BX$5)/12)^$B77 -> 0.81783491 | BJ77: =IF(AK78>AK77,0,AL77+AM77) -> 0 | BK77: =A77*AL77 -> 0 | BL77: =1/(1+(AN77+$BY$5)/12)^$B77 -> 0.82812361 | BM77: =AO77+AR77+AU77+AX77+BA77+BD77+BG77+BJ77 -> 1362952.1 | BN77: =M77*B77 -> 38392397 | BO77: =1/(1+(AN77+$CC$5)/12)^$B77 -> 0.80586812
A78: 66 | B78: 61 | C78: =P78+S78+V78+Y78+AB78+AE78+AH78+AK78 -> 1.7289905e+08 | D78: =C78-E78 -> 0 | E78: =E77-H77-K77 -> 1.7289905e+08 | F78: =PMT($K$13/12,$K$12-B78+1,-E78,0) -> 1444804.7 | G78: =E78*$K$13/12 -> 801963.44 | H78: =F78-G78 -> 642841.23 | I78: =IF(A78<=(30-(240-$K$8)),((A78+(240-$K$7))/30)*$K$6,$K$6)*($K$5/100) -> 0 | J78: =1-(1-I78)^(1/12) -> 0 | K78: =(E78-H78)*J78 -> 0 | L78: =K78+H78+G78 -> 1444804.7 | M78: =L78-G78 -> 642841.23 | N78: =M78*$M$4 -> 144756.01 | O78: =M78*$M$5 -> 498085.21 | P78: =P77-Q77 -> 0 | Q78: =MIN(IF(S78>O78,0,MIN(P78,O78-S78))+IF(P78>0,MIN(AA78,P78)),P78) -> 0 | R78: =P78*($G$10/12) -> 0 | S78: =S77-T77 -> 41964760 | T78: =MIN(IF(S78>O78,O78,S78)+IF(S78>0,AM78,0),S78) -> 626421.08 | U78: =S78*($G$4/12) -> 174853.17 | V78: =V77-W77 -> 12966109 | W78: =IF(T78+P78<=O78+AM78,MIN(V78,O78-Q78+AA78-T78+AM78),0) -> 117641.21 | X78: =V78*($G$5/12) -> 54025.454 | Y78: =IF(V77>O77,(IF(V77>AA77+O77+AM77,Y77+AA77,Y77+AA77-((AA77+O77+AM77)-V77))),Y77-Z77) -> 28233891 | Z78: =MIN(IF(V78>O78,0,MIN(Y78,O78-V78))+IF(AM77>V77,AM77,0),Y78) -> 0 | AA78: =Y78*($G$8/12) -> 117641.21 | AB78: =AB77-AC77 -> 20000000 | AC78: =MIN(IF(Y78>O78,0,MIN(AB78,O78+AM78-Y78))) -> 0 | AD78: =AB78*($G$9/12) -> 83333.333 | AE78: =AE77-AF77 -> 24983685 | AF78: =IF(AE78>N78,N78,AE78) -> 144756.01 | AG78: =AE78*($G$3/12) -> 104098.69 | AH78: =AH77-AI77 -> 13950000 | AI78: =IF(AE78>N78,0,MIN(AH78,N78-AE78)) -> 0 | AJ78: =AH78*($G$6/12) -> 58125 | AK78: =IF(AL77=0,AK77+AM77,AK77-AL77) -> 30800608 | AL78: =MIN(IF(AB78>0,IF(AB78>O78,0,MIN(AK78,O78-AB78)),O78),AK78) -> 0 | AM78: =AK78*($G$7/12) -> 128335.87 | AN78: =FORECAST(B78, $AM$2:$AY$2,$AM$1:$AY$1) -> 0.026835275 | AO78: =Q78+R78 -> 0 | AP78: =Q78*B78 -> 0 | AQ78: =1/(1+(AN78+$CB$5)/12)^$B78 -> 0.76740317 | AR78: =T78+U78 -> 801274.25 | AS78: =T78*A78 -> 41343791 | AT78: =1/(1+(AN78+$BV$5)/12)^$B78 -> 0.78075975 | AU78: =W78+X78 -> 171666.67 | AV78: =W78*A78 -> 7764320 | AW78: =1/(1+(AN78+$BW$5)/12)^$B78 -> 0.78717473 | AX78: =IF(Y79>Y78,0,Z78+AA78) -> 0 | AY78: =A78*Z78 -> 0 | AZ78: =1/(1+(AN78+$BZ$5)/12)^$B78 -> 0.83393084 | BA78: =AC78+AD78 -> 83333.333 | BB78: =AC78*A78 -> 0 | BC78: =1/(1+(AN78+$CA$5)/12)^$B78 -> 0.80566206 | BD78: =AF78+AG78 -> 248854.7 | BE78: =AF78*A78 -> 9553897 | BF78: =1/(1+(AN78+$BU$5)/12)^$B78 -> 0.79372008 | BG78: =AI78+AJ78 -> 58125 | BH78: =AI78*A78 -> 0 | BI78: =1/(1+(AN78+$BX$5)/12)^$B78 -> 0.81476648 | BJ78: =IF(AK79>AK78,0,AL78+AM78) -> 0 | BK78: =A78*AL78 -> 0 | BL78: =1/(1+(AN78+$BY$5)/12)^$B78 -> 0.82518843 | BM78: =AO78+AR78+AU78+AX78+BA78+BD78+BG78+BJ78 -> 1363254 | BN78: =M78*B78 -> 39213315 | BO78: =1/(1+(AN78+$CC$5)/12)^$B78 -> 0.80264745
A79: 67 | B79: 62 | C79: =P79+S79+V79+Y79+AB79+AE79+AH79+AK79 -> 1.7225621e+08 | D79: =C79-E79 -> 0 | E79: =E78-H78-K78 -> 1.7225621e+08 | F79: =PMT($K$13/12,$K$12-B79+1,-E79,0) -> 1444804.7 | G79: =E79*$K$13/12 -> 798981.73 | H79: =F79-G79 -> 645822.94 | I79: =IF(A79<=(30-(240-$K$8)),((A79+(240-$K$7))/30)*$K$6,$K$6)*($K$5/100) -> 0 | J79: =1-(1-I79)^(1/12) -> 0 | K79: =(E79-H79)*J79 -> 0 | L79: =K79+H79+G79 -> 1444804.7 | M79: =L79-G79 -> 645822.94 | N79: =M79*$M$4 -> 145427.44 | O79: =M79*$M$5 -> 500395.5 | P79: =P78-Q78 -> 0 | Q79: =MIN(IF(S79>O79,0,MIN(P79,O79-S79))+IF(P79>0,MIN(AA79,P79)),P79) -> 0 | R79: =P79*($G$10/12) -> 0 | S79: =S78-T78 -> 41338339 | T79: =MIN(IF(S79>O79,O79,S79)+IF(S79>0,AM79,0),S79) -> 629266.1 | U79: =S79*($G$4/12) -> 172243.08 | V79: =V78-W78 -> 12848468 | W79: =IF(T79+P79<=O79+AM79,MIN(V79,O79-Q79+AA79-T79+AM79),0) -> 118131.38 | X79: =V79*($G$5/12) -> 53535.283 | Y79: =IF(V78>O78,(IF(V78>AA78+O78+AM78,Y78+AA78,Y78+AA78-((AA78+O78+AM78)-V78))),Y78-Z78) -> 28351532 | Z79: =MIN(IF(V79>O79,0,MIN(Y79,O79-V79))+IF(AM78>V78,AM78,0),Y79) -> 0 | AA79: =Y79*($G$8/12) -> 118131.38 | AB79: =AB78-AC78 -> 20000000 | AC79: =MIN(IF(Y79>O79,0,MIN(AB79,O79+AM79-Y79))) -> 0 | AD79: =AB79*($G$9/12) -> 83333.333 | AE79: =AE78-AF78 -> 24838929 | AF79: =IF(AE79>N79,N79,AE79) -> 145427.44 | AG79: =AE79*($G$3/12) -> 103495.54 | AH79: =AH78-AI78 -> 13950000 | AI79: =IF(AE79>N79,0,MIN(AH79,N79-AE79)) -> 0 | AJ79: =AH79*($G$6/12) -> 58125 | AK79: =IF(AL78=0,AK78+AM78,AK78-AL78) -> 30928944 | AL79: =MIN(IF(AB79>0,IF(AB79>O79,0,MIN(AK79,O79-AB79)),O79),AK79) -> 0 | AM79: =AK79*($G$7/12) -> 128870.6 | AN79: =FORECAST(B79, $AM$2:$AY$2,$AM$1:$AY$1) -> 0.026915682 | AO79: =Q79+R79 -> 0 | AP79: =Q79*B79 -> 0 | AQ79: =1/(1+(AN79+$CB$5)/12)^$B79 -> 0.76376383 | AR79: =T79+U79 -> 801509.18 | AS79: =T79*A79 -> 42160829 | AT79: =1/(1+(AN79+$BV$5)/12)^$B79 -> 0.77727682 | AU79: =W79+X79 -> 171666.67 | AV79: =W79*A79 -> 7914802.7 | AW79: =1/(1+(AN79+$BW$5)/12)^$B79 -> 0.78376827 | AX79: =IF(Y80>Y79,0,Z79+AA79) -> 0 | AY79: =A79*Z79 -> 0 | AZ79: =1/(1+(AN79+$BZ$5)/12)^$B79 -> 0.83110749 | BA79: =AC79+AD79 -> 83333.333 | BB79: =AC79*A79 -> 0 | BC79: =1/(1+(AN79+$CA$5)/12)^$B79 -> 0.8024808 | BD79: =AF79+AG79 -> 248922.98 | BE79: =AF79*A79 -> 9743638.6 | BF79: =1/(1+(AN79+$BU$5)/12)^$B79 -> 0.79039254 | BG79: =AI79+AJ79 -> 58125 | BH79: =AI79*A79 -> 0 | BI79: =1/(1+(AN79+$BX$5)/12)^$B79 -> 0.81169873 | BJ79: =IF(AK80>AK79,0,AL79+AM79) -> 0 | BK79: =A79*AL79 -> 0 | BL79: =1/(1+(AN79+$BY$5)/12)^$B79 -> 0.82225267 | BM79: =AO79+AR79+AU79+AX79+BA79+BD79+BG79+BJ79 -> 1363557.2 | BN79: =M79*B79 -> 40041022 | BO79: =1/(1+(AN79+$CC$5)/12)^$B79 -> 0.79942899
A80: 68 | B80: 63 | C80: =P80+S80+V80+Y80+AB80+AE80+AH80+AK80 -> 1.7161039e+08 | D80: =C80-E80 -> 0 | E80: =E79-H79-K79 -> 1.7161039e+08 | F80: =PMT($K$13/12,$K$12-B80+1,-E80,0) -> 1444804.7 | G80: =E80*$K$13/12 -> 795986.19 | H80: =F80-G80 -> 648818.48 | I80: =IF(A80<=(30-(240-$K$8)),((A80+(240-$K$7))/30)*$K$6,$K$6)*($K$5/100) -> 0 | J80: =1-(1-I80)^(1/12) -> 0 | K80: =(E80-H80)*J80 -> 0 | L80: =K80+H80+G80 -> 1444804.7 | M80: =L80-G80 -> 648818.48 | N80: =M80*$M$4 -> 146101.98 | O80: =M80*$M$5 -> 502716.5 | P80: =P79-Q79 -> 0 | Q80: =MIN(IF(S80>O80,0,MIN(P80,O80-S80))+IF(P80>0,MIN(AA80,P80)),P80) -> 0 | R80: =P80*($G$10/12) -> 0 | S80: =S79-T79 -> 40709073 | T80: =MIN(IF(S80>O80,O80,S80)+IF(S80>0,AM80,0),S80) -> 632124.06 | U80: =S80*($G$4/12) -> 169621.14 | V80: =V79-W79 -> 12730336 | W80: =IF(T80+P80<=O80+AM80,MIN(V80,O80-Q80+AA80-T80+AM80),0) -> 118623.6 | X80: =V80*($G$5/12) -> 53043.069 | Y80: =IF(V79>O79,(IF(V79>AA79+O79+AM79,Y79+AA79,Y79+AA79-((AA79+O79+AM79)-V79))),Y79-Z79) -> 28469664 | Z80: =MIN(IF(V80>O80,0,MIN(Y80,O80-V80))+IF(AM79>V79,AM79,0),Y80) -> 0 | AA80: =Y80*($G$8/12) -> 118623.6 | AB80: =AB79-AC79 -> 20000000 | AC80: =MIN(IF(Y80>O80,0,MIN(AB80,O80+AM80-Y80))) -> 0 | AD80: =AB80*($G$9/12) -> 83333.333 | AE80: =AE79-AF79 -> 24693502 | AF80: =IF(AE80>N80,N80,AE80) -> 146101.98 | AG80: =AE80*($G$3/12) -> 102889.59 | AH80: =AH79-AI79 -> 13950000 | AI80: =IF(AE80>N80,0,MIN(AH80,N80-AE80)) -> 0 | AJ80: =AH80*($G$6/12) -> 58125 | AK80: =IF(AL79=0,AK79+AM79,AK79-AL79) -> 31057815 | AL80: =MIN(IF(AB80>0,IF(AB80>O80,0,MIN(AK80,O80-AB80)),O80),AK80) -> 0 | AM80: =AK80*($G$7/12) -> 129407.56 | AN80: =FORECAST(B80, $AM$2:$AY$2,$AM$1:$AY$1) -> 0.026996089 | AO80: =Q80+R80 -> 0 | AP80: =Q80*B80 -> 0 | AQ80: =1/(1+(AN80+$CB$5)/12)^$B80 -> 0.76013162 | AR80: =T80+U80 -> 801745.2 | AS80: =T80*A80 -> 42984436 | AT80: =1/(1+(AN80+$BV$5)/12)^$B80 -> 0.7737991 | AU80: =W80+X80 -> 171666.67 | AV80: =W80*A80 -> 8066404.7 | AW80: =1/(1+(AN80+$BW$5)/12)^$B80 -> 0.78036613 | AX80: =IF(Y81>Y80,0,Z80+AA80) -> 0 | AY80: =A80*Z80 -> 0 | AZ80: =1/(1+(AN80+$BZ$5)/12)^$B80 -> 0.82828265 | BA80: =AC80+AD80 -> 83333.333 | BB80: =AC80*A80 -> 0 | BC80: =1/(1+(AN80+$CA$5)/12)^$B80 -> 0.79930144 | BD80: =AF80+AG80 -> 248991.57 | BE80: =AF80*A80 -> 9934934.8 | BF80: =1/(1+(AN80+$BU$5)/12)^$B80 -> 0.78706844 | BG80: =AI80+AJ80 -> 58125 | BH80: =AI80*A80 -> 0 | BI80: =1/(1+(AN80+$BX$5)/12)^$B80 -> 0.80863173 | BJ80: =IF(AK81>AK80,0,AL80+AM80) -> 0 | BK80: =A80*AL80 -> 0 | BL80: =1/(1+(AN80+$BY$5)/12)^$B80 -> 0.81931642 | BM80: =AO80+AR80+AU80+AX80+BA80+BD80+BG80+BJ80 -> 1363861.8 | BN80: =M80*B80 -> 40875564 | BO80: =1/(1+(AN80+$CC$5)/12)^$B80 -> 0.7962128
A81: 69 | B81: 64 | C81: =P81+S81+V81+Y81+AB81+AE81+AH81+AK81 -> 1.7096157e+08 | D81: =C81-E81 -> 0 | E81: =E80-H80-K80 -> 1.7096157e+08 | F81: =PMT($K$13/12,$K$12-B81+1,-E81,0) -> 1444804.7 | G81: =E81*$K$13/12 -> 792976.75 | H81: =F81-G81 -> 651827.92 | I81: =IF(A81<=(30-(240-$K$8)),((A81+(240-$K$7))/30)*$K$6,$K$6)*($K$5/100) -> 0 | J81: =1-(1-I81)^(1/12) -> 0 | K81: =(E81-H81)*J81 -> 0 | L81: =K81+H81+G81 -> 1444804.7 | M81: =L81-G81 -> 651827.92 | N81: =M81*$M$4 -> 146779.65 | O81: =M81*$M$5 -> 505048.27 | P81: =P80-Q80 -> 0 | Q81: =MIN(IF(S81>O81,0,MIN(P81,O81-S81))+IF(P81>0,MIN(AA81,P81)),P81) -> 0 | R81: =P81*($G$10/12) -> 0 | S81: =S80-T80 -> 40076949 | T81: =MIN(IF(S81>O81,O81,S81)+IF(S81>0,AM81,0),S81) -> 634995.03 | U81: =S81*($G$4/12) -> 166987.29 | V81: =V80-W80 -> 12611713 | W81: =IF(T81+P81<=O81+AM81,MIN(V81,O81-Q81+AA81-T81+AM81),0) -> 119117.86 | X81: =V81*($G$5/12) -> 52548.804 | Y81: =IF(V80>O80,(IF(V80>AA80+O80+AM80,Y80+AA80,Y80+AA80-((AA80+O80+AM80)-V80))),Y80-Z80) -> 28588287 | Z81: =MIN(IF(V81>O81,0,MIN(Y81,O81-V81))+IF(AM80>V80,AM80,0),Y81) -> 0 | AA81: =Y81*($G$8/12) -> 119117.86 | AB81: =AB80-AC80 -> 20000000 | AC81: =MIN(IF(Y81>O81,0,MIN(AB81,O81+AM81-Y81))) -> 0 | AD81: =AB81*($G$9/12) -> 83333.333 | AE81: =AE80-AF80 -> 24547400 | AF81: =IF(AE81>N81,N81,AE81) -> 146779.65 | AG81: =AE81*($G$3/12) -> 102280.83 | AH81: =AH80-AI80 -> 13950000 | AI81: =IF(AE81>N81,0,MIN(AH81,N81-AE81)) -> 0 | AJ81: =AH81*($G$6/12) -> 58125 | AK81: =IF(AL80=0,AK80+AM80,AK80-AL80) -> 31187222 | AL81: =MIN(IF(AB81>0,IF(AB81>O81,0,MIN(AK81,O81-AB81)),O81),AK81) -> 0 | AM81: =AK81*($G$7/12) -> 129946.76 | AN81: =FORECAST(B81, $AM$2:$AY$2,$AM$1:$AY$1) -> 0.027076496 | AO81: =Q81+R81 -> 0 | AP81: =Q81*B81 -> 0 | AQ81: =1/(1+(AN81+$CB$5)/12)^$B81 -> 0.75650658 | AR81: =T81+U81 -> 801982.31 | AS81: =T81*A81 -> 43814657 | AT81: =1/(1+(AN81+$BV$5)/12)^$B81 -> 0.77032666 | AU81: =W81+X81 -> 171666.67 | AV81: =W81*A81 -> 8219132.5 | AW81: =1/(1+(AN81+$BW$5)/12)^$B81 -> 0.7769684 | AX81: =IF(Y82>Y81,0,Z81+AA81) -> 0 | AY81: =A81*Z81 -> 0 | AZ81: =1/(1+(AN81+$BZ$5)/12)^$B81 -> 0.82545637 | BA81: =AC81+AD81 -> 83333.333 | BB81: =AC81*A81 -> 0 | BC81: =1/(1+(AN81+$CA$5)/12)^$B81 -> 0.79612404 | BD81: =AF81+AG81 -> 249060.48 | BE81: =AF81*A81 -> 10127796 | BF81: =1/(1+(AN81+$BU$5)/12)^$B81 -> 0.78374786 | BG81: =AI81+AJ81 -> 58125 | BH81: =AI81*A81 -> 0 | BI81: =1/(1+(AN81+$BX$5)/12)^$B81 -> 0.80556556 | BJ81: =IF(AK82>AK81,0,AL81+AM81) -> 0 | BK81: =A81*AL81 -> 0 | BL81: =1/(1+(AN81+$BY$5)/12)^$B81 -> 0.81637975 | BM81: =AO81+AR81+AU81+AX81+BA81+BD81+BG81+BJ81 -> 1364167.8 | BN81: =M81*B81 -> 41716987 | BO81: =1/(1+(AN81+$CC$5)/12)^$B81 -> 0.79299897
... A252: 240 | B252: 235 | C252: =P252+S252+V252+Y252+AB252+AE252+AH252+AK252 -> 1635079.4 | D252: =C252-E252 -> 196945.26 | E252: =E251-H251-K251 -> 1438134.1 | F252: =PMT($K$13/12,$K$12-B252+1,-E252,0) -> 1444804.7 | G252: =E252*$K$13/12 -> 6670.5455 | H252: =F252-G252 -> 1438134.1 | I252: =IF(A252<=(30-(240-$K$8)),((A252+(240-$K$7))/30)*$K$6,$K$6)*($K$5/100) -> 0 | J252: =1-(1-I252)^(1/12) -> 0 | K252: =(E252-H252)*J252 -> 0 | L252: =K252+H252+G252 -> 1444804.7 | M252: =L252-G252 -> 1438134.1 | N252: =M252*$M$4 -> 323841.34 | O252: =M252*$M$5 -> 1114292.8 | P252: =P251-Q251 -> 0 | Q252: =MIN(IF(S252>O252,0,MIN(P252,O252-S252))+IF(P252>0,MIN(AA252,P252)),P252) -> 0 | R252: =P252*($G$10/12) -> 0 | S252: =S251-T251 -> 0 | T252: =MIN(IF(S252>O252,O252,S252)+IF(S252>0,AM252,0),S252) -> 0 | U252: =S252*($G$4/12) -> 0 | V252: =V251-W251 -> 0 | W252: =IF(T252+P252<=O252+AM252,MIN(V252,O252-Q252+AA252-T252+AM252),0) -> 0 | X252: =V252*($G$5/12) -> 0 | Y252: =IF(V251>O251,(IF(V251>AA251+O251+AM251,Y251+AA251,Y251+AA251-((AA251+O251+AM251)-V251))),Y251-Z251) -> 0 | Z252: =MIN(IF(V252>O252,0,MIN(Y252,O252-V252))+IF(AM251>V251,AM251,0),Y252) -> 0 | AA252: =Y252*($G$8/12) -> 0 | AB252: =AB251-AC251 -> 0 | AC252: =MIN(IF(Y252>O252,0,MIN(AB252,O252+AM252-Y252))) -> 0 | AD252: =AB252*($G$9/12) -> 0 | AE252: =AE251-AF251 -> 0 | AF252: =IF(AE252>N252,N252,AE252) -> 0 | AG252: =AE252*($G$3/12) -> 0 | AH252: =AH251-AI251 -> 323841.34 | AI252: =IF(AE252>N252,0,MIN(AH252,N252-AE252)) -> 323841.34 | AJ252: =AH252*($G$6/12) -> 1349.3389 | AK252: =IF(AL251=0,AK251+AM251,AK251-AL251) -> 1311238 | AL252: =MIN(IF(AB252>0,IF(AB252>O252,0,MIN(AK252,O252-AB252)),O252),AK252) -> 1114292.8 | AM252: =AK252*($G$7/12) -> 5463.4919 | AN252: =FORECAST(B252, $AM$2:$AY$2,$AM$1:$AY$1) -> 0.040826125 | AO252: =Q252+R252 -> 0 | AP252: =Q252*B252 -> 0 | AQ252: =1/(1+(AN252+$CB$5)/12)^$B252 -> 0.27456859 | AR252: =T252+U252 -> 0 | AS252: =T252*A252 -> 0 | AT252: =1/(1+(AN252+$BV$5)/12)^$B252 -> 0.29341819 | AU252: =W252+X252 -> 0 | AV252: =W252*A252 -> 0 | AW252: =1/(1+(AN252+$BW$5)/12)^$B252 -> 0.3028041 | AX252: =IF(Y253>Y252,0,Z252+AA252) -> 0 | AY252: =A252*Z252 -> 0 | AZ252: =1/(1+(AN252+$BZ$5)/12)^$B252 -> 0.3780838 | BA252: =AC252+AD252 -> 0 | BB252: =AC252*A252 -> 0 | BC252: =1/(1+(AN252+$CA$5)/12)^$B252 -> 0.33109779 | BD252: =AF252+AG252 -> 0 | BE252: =AF252*A252 -> 0 | BF252: =1/(1+(AN252+$BU$5)/12)^$B252 -> 0.31260792 | BG252: =AI252+AJ252 -> 325190.68 | BH252: =AI252*A252 -> 77721922 | BI252: =1/(1+(AN252+$BX$5)/12)^$B252 -> 0.34572868 | BJ252: =IF(AK253>AK252,0,AL252+AM252) -> 1119756.3 | BK252: =A252*AL252 -> 2.6743027e+08 | BL252: =1/(1+(AN252+$BY$5)/12)^$B252 -> 0.36305816 | BM252: =AO252+AR252+AU252+AX252+BA252+BD252+BG252+BJ252 -> 1444947 | BN252: =M252*B252 -> 3.3796152e+08 | BO252: =1/(1+(AN252+$CC$5)/12)^$B252 -> 0.32635589
AJ253: Z(accrual) | AK253: =AK252-AL252 -> 196945.26

Sheet Inverse Yield Curve
A1: Zoom | AB1: Months | AC1: Starting balance | AD1: payment | AE1: interest+Servicing | AF1: principal | AG1: remaining balance | AL1: Date | AM1: 1 | AN1: 2 | AO1: 3 | AP1: 4 | AQ1: 6 | AR1: 12 | AS1: 24 | AT1: 36 | AU1: 60 | AV1: 84 | AW1: 120 | AX1: 240 | AY1: 360 | BA1: Weighted Average Life Sensitivity Analysis
E2: Traunches | F2: Par Amount | G2: Coupon Rate | H2: WAL Calc | AB2: 1 | AC2: =F11 -> 206500000 | AD2: =PMT($K$4/12,$K$7-AB2+1,-AC2) -> 1428195.9 | AE2: =AC2*$K$4/12 -> 957815.83 | AF2: =AD2-AE2 -> 470380.09 | AG2: =AC2-AF2 -> 2.0602962e+08 | AI2: Traunches | AJ2: WAL | AL2: Inverse | AM2: =AY3 -> 0.0443 | AN2: =AX3 -> 0.0447 | AO2: =AW3 -> 0.0383 | AP2: =AV3 -> 0.0345 | AQ2: =AU3 -> 0.031 | AR2: =AT3 -> 0.026 | AS2: =AS3 -> 0.0236 | AT2: =AR3 -> 0.0217 | AU2: =AQ3 -> 0.0197 | AV2: =AP3 -> N/A | AW2: =AO3 -> 0.0172 | AX2: =AN3 -> N/A | AY2: =AN2 -> 0.0447 | BA2: PSA Speed | BB2: Tranche CA | BC2: PSA Speed | BD2: Tranche CG | BE2: PSA Speed | BF2: Tranche CM | BG2: PSA Speed | BH2: Tranche CY | BI2: PSA Speed | BJ2: Tranche CZ | BK2: PSA Speed | BL2: Tranche GZ | BM2: PSA Speed | BN2: Tranche TC | BO2: PSA Speed | BP2: Tranche VE | BQ2: PSA Speed | BR2: Collateral | BU2: CA | BV2: CG | BW2: CM | BX2: CY | BY2: CZ | BZ2: GZ | CA2: TC | CB2: VE | CC2: Collateral
E3: CA | F3: 32550000 | G3: 0.05 | H3: =F3*G3 -> 1627500 | J3: Assumptions | L3: Asset Principal Amount | AB3: 2 | AC3: =AG2 -> 2.0602962e+08 | AD3: =PMT($K$4/12,$K$7-AB3+1,-AC3) -> 1428195.9 | AE3: =AC3*$K$4/12 -> 955634.05 | AF3: =AD3-AE3 -> 472561.87 | AG3: =AC3-AF3 -> 2.0555706e+08 | AI3: CA | AJ3: =SUM(BE18:BE252)/(12*F3) -> 4.2406411 | AL3: 39689 | AM3: 0.0163 | AN3: N/A | AO3: 0.0172 | AP3: N/A | AQ3: 0.0197 | AR3: 0.0217 | AS3: 0.0236 | AT3: 0.026 | AU3: 0.031 | AV3: 0.0345 | AW3: 0.0383 | AX3: 0.0447 | AY3: 0.0443 | BA3: 0 | BB3: =AJ3 -> 4.2406411 | BC3: 0 | BD3: =AJ4 -> 2.7691282 | BE3: 0 | BF3: =AJ5 -> 5.2494224 | BG3: 0 | BH3: =AJ6 -> 12.809991 | BI3: 0 | BJ3: =AJ7 -> 13.629662 | BK3: 0 | BL3: =AJ8 -> 6.7727119 | BM3: 0 | BN3: =AJ9 -> 8.8868058 | BO3: 0 | BP3: =AJ10 -> 2.2429547 | BQ3: 0 | BR3: =AJ11 -> 6.3947795 | BT3: Value | BU3: =SUMPRODUCT(BD$18:BD$252,BF$18:BF$252) -> 32549912 | BV3: =SUMPRODUCT(AR$18:AR$252,AT$18:AT$252) -> 74799836 | BW3: =SUMPRODUCT(AU$18:AU$252,AW$18:AW$252) -> 13999917 | BX3: =SUMPRODUCT(BG$18:BG$252,BI$18:BI$252) -> 13949894 | BY3: =SUMPRODUCT(BL$18:BL$252,BJ$18:BJ$252) -> 23999782 | BZ3: =SUMPRODUCT(AX$18:AX$252,AZ$18:AZ$252) -> 24002328 | CA3: =SUMPRODUCT(BA$18:BA$252,BC$18:BC$252) -> 19999839 | CB3: =SUMPRODUCT(AO$18:AO$252,AQ$18:AQ$252) -> 5200000 | CC3: =SUMPRODUCT(BM$18:BM$252,BO$18:BO$252) -> 2.0650012e+08
E4: CG | F4: 74800000 | G4: 0.05 | H4: =F4*G4 -> 3740000 | J4: WAC | K4: =5.566% -> 0.05566 | L4: CA & CY | M4: 0.2251816 | N4: GROUP A | AB4: 3 | AC4: =AG3 -> 2.0555706e+08 | AD4: =PMT($K$4/12,$K$7-AB4+1,-AC4) -> 1428195.9 | AE4: =AC4*$K$4/12 -> 953442.15 | AF4: =AD4-AE4 -> 474753.77 | AG4: =AC4-AF4 -> 2.050823e+08 | AI4: CG | AJ4: =SUM(AS18:AS252)/(12*F4) -> 2.7691282 | BA4: 100 | BB4: 5.674315 | BC4: 100 | BD4: 3.5204846 | BE4: 100 | BF4: 6.6167879 | BG4: 100 | BH4: 15.403897 | BI4: 100 | BJ4: 15.753771 | BK4: 100 | BL4: 8.6773068 | BM4: 100 | BN4: 11.192287 | BO4: 100 | BP4: 2.2429547 | BQ4: 100 | BR4: 8.1765229 | BT4: Difference | BU4: =BU3-F3 -> -88.408769 | BV4: =BV3-F4 -> -164.46602 | BW4: =BW3-F5 -> -83.341595 | BX4: =BX3-F6 -> -106.04694 | BY4: =BY3-F7 -> -217.80597 | BZ4: =BZ3-F7 -> 2328.4656 | CA4: =CA3-F9 -> -161.07782 | CB4: =CB3-F10 -> -8.4595755e-05 | CC4: =CC3-F11 -> 117.07575
E5: CM | F5: 14000000 | G5: 0.05 | H5: =F5*G5 -> 700000 | J5: PSA | K5: 183 | L5: CG, VE, CM, GZ,TC &CZ | M5: 0.7748184 | N5: GROUP B | AB5: 4 | AC5: =AG4 -> 2.050823e+08 | AD5: =PMT($K$4/12,$K$7-AB5+1,-AC5) -> 1428195.9 | AE5: =AC5*$K$4/12 -> 951240.09 | AF5: =AD5-AE5 -> 476955.84 | AG5: =AC5-AF5 -> 2.0460535e+08 | AI5: CM | AJ5: =SUM(AV18:AV252)/(12*F5) -> 5.2494224 | BA5: 183 | BB5: 4.2406411 | BC5: 183 | BD5: 2.7691282 | BE5: 183 | BF5: 5.2494224 | BG5: 183 | BH5: 12.809991 | BI5: 183 | BJ5: 13.629662 | BK5: 183 | BL5: 6.7727119 | BM5: 183 | BN5: 8.8868058 | BO5: 183 | BP5: 2.2429547 | BQ5: 183 | BR5: 6.3947795 | BT5: X* | BU5: 0.018578899 | BV5: 0.018946407 | BW5: 0.018595214 | BX5: 0.017279956 | BY5: 0.016580002 | BZ5: 0.0044188321 | CA5: 0.017966763 | CB5: 0.018949117 | CC5: 0.017784164
E6: CY | F6: 13950000 | G6: 0.05 | H6: =F6*G6 -> 697500 | J6: CPR | K6: 0.06 | AB6: 5 | AC6: =AG5 -> 2.0460535e+08 | AD6: =PMT($K$4/12,$K$7-AB6+1,-AC6) -> 1428195.9 | AE6: =AC6*$K$4/12 -> 949027.81 | AF6: =AD6-AE6 -> 479168.12 | AG6: =AC6-AF6 -> 2.0412618e+08 | AI6: CY | AJ6: =SUM(BH18:BH252)/(12*F6) -> 12.809991 | AO6: =AY3-AM3 -> 0.028 | BA6: 300 | BB6: 3.2177338 | BC6: 300 | BD6: 2.2376972 | BE6: 300 | BF6: 4.0739692 | BG6: 300 | BH6: 9.8596467 | BI6: 300 | BJ6: 10.973218 | BK6: 300 | BL6: 5.1671645 | BM6: 300 | BN6: 6.7889253 | BO6: 300 | BP6: 2.124623 | BQ6: 300 | BR6: 4.793641
E7: CZ | F7: 24000000 | G7: 0.05 | H7: =F7*G7 -> 1200000 | J7: Term (m) | K7: 240 | AI7: CZ | AJ7: =SUM(BK18:BK252)/(12*AL12) -> 13.629662 | AO7: =AO6/2 -> 0.014 | BA7: 400 | BB7: 2.7334889 | BC7: 400 | BD7: 1.9791573 | BE7: 400 | BF7: 3.4818708 | BG7: 400 | BH7: 8.073956 | BI7: 400 | BJ7: 9.1629434 | BK7: 400 | BL7: 4.3421672 | BM7: 400 | BN7: 5.6565095 | BO7: 400 | BP7: 1.9522052 | BQ7: 400 | BR7: 3.9189624
E8: GZ | F8: 22000000 | G8: 0.05 | H8: =F8*G8 -> 1100000 | J8: Term to Maturity | K8: 235 | AI8: GZ | AJ8: =SUM(AY18:AY252)/(12*AL11) -> 6.7727119 | AO8: =AO7/2 -> 0.007
E9: TC | F9: 20000000 | G9: 0.05 | H9: =F9*G9 -> 1000000 | AI9: TC | AJ9: =SUM(BB18:BB252)/(12*F9) -> 8.8868058
E10: VE | F10: 5200000 | G10: 0.05 | H10: =F10*G10 -> 260000 | K10: Assets | AI10: VE | AJ10: =SUM(AP18:AP252)/(12*F10) -> 2.2429547 | AN10: =AM1 -> 1 | AO10: =AY1 -> 360 | BT10: x
E11: The Assets | F11: =SUM(F3:F10) -> 206500000 | G11: 0.05 | H11: =SUM(H3:H10) -> 10325000 | J11: Balance | K11: 206500000 | AI11: Collateral | AJ11: =SUM(BN18:BN252)/(12*F11) -> 6.3947795 | AK11: Max GZ | AL11: =MAX(Y18:Y252) -> 28469664 | AN11: =AM2 -> 0.0443 | AO11: =AY2 -> 0.0447 | BT11: PSA Speed | BU11: Tranche CA | BV11: Tranche CG | BW11: Tranche CM | BX11: Tranche CY | BY11: Tranche CZ | BZ11: Tranche GZ | CA11: Tranche TC | CB11: Tranche VE | CC11: Collateral
J12: Term | K12: 235 | AK12: Max CZ | AL12: =MAX(AK18:AK252) -> 38394299 | BT12: 0 | BU12: =BU5 -> 0.018578899 | BV12: =BV5 -> 0.018946407 | BW12: =BW5 -> 0.018595214 | BX12: =BX5 -> 0.017279956 | BY12: =BY5 -> 0.016580002 | BZ12: =BZ5 -> 0.0044188321 | CA12: =CA5 -> 0.017966763 | CB12: =CB5 -> 0.018949117 | CC12: =CC5 -> 0.017784164
J13: WACC | K13: 0.05566 | Q13: Principal Check | T13: Principal Check | W13: Principal Check | Z13: Principal Check | AC13: Principal Check | AF13: Principal Check | AI13: Principal Check | AL13: Principal Check | BT13: 100 | BU13: ='PSA 100 vs X'!BU5 -> 0.02192039 | BV13: ='PSA 100 vs X'!BV5 -> 0.024446806 | BW13: ='PSA 100 vs X'!BW5 -> 0.022364026 | BX13: ='PSA 100 vs X'!BX5 -> 0.015325083 | BY13: ='PSA 100 vs X'!BY5 -> 0.013014966 | BZ13: ='PSA 100 vs X'!BZ5 -> 0.0094330705 | CA13: ='PSA 100 vs X'!CA5 -> 0.018586373 | CB13: ='PSA 100 vs X'!CB5 -> 0.025358489 | CC13: ='PSA 100 vs X'!CC5 -> 0.018573832
Q14: =SUM(Q18:Q252) -> 5200000 | T14: =SUM(T18:T252) -> 74800000 | W14: =SUM(W18:W252) -> 14000000 | Z14: =SUM(Z18:Z252) -> 28469664 | AC14: =SUM(AC18:AC252) -> 20000000 | AF14: =SUM(AF18:AF252) -> 32550000 | AI14: =SUM(AI18:AI252) -> 13950000 | AL14: =SUM(AL18:AL252) -> 38120709 | BT14: 183 | BU14: {='PSA 183 on X'!BU5:CC5} -> 0.023516729 | BV14: 0.025345018 | BW14: 0.023591729 | BX14: 0.017086336 | BY14: 0.014918714 | BZ14: 0.00807609 | CA14: 0.020458943 | CB14: 0.025358489 | CC14: 0.020014572
BT15: 300 | BU15: {='PSA 300 vs X'!BU5:CC5} -> 0.02475377 | BV15: 0.025986937 | BW15: 0.024644633 | BX15: 0.019234935 | BY15: 0.017050756 | BZ15: 0.0050007568 | CA15: 0.022223415 | CB15: 0.025575242 | CC15: 0.021548058
N16: Asset Prinicpal Amount | Q16: Tranche VE | T16: Tranche CG | W16: Tranche CM | Z16: Tranche GZ | AC16: Tranche TC | AF16: Tranche CA | AH16: Tranche CY | AK16: Tranche CZ | AN16: Treasury | AP16: Tranche VE | AS16: Tranche CG | AV16: Tranche CM | AY16: Tranche GZ | BB16: Tranche TC | BE16: Tranche CA | BG16: Tranche CY | BJ16: Tranche CZ | BM16: Collateral | BT16: 400 | BU16: {='PSA 400 on X'!BU5:CC5} -> 0.025355313 | BV16: 0.026294327 | BW16: 0.02519042 | BX16: 0.020661746 | BY16: 0.018584184 | BZ16: 0.001909631 | CA16: 0.023220943 | CB16: 0.025850064 | CC16: 0.022559104
A17: CPR Month | B17: Month | C17: Principal | E17: Asset Principal | F17: Payment | G17: Interest+Servicing | H17: Principal | I17: CPR | J17: SMM | K17: Prepayment | L17: Total Collateral CF | M17: Excess CF | N17: Group A | O17: Group B | P17: Balance | Q17: Principal2 | R17: Interest | S17: Balance5 | T17: Principal6 | U17: Interest7 | V17: Balance8 | W17: Principal9 | X17: Interest | Y17: Balance11 | Z17: Principal12 | AA17: Interest(Z) | AB17: Balance14 | AC17: Principal15 | AD17: Interest16 | AE17: Balance20 | AF17: Principal21 | AG17: Interest22 | AH17: Balance202 | AI17: Principal213 | AJ17: Interest224 | AK17: Balance3 | AL17: Principal4 | AM17: Interest(Z) | AN17: Yield Curve | AO17: Cash Flow | AP17: Average life | AQ17: Discount Factor | AR17: Cash Flow | AS17: Average life | AT17: Discount Factor | AU17: Cash Flow | AV17: Average life | AW17: Discount Factor | AX17: Cash Flow | AY17: Average life | AZ17: Discount Factor | BA17: Cash Flow | BB17: Average life | BC17: Discount Factor | BD17: Cash Flow | BE17: Average life | BF17: Discount Factor | BG17: Cash Flow | BH17: Average life | BI17: Discount Factor | BJ17: Cash Flow | BK17: Average life | BL17: Discount Factor | BM17: Cash Flow | BN17: Average life | BO17: Discount Factor
A18: 6 | B18: 1 | C18: =P18+S18+V18+Y18+AB18+AE18+AH18+AK18 -> 206500000 | D18: =C18-E18 -> 0 | E18: =$F$11 -> 206500000 | F18: =PMT($K$13/12,$K$12-B18+1,-E18,0) -> 1444804.7 | G18: =E18*$K$13/12 -> 957815.83 | H18: =F18-G18 -> 486988.84 | I18: =IF(A18<=(30-(240-$K$8)),((B18+(240-$K$7))/30)*$K$6,$K$6)*($K$5/100) -> 0.00366 | J18: =1-(1-I18)^(1/12) -> 0.00030551284 | K18: =(E18-H18)*J18 -> 62939.62 | L18: =K18+H18+G18 -> 1507744.3 | M18: =L18-G18 -> 549928.46 | N18: =M18*$M$4 -> 123833.77 | O18: =M18*$M$5 -> 426094.69 | P18: =$F$10 -> 5200000 | Q18: =MIN(IF(S18>O18,0,MIN(P18,O18-S18))+IF(P18>0,MIN(AA18,P18)),P18) -> 91666.667 | R18: =P18*($G$10/12) -> 21666.667 | S18: =$F$4 -> 74800000 | T18: =MIN(IF(S18>O18,O18,S18)+IF(S18>0,AM18,0),S18) -> 526094.69 | U18: =S18*($G$4/12) -> 311666.67 | V18: =$F$5 -> 14000000 | W18: =IF(T18+P18<=O18+AM18+AA18,MIN(V18,O18-Q18+AA18-T18+AM18),0) -> 0 | X18: =V18*($G$5/12) -> 58333.333 | Y18: =$F$8 -> 22000000 | Z18: =IF(V18>O18,0,MIN(Y18,O18-V18)) -> 0 | AA18: =Y18*($G$8/12) -> 91666.667 | AB18: =F9 -> 20000000 | AC18: =MIN(IF(Y18>O18,0,MIN(AB18,O18+AM18-Y18))) -> 0 | AD18: =AB18*($G$9/12) -> 83333.333 | AE18: =F3 -> 32550000 | AF18: =IF(AE18>N18,N18,AE18) -> 123833.77 | AG18: =AE18*($G$3/12) -> 135625 | AH18: =F6 -> 13950000 | AI18: =IF(AE18>N18,0,MIN(AH18,N18-AE18)) -> 0 | AJ18: =AH18*($G$6/12) -> 58125 | AK18: =F7 -> 24000000 | AL18: =IF(AB18>0,IF(AB18>O18,0,MIN(AK18,O18-AB18)),O18) -> 0 | AM18: =AK18*($G$7/12) -> 100000 | AN18: =FORECAST(B18, $AM$2:$AY$2,$AM$1:$AY$1) -> 0.030523604 | AO18: =Q18+R18 -> 113333.33 | AP18: =Q18*B18 -> 91666.667 | AQ18: =1/(1+(AN18+$CB$5)/12)^$B18 -> 0.9958942 | AR18: =T18+U18 -> 837761.36 | AS18: =T18*A18 -> 3156568.1 | AT18: =1/(1+(AN18+$BV$5)/12)^$B18 -> 0.99589442 | AU18: =W18+X18 -> 58333.333 | AV18: =W18*A18 -> 0 | AW18: =1/(1+(AN18+$BW$5)/12)^$B18 -> 0.99592345 | AX18: =IF(Y19>Y18,0,Z18+AA18) -> 0 | AY18: =A18*Z18 -> 0 | AZ18: =1/(1+(AN18+$BZ$5)/12)^$B18 -> 0.99709658 | BA18: =AC18+AD18 -> 83333.333 | BB18: =AC18*A18 -> 0 | BC18: =1/(1+(AN18+$CA$5)/12)^$B18 -> 0.9959754 | BD18: =AF18+AG18 -> 259458.77 | BE18: =AF18*A18 -> 743002.61 | BF18: =1/(1+(AN18+$BU$5)/12)^$B18 -> 0.9959248 | BG18: =AI18+AJ18 -> 58125 | BH18: =AI18*A18 -> 0 | BI18: =1/(1+(AN18+$BX$5)/12)^$B18 -> 0.99603218 | BJ18: =IF(AK19>AK18,0,AL18+AM18) -> 0 | BK18: =A18*AL18 -> 0 | BL18: =1/(1+(AN18+$BY$5)/12)^$B18 -> 0.99609005 | BM18: =AO18+AR18+AU18+AX18+BA18+BD18+BG18+BJ18 -> 1410345.1 | BN18: =M18*B18 -> 549928.46 | BO18: =1/(1+(AN18+$CC$5)/12)^$B18 -> 0.99599049
A19: 7 | B19: 2 | C19: =P19+S19+V19+Y19+AB19+AE19+AH19+AK19 -> 2.0595007e+08 | D19: =C19-E19 -> 0 | E19: =E18-H18-K18 -> 2.0595007e+08 | F19: =PMT($K$13/12,$K$12-B19+1,-E19,0) -> 1444363.3 | G19: =E19*$K$13/12 -> 955265.08 | H19: =F19-G19 -> 489098.18 | I19: =IF(A19<=(30-(240-$K$8)),((A19+(240-$K$7))/30)*$K$6,$K$6)*($K$5/100) -> 0.02562 | J19: =1-(1-I19)^(1/12) -> 0.0021604884 | K19: =(E19-H19)*J19 -> 443896.05 | L19: =K19+H19+G19 -> 1888259.3 | M19: =L19-G19 -> 932994.24 | N19: =M19*$M$4 -> 210093.13 | O19: =M19*$M$5 -> 722901.1 | P19: =P18-Q18 -> 5108333.3 | Q19: =MIN(IF(S19>O19,0,MIN(P19,O19-S19))+IF(P19>0,MIN(AA19,P19)),P19) -> 92048.611 | R19: =P19*($G$10/12) -> 21284.722 | S19: =S18-T18 -> 74273905 | T19: =MIN(IF(S19>O19,O19,S19)+IF(S19>0,AM19,0),S19) -> 823317.77 | U19: =S19*($G$4/12) -> 309474.61 | V19: =V18-W18 -> 14000000 | W19: =IF(T19+P19<=O19+AM19+AA19,MIN(V19,O19-Q19+AA19-T19+AM19),0) -> 0 | X19: =V19*($G$5/12) -> 58333.333 | Y19: =IF(V18>O18,(IF(V18>AA18+O18+AM18,Y18+AA18,Y18+AA18-((AA18+O18+AM18)-V18))),Y18-Z18) -> 22091667 | Z19: =MIN(IF(V19>O19,0,MIN(Y19,O19-V19))+IF(AM18>V18,AM18,0),Y19) -> 0 | AA19: =Y19*($G$8/12) -> 92048.611 | AB19: =AB18-AC18 -> 20000000 | AC19: =MIN(IF(Y19>O19,0,MIN(AB19,O19+AM19-Y19))) -> 0 | AD19: =AB19*($G$9/12) -> 83333.333 | AE19: =AE18-AF18 -> 32426166 | AF19: =IF(AE19>N19,N19,AE19) -> 210093.13 | AG19: =AE19*($G$3/12) -> 135109.03 | AH19: =AH18-AI18 -> 13950000 | AI19: =IF(AE19>N19,0,MIN(AH19,N19-AE19)) -> 0 | AJ19: =AH19*($G$6/12) -> 58125 | AK19: =IF(AL18=0,AK18+AM18,AK18-AL18) -> 24100000 | AL19: =MIN(IF(AB19>0,IF(AB19>O19,0,MIN(AK19,O19-AB19)),O19),AK19) -> 0 | AM19: =AK19*($G$7/12) -> 100416.67 | AN19: =FORECAST(B19, $AM$2:$AY$2,$AM$1:$AY$1) -> 0.030539715 | AO19: =Q19+R19 -> 113333.33 | AP19: =Q19*B19 -> 184097.22 | AQ19: =1/(1+(AN19+$CB$5)/12)^$B19 -> 0.99180261 | AR19: =T19+U19 -> 1132792.4 | AS19: =T19*A19 -> 5763224.4 | AT19: =1/(1+(AN19+$BV$5)/12)^$B19 -> 0.99180305 | AU19: =W19+X19 -> 58333.333 | AV19: =W19*A19 -> 0 | AW19: =1/(1+(AN19+$BW$5)/12)^$B19 -> 0.99186087 | AX19: =IF(Y20>Y19,0,Z19+AA19) -> 0 | AY19: =A19*Z19 -> 0 | AZ19: =1/(1+(AN19+$BZ$5)/12)^$B19 -> 0.99419894 | BA19: =AC19+AD19 -> 83333.333 | BB19: =AC19*A19 -> 0 | BC19: =1/(1+(AN19+$CA$5)/12)^$B19 -> 0.99196434 | BD19: =AF19+AG19 -> 345202.16 | BE19: =AF19*A19 -> 1470651.9 | BF19: =1/(1+(AN19+$BU$5)/12)^$B19 -> 0.99186355 | BG19: =AI19+AJ19 -> 58125 | BH19: =AI19*A19 -> 0 | BI19: =1/(1+(AN19+$BX$5)/12)^$B19 -> 0.99207744 | BJ19: =IF(AK20>AK19,0,AL19+AM19) -> 0 | BK19: =A19*AL19 -> 0 | BL19: =1/(1+(AN19+$BY$5)/12)^$B19 -> 0.99219273 | BM19: =AO19+AR19+AU19+AX19+BA19+BD19+BG19+BJ19 -> 1791119.5 | BN19: =M19*B19 -> 1865988.5 | BO19: =1/(1+(AN19+$CC$5)/12)^$B19 -> 0.99199441
A20: 8 | B20: 3 | C20: =P20+S20+V20+Y20+AB20+AE20+AH20+AK20 -> 2.0501708e+08 | D20: =C20-E20 -> 0 | E20: =E19-H19-K19 -> 2.0501708e+08 | F20: =PMT($K$13/12,$K$12-B20+1,-E20,0) -> 1441242.7 | G20: =E20*$K$13/12 -> 950937.54 | H20: =F20-G20 -> 490305.19 | I20: =IF(A20<=(30-(240-$K$8)),((A20+(240-$K$7))/30)*$K$6,$K$6)*($K$5/100) -> 0.02928 | J20: =1-(1-I20)^(1/12) -> 0.0024733707 | K20: =(E20-H20)*J20 -> 505870.53 | L20: =K20+H20+G20 -> 1947113.3 | M20: =L20-G20 -> 996175.72 | N20: =M20*$M$4 -> 224320.44 | O20: =M20*$M$5 -> 771855.28 | P20: =P19-Q19 -> 5016284.7 | Q20: =MIN(IF(S20>O20,0,MIN(P20,O20-S20))+IF(P20>0,MIN(AA20,P20)),P20) -> 92432.147 | R20: =P20*($G$10/12) -> 20901.186 | S20: =S19-T19 -> 73450588 | T20: =MIN(IF(S20>O20,O20,S20)+IF(S20>0,AM20,0),S20) -> 872690.35 | U20: =S20*($G$4/12) -> 306044.11 | V20: =V19-W19 -> 14000000 | W20: =IF(T20+P20<=O20+AM20+AA20,MIN(V20,O20-Q20+AA20-T20+AM20),0) -> 0 | X20: =V20*($G$5/12) -> 58333.333 | Y20: =IF(V19>O19,(IF(V19>AA19+O19+AM19,Y19+AA19,Y19+AA19-((AA19+O19+AM19)-V19))),Y19-Z19) -> 22183715 | Z20: =MIN(IF(V20>O20,0,MIN(Y20,O20-V20))+IF(AM19>V19,AM19,0),Y20) -> 0 | AA20: =Y20*($G$8/12) -> 92432.147 | AB20: =AB19-AC19 -> 20000000 | AC20: =MIN(IF(Y20>O20,0,MIN(AB20,O20+AM20-Y20))) -> 0 | AD20: =AB20*($G$9/12) -> 83333.333 | AE20: =AE19-AF19 -> 32216073 | AF20: =IF(AE20>N20,N20,AE20) -> 224320.44 | AG20: =AE20*($G$3/12) -> 134233.64 | AH20: =AH19-AI19 -> 13950000 | AI20: =IF(AE20>N20,0,MIN(AH20,N20-AE20)) -> 0 | AJ20: =AH20*($G$6/12) -> 58125 | AK20: =IF(AL19=0,AK19+AM19,AK19-AL19) -> 24200417 | AL20: =MIN(IF(AB20>0,IF(AB20>O20,0,MIN(AK20,O20-AB20)),O20),AK20) -> 0 | AM20: =AK20*($G$7/12) -> 100835.07 | AN20: =FORECAST(B20, $AM$2:$AY$2,$AM$1:$AY$1) -> 0.030555826 | AO20: =Q20+R20 -> 113333.33 | AP20: =Q20*B20 -> 277296.44 | AQ20: =1/(1+(AN20+$CB$5)/12)^$B20 -> 0.98772518 | AR20: =T20+U20 -> 1178734.5 | AS20: =T20*A20 -> 6981522.8 | AT20: =1/(1+(AN20+$BV$5)/12)^$B20 -> 0.98772585 | AU20: =W20+X20 -> 58333.333 | AV20: =W20*A20 -> 0 | AW20: =1/(1+(AN20+$BW$5)/12)^$B20 -> 0.98781222 | AX20: =IF(Y21>Y20,0,Z20+AA20) -> 0 | AY20: =A20*Z20 -> 0 | AZ20: =1/(1+(AN20+$BZ$5)/12)^$B20 -> 0.99130706 | BA20: =AC20+AD20 -> 83333.333 | BB20: =AC20*A20 -> 0 | BC20: =1/(1+(AN20+$CA$5)/12)^$B20 -> 0.9879668 | BD20: =AF20+AG20 -> 358554.08 | BE20: =AF20*A20 -> 1794563.5 | BF20: =1/(1+(AN20+$BU$5)/12)^$B20 -> 0.98781623 | BG20: =AI20+AJ20 -> 58125 | BH20: =AI20*A20 -> 0 | BI20: =1/(1+(AN20+$BX$5)/12)^$B20 -> 0.98813577 | BJ20: =IF(AK21>AK20,0,AL20+AM20) -> 0 | BK20: =A20*AL20 -> 0 | BL20: =1/(1+(AN20+$BY$5)/12)^$B20 -> 0.98830801 | BM20: =AO20+AR20+AU20+AX20+BA20+BD20+BG20+BJ20 -> 1850413.5 | BN20: =M20*B20 -> 2988527.2 | BO20: =1/(1+(AN20+$CC$5)/12)^$B20 -> 0.98801172
A21: 9 | B21: 4 | C21: =P21+S21+V21+Y21+AB21+AE21+AH21+AK21 -> 2.040209e+08 | D21: =C21-E21 -> 0 | E21: =E20-H20-K20 -> 2.040209e+08 | F21: =PMT($K$13/12,$K$12-B21+1,-E21,0) -> 1437678 | G21: =E21*$K$13/12 -> 946316.95 | H21: =F21-G21 -> 491361.06 | I21: =IF(A21<=(30-(240-$K$8)),((A21+(240-$K$7))/30)*$K$6,$K$6)*($K$5/100) -> 0.03294 | J21: =1-(1-I21)^(1/12) -> 0.0027873363 | K21: =(E21-H21)*J21 -> 567305.28 | L21: =K21+H21+G21 -> 2004983.3 | M21: =L21-G21 -> 1058666.3 | N21: =M21*$M$4 -> 238392.18 | O21: =M21*$M$5 -> 820274.16 | P21: =P20-Q20 -> 4923852.6 | Q21: =MIN(IF(S21>O21,0,MIN(P21,O21-S21))+IF(P21>0,MIN(AA21,P21)),P21) -> 92817.281 | R21: =P21*($G$10/12) -> 20516.052 | S21: =S20-T20 -> 72577897 | T21: =MIN(IF(S21>O21,O21,S21)+IF(S21>0,AM21,0),S21) -> 921529.37 | U21: =S21*($G$4/12) -> 302407.9 | V21: =V20-W20 -> 14000000 | W21: =IF(T21+P21<=O21+AM21+AA21,MIN(V21,O21-Q21+AA21-T21+AM21),0) -> 0 | X21: =V21*($G$5/12) -> 58333.333 | Y21: =IF(V20>O20,(IF(V20>AA20+O20+AM20,Y20+AA20,Y20+AA20-((AA20+O20+AM20)-V20))),Y20-Z20) -> 22276147 | Z21: =MIN(IF(V21>O21,0,MIN(Y21,O21-V21))+IF(AM20>V20,AM20,0),Y21) -> 0 | AA21: =Y21*($G$8/12) -> 92817.281 | AB21: =AB20-AC20 -> 20000000 | AC21: =MIN(IF(Y21>O21,0,MIN(AB21,O21+AM21-Y21))) -> 0 | AD21: =AB21*($G$9/12) -> 83333.333 | AE21: =AE20-AF20 -> 31991753 | AF21: =IF(AE21>N21,N21,AE21) -> 238392.18 | AG21: =AE21*($G$3/12) -> 133298.97 | AH21: =AH20-AI20 -> 13950000 | AI21: =IF(AE21>N21,0,MIN(AH21,N21-AE21)) -> 0 | AJ21: =AH21*($G$6/12) -> 58125 | AK21: =IF(AL20=0,AK20+AM20,AK20-AL20) -> 24301252 | AL21: =MIN(IF(AB21>0,IF(AB21>O21,0,MIN(AK21,O21-AB21)),O21),AK21) -> 0 | AM21: =AK21*($G$7/12) -> 101255.22 | AN21: =FORECAST(B21, $AM$2:$AY$2,$AM$1:$AY$1) -> 0.030571937 | AO21: =Q21+R21 -> 113333.33 | AP21: =Q21*B21 -> 371269.12 | AQ21: =1/(1+(AN21+$CB$5)/12)^$B21 -> 0.98366189 | AR21: =T21+U21 -> 1223937.3 | AS21: =T21*A21 -> 8293764.4 | AT21: =1/(1+(AN21+$BV$5)/12)^$B21 -> 0.98366277 | AU21: =W21+X21 -> 58333.333 | AV21: =W21*A21 -> 0 | AW21: =1/(1+(AN21+$BW$5)/12)^$B21 -> 0.98377746 | AX21: =IF(Y22>Y21,0,Z21+AA21) -> 0 | AY21: =A21*Z21 -> 0 | AZ21: =1/(1+(AN21+$BZ$5)/12)^$B21 -> 0.98842094 | BA21: =AC21+AD21 -> 83333.333 | BB21: =AC21*A21 -> 0 | BC21: =1/(1+(AN21+$CA$5)/12)^$B21 -> 0.98398273 | BD21: =AF21+AG21 -> 371691.15 | BE21: =AF21*A21 -> 2145529.6 | BF21: =1/(1+(AN21+$BU$5)/12)^$B21 -> 0.98378279 | BG21: =AI21+AJ21 -> 58125 | BH21: =AI21*A21 -> 0 | BI21: =1/(1+(AN21+$BX$5)/12)^$B21 -> 0.98420712 | BJ21: =IF(AK22>AK21,0,AL21+AM21) -> 0 | BK21: =A21*AL21 -> 0 | BL21: =1/(1+(AN21+$BY$5)/12)^$B21 -> 0.98443588 | BM21: =AO21+AR21+AU21+AX21+BA21+BD21+BG21+BJ21 -> 1908753.4 | BN21: =M21*B21 -> 4234665.3 | BO21: =1/(1+(AN21+$CC$5)/12)^$B21 -> 0.98404238
A22: 10 | B22: 5 | C22: =P22+S22+V22+Y22+AB22+AE22+AH22+AK22 -> 2.0296224e+08 | D22: =C22-E22 -> 0 | E22: =E21-H21-K21 -> 2.0296224e+08 | F22: =PMT($K$13/12,$K$12-B22+1,-E22,0) -> 1433670.7 | G22: =E22*$K$13/12 -> 941406.5 | H22: =F22-G22 -> 492264.21 | I22: =IF(A22<=(30-(240-$K$8)),((A22+(240-$K$7))/30)*$K$6,$K$6)*($K$5/100) -> 0.0366 | J22: =1-(1-I22)^(1/12) -> 0.003102393 | K22: =(E22-H22)*J22 -> 628141.42 | L22: =K22+H22+G22 -> 2061812.1 | M22: =L22-G22 -> 1120405.6 | N22: =M22*$M$4 -> 252294.73 | O22: =M22*$M$5 -> 868110.9 | P22: =P21-Q21 -> 4831035.3 | Q22: =MIN(IF(S22>O22,0,MIN(P22,O22-S22))+IF(P22>0,MIN(AA22,P22)),P22) -> 93204.02 | R22: =P22*($G$10/12) -> 20129.314 | S22: =S21-T21 -> 71656368 | T22: =MIN(IF(S22>O22,O22,S22)+IF(S22>0,AM22,0),S22) -> 969788.02 | U22: =S22*($G$4/12) -> 298568.2 | V22: =V21-W21 -> 14000000 | W22: =IF(T22+P22<=O22+AM22+AA22,MIN(V22,O22-Q22+AA22-T22+AM22),0) -> 0 | X22: =V22*($G$5/12) -> 58333.333 | Y22: =IF(V21>O21,(IF(V21>AA21+O21+AM21,Y21+AA21,Y21+AA21-((AA21+O21+AM21)-V21))),Y21-Z21) -> 22368965 | Z22: =MIN(IF(V22>O22,0,MIN(Y22,O22-V22))+IF(AM21>V21,AM21,0),Y22) -> 0 | AA22: =Y22*($G$8/12) -> 93204.02 | AB22: =AB21-AC21 -> 20000000 | AC22: =MIN(IF(Y22>O22,0,MIN(AB22,O22+AM22-Y22))) -> 0 | AD22: =AB22*($G$9/12) -> 83333.333 | AE22: =AE21-AF21 -> 31753360 | AF22: =IF(AE22>N22,N22,AE22) -> 252294.73 | AG22: =AE22*($G$3/12) -> 132305.67 | AH22: =AH21-AI21 -> 13950000 | AI22: =IF(AE22>N22,0,MIN(AH22,N22-AE22)) -> 0 | AJ22: =AH22*($G$6/12) -> 58125 | AK22: =IF(AL21=0,AK21+AM21,AK21-AL21) -> 24402507 | AL22: =MIN(IF(AB22>0,IF(AB22>O22,0,MIN(AK22,O22-AB22)),O22),AK22) -> 0 | AM22: =AK22*($G$7/12) -> 101677.11 | AN22: =FORECAST(B22, $AM$2:$AY$2,$AM$1:$AY$1) -> 0.030588047 | AO22: =Q22+R22 -> 113333.33 | AP22: =Q22*B22 -> 466020.1 | AQ22: =1/(1+(AN22+$CB$5)/12)^$B22 -> 0.97961269 | AR22: =T22+U22 -> 1268356.2 | AS22: =T22*A22 -> 9697880.2 | AT22: =1/(1+(AN22+$BV$5)/12)^$B22 -> 0.97961379 | AU22: =W22+X22 -> 58333.333 | AV22: =W22*A22 -> 0 | AW22: =1/(1+(AN22+$BW$5)/12)^$B22 -> 0.97975656 | AX22: =IF(Y23>Y22,0,Z22+AA22) -> 0 | AY22: =A22*Z22 -> 0 | AZ22: =1/(1+(AN22+$BZ$5)/12)^$B22 -> 0.98554059 | BA22: =AC22+AD22 -> 83333.333 | BB22: =AC22*A22 -> 0 | BC22: =1/(1+(AN22+$CA$5)/12)^$B22 -> 0.98001211 | BD22: =AF22+AG22 -> 384600.4 | BE22: =AF22*A22 -> 2522947.3 | BF22: =1/(1+(AN22+$BU$5)/12)^$B22 -> 0.9797632 | BG22: =AI22+AJ22 -> 58125 | BH22: =AI22*A22 -> 0 | BI22: =1/(1+(AN22+$BX$5)/12)^$B22 -> 0.98029148 | BJ22: =IF(AK23>AK22,0,AL22+AM22) -> 0 | BK22: =A22*AL22 -> 0 | BL22: =1/(1+(AN22+$BY$5)/12)^$B22 -> 0.98057629 | BM22: =AO22+AR22+AU22+AX22+BA22+BD22+BG22+BJ22 -> 1966081.6 | BN22: =M22*B22 -> 5602028.2 | BO22: =1/(1+(AN22+$CC$5)/12)^$B22 -> 0.98008637
A23: 11 | B23: 6 | C23: =P23+S23+V23+Y23+AB23+AE23+AH23+AK23 -> 2.0184183e+08 | D23: =C23-E23 -> 0 | E23: =E22-H22-K22 -> 2.0184183e+08 | F23: =PMT($K$13/12,$K$12-B23+1,-E23,0) -> 1429222.9 | G23: =E23*$K$13/12 -> 936209.69 | H23: =F23-G23 -> 493013.22 | I23: =IF(A23<=(30-(240-$K$8)),((A23+(240-$K$7))/30)*$K$6,$K$6)*($K$5/100) -> 0.04026 | J23: =1-(1-I23)^(1/12) -> 0.0034185488 | K23: =(E23-H23)*J23 -> 688320.75 | L23: =K23+H23+G23 -> 2117543.7 | M23: =L23-G23 -> 1181334 | N23: =M23*$M$4 -> 266014.67 | O23: =M23*$M$5 -> 915319.3 | P23: =P22-Q22 -> 4737831.3 | Q23: =MIN(IF(S23>O23,0,MIN(P23,O23-S23))+IF(P23>0,MIN(AA23,P23)),P23) -> 93592.37 | R23: =P23*($G$10/12) -> 19740.964 | S23: =S22-T22 -> 70686580 | T23: =MIN(IF(S23>O23,O23,S23)+IF(S23>0,AM23,0),S23) -> 1017420.1 | U23: =S23*($G$4/12) -> 294527.42 | V23: =V22-W22 -> 14000000 | W23: =IF(T23+P23<=O23+AM23+AA23,MIN(V23,O23-Q23+AA23-T23+AM23),0) -> 0 | X23: =V23*($G$5/12) -> 58333.333 | Y23: =IF(V22>O22,(IF(V22>AA22+O22+AM22,Y22+AA22,Y22+AA22-((AA22+O22+AM22)-V22))),Y22-Z22) -> 22462169 | Z23: =MIN(IF(V23>O23,0,MIN(Y23,O23-V23))+IF(AM22>V22,AM22,0),Y23) -> 0 | AA23: =Y23*($G$8/12) -> 93592.37 | AB23: =AB22-AC22 -> 20000000 | AC23: =MIN(IF(Y23>O23,0,MIN(AB23,O23+AM23-Y23))) -> 0 | AD23: =AB23*($G$9/12) -> 83333.333 | AE23: =AE22-AF22 -> 31501066 | AF23: =IF(AE23>N23,N23,AE23) -> 266014.67 | AG23: =AE23*($G$3/12) -> 131254.44 | AH23: =AH22-AI22 -> 13950000 | AI23: =IF(AE23>N23,0,MIN(AH23,N23-AE23)) -> 0 | AJ23: =AH23*($G$6/12) -> 58125 | AK23: =IF(AL22=0,AK22+AM22,AK22-AL22) -> 24504184 | AL23: =MIN(IF(AB23>0,IF(AB23>O23,0,MIN(AK23,O23-AB23)),O23),AK23) -> 0 | AM23: =AK23*($G$7/12) -> 102100.77 | AN23: =FORECAST(B23, $AM$2:$AY$2,$AM$1:$AY$1) -> 0.030604158 | AO23: =Q23+R23 -> 113333.33 | AP23: =Q23*B23 -> 561554.22 | AQ23: =1/(1+(AN23+$CB$5)/12)^$B23 -> 0.97557755 | AR23: =T23+U23 -> 1311947.5 | AS23: =T23*A23 -> 11191621 | AT23: =1/(1+(AN23+$BV$5)/12)^$B23 -> 0.97557887 | AU23: =W23+X23 -> 58333.333 | AV23: =W23*A23 -> 0 | AW23: =1/(1+(AN23+$BW$5)/12)^$B23 -> 0.97574949 | AX23: =IF(Y24>Y23,0,Z23+AA23) -> 0 | AY23: =A23*Z23 -> 0 | AZ23: =1/(1+(AN23+$BZ$5)/12)^$B23 -> 0.982666 | BA23: =AC23+AD23 -> 83333.333 | BB23: =AC23*A23 -> 0 | BC23: =1/(1+(AN23+$CA$5)/12)^$B23 -> 0.9760549 | BD23: =AF23+AG23 -> 397269.11 | BE23: =AF23*A23 -> 2926161.4 | BF23: =1/(1+(AN23+$BU$5)/12)^$B23 -> 0.97575742 | BG23: =AI23+AJ23 -> 58125 | BH23: =AI23*A23 -> 0 | BI23: =1/(1+(AN23+$BX$5)/12)^$B23 -> 0.9763888 | BJ23: =IF(AK24>AK23,0,AL23+AM23) -> 0 | BK23: =A23*AL23 -> 0 | BL23: =1/(1+(AN23+$BY$5)/12)^$B23 -> 0.97672922 | BM23: =AO23+AR23+AU23+AX23+BA23+BD23+BG23+BJ23 -> 2022341.6 | BN23: =M23*B23 -> 7088003.8 | BO23: =1/(1+(AN23+$CC$5)/12)^$B23 -> 0.97614366
A24: 12 | B24: 7 | C24: =P24+S24+V24+Y24+AB24+AE24+AH24+AK24 -> 2.006605e+08 | D24: =C24-E24 -> 0 | E24: =E23-H23-K23 -> 2.006605e+08 | F24: =PMT($K$13/12,$K$12-B24+1,-E24,0) -> 1424337 | G24: =E24*$K$13/12 -> 930730.27 | H24: =F24-G24 -> 493606.77 | I24: =IF(A24<=(30-(240-$K$8)),((A24+(240-$K$7))/30)*$K$6,$K$6)*($K$5/100) -> 0.04392 | J24: =1-(1-I24)^(1/12) -> 0.0037358117 | K24: =(E24-H24)*J24 -> 747785.81 | L24: =K24+H24+G24 -> 2172122.8 | M24: =L24-G24 -> 1241392.6 | N24: =M24*$M$4 -> 279538.76 | O24: =M24*$M$5 -> 961853.81 | P24: =P23-Q23 -> 4644238.9 | Q24: =MIN(IF(S24>O24,0,MIN(P24,O24-S24))+IF(P24>0,MIN(AA24,P24)),P24) -> 93982.338 | R24: =P24*($G$10/12) -> 19350.995 | S24: =S23-T23 -> 69669160 | T24: =MIN(IF(S24>O24,O24,S24)+IF(S24>0,AM24,0),S24) -> 1064380 | U24: =S24*($G$4/12) -> 290288.17 | V24: =V23-W23 -> 14000000 | W24: =IF(T24+P24<=O24+AM24+AA24,MIN(V24,O24-Q24+AA24-T24+AM24),0) -> 0 | X24: =V24*($G$5/12) -> 58333.333 | Y24: =IF(V23>O23,(IF(V23>AA23+O23+AM23,Y23+AA23,Y23+AA23-((AA23+O23+AM23)-V23))),Y23-Z23) -> 22555761 | Z24: =MIN(IF(V24>O24,0,MIN(Y24,O24-V24))+IF(AM23>V23,AM23,0),Y24) -> 0 | AA24: =Y24*($G$8/12) -> 93982.338 | AB24: =AB23-AC23 -> 20000000 | AC24: =MIN(IF(Y24>O24,0,MIN(AB24,O24+AM24-Y24))) -> 0 | AD24: =AB24*($G$9/12) -> 83333.333 | AE24: =AE23-AF23 -> 31235051 | AF24: =IF(AE24>N24,N24,AE24) -> 279538.76 | AG24: =AE24*($G$3/12) -> 130146.05 | AH24: =AH23-AI23 -> 13950000 | AI24: =IF(AE24>N24,0,MIN(AH24,N24-AE24)) -> 0 | AJ24: =AH24*($G$6/12) -> 58125 | AK24: =IF(AL23=0,AK23+AM23,AK23-AL23) -> 24606285 | AL24: =MIN(IF(AB24>0,IF(AB24>O24,0,MIN(AK24,O24-AB24)),O24),AK24) -> 0 | AM24: =AK24*($G$7/12) -> 102526.19 | AN24: =FORECAST(B24, $AM$2:$AY$2,$AM$1:$AY$1) -> 0.030620269 | AO24: =Q24+R24 -> 113333.33 | AP24: =Q24*B24 -> 657876.37 | AQ24: =1/(1+(AN24+$CB$5)/12)^$B24 -> 0.97155644 | AR24: =T24+U24 -> 1354668.2 | AS24: =T24*A24 -> 12772560 | AT24: =1/(1+(AN24+$BV$5)/12)^$B24 -> 0.97155797 | AU24: =W24+X24 -> 58333.333 | AV24: =W24*A24 -> 0 | AW24: =1/(1+(AN24+$BW$5)/12)^$B24 -> 0.97175621 | AX24: =IF(Y25>Y24,0,Z24+AA24) -> 0 | AY24: =A24*Z24 -> 0 | AZ24: =1/(1+(AN24+$BZ$5)/12)^$B24 -> 0.97979718 | BA24: =AC24+AD24 -> 83333.333 | BB24: =AC24*A24 -> 0 | BC24: =1/(1+(AN24+$CA$5)/12)^$B24 -> 0.97211107 | BD24: =AF24+AG24 -> 409684.81 | BE24: =AF24*A24 -> 3354465.2 | BF24: =1/(1+(AN24+$BU$5)/12)^$B24 -> 0.97176542 | BG24: =AI24+AJ24 -> 58125 | BH24: =AI24*A24 -> 0 | BI24: =1/(1+(AN24+$BX$5)/12)^$B24 -> 0.97249905 | BJ24: =IF(AK25>AK24,0,AL24+AM24) -> 0 | BK24: =A24*AL24 -> 0 | BL24: =1/(1+(AN24+$BY$5)/12)^$B24 -> 0.97289464 | BM24: =AO24+AR24+AU24+AX24+BA24+BD24+BG24+BJ24 -> 2077478 | BN24: =M24*B24 -> 8689748.1 | BO24: =1/(1+(AN24+$CC$5)/12)^$B24 -> 0.9722142
A25: 13 | B25: 8 | C25: =P25+S25+V25+Y25+AB25+AE25+AH25+AK25 -> 1.994191e+08 | D25: =C25-E25 -> 0 | E25: =E24-H24-K24 -> 1.994191e+08 | F25: =PMT($K$13/12,$K$12-B25+1,-E25,0) -> 1419016 | G25: =E25*$K$13/12 -> 924972.27 | H25: =F25-G25 -> 494043.71 | I25: =IF(A25<=(30-(240-$K$8)),((A25+(240-$K$7))/30)*$K$6,$K$6)*($K$5/100) -> 0.04758 | J25: =1-(1-I25)^(1/12) -> 0.0040541899 | K25: =(E25-H25)*J25 -> 806479.97 | L25: =K25+H25+G25 -> 2225496 | M25: =L25-G25 -> 1300523.7 | N25: =M25*$M$4 -> 292854 | O25: =M25*$M$5 -> 1007669.7 | P25: =P24-Q24 -> 4550256.6 | Q25: =MIN(IF(S25>O25,0,MIN(P25,O25-S25))+IF(P25>0,MIN(AA25,P25)),P25) -> 94373.931 | R25: =P25*($G$10/12) -> 18959.402 | S25: =S24-T24 -> 68604780 | T25: =MIN(IF(S25>O25,O25,S25)+IF(S25>0,AM25,0),S25) -> 1110623.1 | U25: =S25*($G$4/12) -> 285853.25 | V25: =V24-W24 -> 14000000 | W25: =IF(T25+P25<=O25+AM25+AA25,MIN(V25,O25-Q25+AA25-T25+AM25),0) -> 0 | X25: =V25*($G$5/12) -> 58333.333 | Y25: =IF(V24>O24,(IF(V24>AA24+O24+AM24,Y24+AA24,Y24+AA24-((AA24+O24+AM24)-V24))),Y24-Z24) -> 22649743 | Z25: =MIN(IF(V25>O25,0,MIN(Y25,O25-V25))+IF(AM24>V24,AM24,0),Y25) -> 0 | AA25: =Y25*($G$8/12) -> 94373.931 | AB25: =AB24-AC24 -> 20000000 | AC25: =MIN(IF(Y25>O25,0,MIN(AB25,O25+AM25-Y25))) -> 0 | AD25: =AB25*($G$9/12) -> 83333.333 | AE25: =AE24-AF24 -> 30955512 | AF25: =IF(AE25>N25,N25,AE25) -> 292854 | AG25: =AE25*($G$3/12) -> 128981.3 | AH25: =AH24-AI24 -> 13950000 | AI25: =IF(AE25>N25,0,MIN(AH25,N25-AE25)) -> 0 | AJ25: =AH25*($G$6/12) -> 58125 | AK25: =IF(AL24=0,AK24+AM24,AK24-AL24) -> 24708811 | AL25: =MIN(IF(AB25>0,IF(AB25>O25,0,MIN(AK25,O25-AB25)),O25),AK25) -> 0 | AM25: =AK25*($G$7/12) -> 102953.38 | AN25: =FORECAST(B25, $AM$2:$AY$2,$AM$1:$AY$1) -> 0.03063638 | AO25: =Q25+R25 -> 113333.33 | AP25: =Q25*B25 -> 754991.45 | AQ25: =1/(1+(AN25+$CB$5)/12)^$B25 -> 0.96754931 | AR25: =T25+U25 -> 1396476.3 | AS25: =T25*A25 -> 14438100 | AT25: =1/(1+(AN25+$BV$5)/12)^$B25 -> 0.96755105 | AU25: =W25+X25 -> 58333.333 | AV25: =W25*A25 -> 0 | AW25: =1/(1+(AN25+$BW$5)/12)^$B25 -> 0.96777668 | AX25: =IF(Y26>Y25,0,Z25+AA25) -> 0 | AY25: =A25*Z25 -> 0 | AZ25: =1/(1+(AN25+$BZ$5)/12)^$B25 -> 0.97693411 | BA25: =AC25+AD25 -> 83333.333 | BB25: =AC25*A25 -> 0 | BC25: =1/(1+(AN25+$CA$5)/12)^$B25 -> 0.96818059 | BD25: =AF25+AG25 -> 421835.3 | BE25: =AF25*A25 -> 3807102 | BF25: =1/(1+(AN25+$BU$5)/12)^$B25 -> 0.96778716 | BG25: =AI25+AJ25 -> 58125 | BH25: =AI25*A25 -> 0 | BI25: =1/(1+(AN25+$BX$5)/12)^$B25 -> 0.96862221 | BJ25: =IF(AK26>AK25,0,AL25+AM25) -> 0 | BK25: =A25*AL25 -> 0 | BL25: =1/(1+(AN25+$BY$5)/12)^$B25 -> 0.96907253 | BM25: =AO25+AR25+AU25+AX25+BA25+BD25+BG25+BJ25 -> 2131436.6 | BN25: =M25*B25 -> 10404189 | BO25: =1/(1+(AN25+$CC$5)/12)^$B25 -> 0.96829798
A26: 14 | B26: 9 | C26: =P26+S26+V26+Y26+AB26+AE26+AH26+AK26 -> 1.9811858e+08 | D26: =C26-E26 -> 0 | E26: =E25-H25-K25 -> 1.9811858e+08 | F26: =PMT($K$13/12,$K$12-B26+1,-E26,0) -> 1413263 | G26: =E26*$K$13/12 -> 918940.01 | H26: =F26-G26 -> 494323.01 | I26: =IF(A26<=(30-(240-$K$8)),((A26+(240-$K$7))/30)*$K$6,$K$6)*($K$5/100) -> 0.05124 | J26: =1-(1-I26)^(1/12) -> 0.0043736916 | K26: =(E26-H26)*J26 -> 864347.55 | L26: =K26+H26+G26 -> 2277610.6 | M26: =L26-G26 -> 1358670.6 | N26: =M26*$M$4 -> 305947.61 | O26: =M26*$M$5 -> 1052723 | P26: =P25-Q25 -> 4455882.6 | Q26: =MIN(IF(S26>O26,0,MIN(P26,O26-S26))+IF(P26>0,MIN(AA26,P26)),P26) -> 94767.156 | R26: =P26*($G$10/12) -> 18566.178 | S26: =S25-T25 -> 67494157 | T26: =MIN(IF(S26>O26,O26,S26)+IF(S26>0,AM26,0),S26) -> 1156105.3 | U26: =S26*($G$4/12) -> 281225.65 | V26: =V25-W25 -> 14000000 | W26: =IF(T26+P26<=O26+AM26+AA26,MIN(V26,O26-Q26+AA26-T26+AM26),0) -> 0 | X26: =V26*($G$5/12) -> 58333.333 | Y26: =IF(V25>O25,(IF(V25>AA25+O25+AM25,Y25+AA25,Y25+AA25-((AA25+O25+AM25)-V25))),Y25-Z25) -> 22744117 | Z26: =MIN(IF(V26>O26,0,MIN(Y26,O26-V26))+IF(AM25>V25,AM25,0),Y26) -> 0 | AA26: =Y26*($G$8/12) -> 94767.156 | AB26: =AB25-AC25 -> 20000000 | AC26: =MIN(IF(Y26>O26,0,MIN(AB26,O26+AM26-Y26))) -> 0 | AD26: =AB26*($G$9/12) -> 83333.333 | AE26: =AE25-AF25 -> 30662658 | AF26: =IF(AE26>N26,N26,AE26) -> 305947.61 | AG26: =AE26*($G$3/12) -> 127761.08 | AH26: =AH25-AI25 -> 13950000 | AI26: =IF(AE26>N26,0,MIN(AH26,N26-AE26)) -> 0 | AJ26: =AH26*($G$6/12) -> 58125 | AK26: =IF(AL25=0,AK25+AM25,AK25-AL25) -> 24811764 | AL26: =MIN(IF(AB26>0,IF(AB26>O26,0,MIN(AK26,O26-AB26)),O26),AK26) -> 0 | AM26: =AK26*($G$7/12) -> 103382.35 | AN26: =FORECAST(B26, $AM$2:$AY$2,$AM$1:$AY$1) -> 0.030652491 | AO26: =Q26+R26 -> 113333.33 | AP26: =Q26*B26 -> 852904.4 | AQ26: =1/(1+(AN26+$CB$5)/12)^$B26 -> 0.96355613 | AR26: =T26+U26 -> 1437331 | AS26: =T26*A26 -> 16185474 | AT26: =1/(1+(AN26+$BV$5)/12)^$B26 -> 0.96355808 | AU26: =W26+X26 -> 58333.333 | AV26: =W26*A26 -> 0 | AW26: =1/(1+(AN26+$BW$5)/12)^$B26 -> 0.96381087 | AX26: =IF(Y27>Y26,0,Z26+AA26) -> 0 | AY26: =A26*Z26 -> 0 | AZ26: =1/(1+(AN26+$BZ$5)/12)^$B26 -> 0.9740768 | BA26: =AC26+AD26 -> 83333.333 | BB26: =AC26*A26 -> 0 | BC26: =1/(1+(AN26+$CA$5)/12)^$B26 -> 0.96426342 | BD26: =AF26+AG26 -> 433708.69 | BE26: =AF26*A26 -> 4283266.5 | BF26: =1/(1+(AN26+$BU$5)/12)^$B26 -> 0.96382262 | BG26: =AI26+AJ26 -> 58125 | BH26: =AI26*A26 -> 0 | BI26: =1/(1+(AN26+$BX$5)/12)^$B26 -> 0.96475825 | BJ26: =IF(AK27>AK26,0,AL26+AM26) -> 0 | BK26: =A26*AL26 -> 0 | BL26: =1/(1+(AN26+$BY$5)/12)^$B26 -> 0.96526285 | BM26: =AO26+AR26+AU26+AX26+BA26+BD26+BG26+BJ26 -> 2184164.6 | BN26: =M26*B26 -> 12228035 | BO26: =1/(1+(AN26+$CC$5)/12)^$B26 -> 0.96439495
A27: 15 | B27: 10 | C27: =P27+S27+V27+Y27+AB27+AE27+AH27+AK27 -> 1.9675991e+08 | D27: =C27-E27 -> 0 | E27: =E26-H26-K26 -> 1.9675991e+08 | F27: =PMT($K$13/12,$K$12-B27+1,-E27,0) -> 1407081.8 | G27: =E27*$K$13/12 -> 912638.04 | H27: =F27-G27 -> 494443.8 | I27: =IF(A27<=(30-(240-$K$8)),((A27+(240-$K$7))/30)*$K$6,$K$6)*($K$5/100) -> 0.0549 | J27: =1-(1-I27)^(1/12) -> 0.0046943251 | K27: =(E27-H27)*J27 -> 921333.91 | L27: =K27+H27+G27 -> 2328415.8 | M27: =L27-G27 -> 1415777.7 | N27: =M27*$M$4 -> 318807.09 | O27: =M27*$M$5 -> 1096970.6 | P27: =P26-Q26 -> 4361115.5 | Q27: =MIN(IF(S27>O27,0,MIN(P27,O27-S27))+IF(P27>0,MIN(AA27,P27)),P27) -> 95162.019 | R27: =P27*($G$10/12) -> 18171.315 | S27: =S26-T26 -> 66338051 | T27: =MIN(IF(S27>O27,O27,S27)+IF(S27>0,AM27,0),S27) -> 1200783.7 | U27: =S27*($G$4/12) -> 276408.55 | V27: =V26-W26 -> 14000000 | W27: =IF(T27+P27<=O27+AM27+AA27,MIN(V27,O27-Q27+AA27-T27+AM27),0) -> 0 | X27: =V27*($G$5/12) -> 58333.333 | Y27: =IF(V26>O26,(IF(V26>AA26+O26+AM26,Y26+AA26,Y26+AA26-((AA26+O26+AM26)-V26))),Y26-Z26) -> 22838885 | Z27: =MIN(IF(V27>O27,0,MIN(Y27,O27-V27))+IF(AM26>V26,AM26,0),Y27) -> 0 | AA27: =Y27*($G$8/12) -> 95162.019 | AB27: =AB26-AC26 -> 20000000 | AC27: =MIN(IF(Y27>O27,0,MIN(AB27,O27+AM27-Y27))) -> 0 | AD27: =AB27*($G$9/12) -> 83333.333 | AE27: =AE26-AF26 -> 30356711 | AF27: =IF(AE27>N27,N27,AE27) -> 318807.09 | AG27: =AE27*($G$3/12) -> 126486.29 | AH27: =AH26-AI26 -> 13950000 | AI27: =IF(AE27>N27,0,MIN(AH27,N27-AE27)) -> 0 | AJ27: =AH27*($G$6/12) -> 58125 | AK27: =IF(AL26=0,AK26+AM26,AK26-AL26) -> 24915147 | AL27: =MIN(IF(AB27>0,IF(AB27>O27,0,MIN(AK27,O27-AB27)),O27),AK27) -> 0 | AM27: =AK27*($G$7/12) -> 103813.11 | AN27: =FORECAST(B27, $AM$2:$AY$2,$AM$1:$AY$1) -> 0.030668601 | AO27: =Q27+R27 -> 113333.33 | AP27: =Q27*B27 -> 951620.19 | AQ27: =1/(1+(AN27+$CB$5)/12)^$B27 -> 0.95957687 | AR27: =T27+U27 -> 1477192.3 | AS27: =T27*A27 -> 18011756 | AT27: =1/(1+(AN27+$BV$5)/12)^$B27 -> 0.95957903 | AU27: =W27+X27 -> 58333.333 | AV27: =W27*A27 -> 0 | AW27: =1/(1+(AN27+$BW$5)/12)^$B27 -> 0.95985875 | AX27: =IF(Y28>Y27,0,Z27+AA27) -> 0 | AY27: =A27*Z27 -> 0 | AZ27: =1/(1+(AN27+$BZ$5)/12)^$B27 -> 0.97122525 | BA27: =AC27+AD27 -> 83333.333 | BB27: =AC27*A27 -> 0 | BC27: =1/(1+(AN27+$CA$5)/12)^$B27 -> 0.96035953 | BD27: =AF27+AG27 -> 445293.38 | BE27: =AF27*A27 -> 4782106.3 | BF27: =1/(1+(AN27+$BU$5)/12)^$B27 -> 0.95987175 | BG27: =AI27+AJ27 -> 58125 | BH27: =AI27*A27 -> 0 | BI27: =1/(1+(AN27+$BX$5)/12)^$B27 -> 0.96090713 | BJ27: =IF(AK28>AK27,0,AL27+AM27) -> 0 | BK27: =A27*AL27 -> 0 | BL27: =1/(1+(AN27+$BY$5)/12)^$B27 -> 0.96146557 | BM27: =AO27+AR27+AU27+AX27+BA27+BD27+BG27+BJ27 -> 2235610.7 | BN27: =M27*B27 -> 14157777 | BO27: =1/(1+(AN27+$CC$5)/12)^$B27 -> 0.96050508
A28: 16 | B28: 11 | C28: =P28+S28+V28+Y28+AB28+AE28+AH28+AK28 -> 1.9534413e+08 | D28: =C28-E28 -> 0 | E28: =E27-H27-K27 -> 1.9534413e+08 | F28: =PMT($K$13/12,$K$12-B28+1,-E28,0) -> 1400476.5 | G28: =E28*$K$13/12 -> 906071.19 | H28: =F28-G28 -> 494405.35 | I28: =IF(A28<=(30-(240-$K$8)),((A28+(240-$K$7))/30)*$K$6,$K$6)*($K$5/100) -> 0.05856 | J28: =1-(1-I28)^(1/12) -> 0.0050160989 | K28: =(E28-H28)*J28 -> 977385.49 | L28: =K28+H28+G28 -> 2377862 | M28: =L28-G28 -> 1471790.8 | N28: =M28*$M$4 -> 331420.21 | O28: =M28*$M$5 -> 1140370.6 | P28: =P27-Q27 -> 4265953.5 | Q28: =MIN(IF(S28>O28,0,MIN(P28,O28-S28))+IF(P28>0,MIN(AA28,P28)),P28) -> 95558.527 | R28: =P28*($G$10/12) -> 17774.806 | S28: =S27-T27 -> 65137268 | T28: =MIN(IF(S28>O28,O28,S28)+IF(S28>0,AM28,0),S28) -> 1244616.3 | U28: =S28*($G$4/12) -> 271405.28 | V28: =V27-W27 -> 14000000 | W28: =IF(T28+P28<=O28+AM28+AA28,MIN(V28,O28-Q28+AA28-T28+AM28),0) -> 0 | X28: =V28*($G$5/12) -> 58333.333 | Y28: =IF(V27>O27,(IF(V27>AA27+O27+AM27,Y27+AA27,Y27+AA27-((AA27+O27+AM27)-V27))),Y27-Z27) -> 22934047 | Z28: =MIN(IF(V28>O28,0,MIN(Y28,O28-V28))+IF(AM27>V27,AM27,0),Y28) -> 0 | AA28: =Y28*($G$8/12) -> 95558.527 | AB28: =AB27-AC27 -> 20000000 | AC28: =MIN(IF(Y28>O28,0,MIN(AB28,O28+AM28-Y28))) -> 0 | AD28: =AB28*($G$9/12) -> 83333.333 | AE28: =AE27-AF27 -> 30037904 | AF28: =IF(AE28>N28,N28,AE28) -> 331420.21 | AG28: =AE28*($G$3/12) -> 125157.93 | AH28: =AH27-AI27 -> 13950000 | AI28: =IF(AE28>N28,0,MIN(AH28,N28-AE28)) -> 0 | AJ28: =AH28*($G$6/12) -> 58125 | AK28: =IF(AL27=0,AK27+AM27,AK27-AL27) -> 25018960 | AL28: =MIN(IF(AB28>0,IF(AB28>O28,0,MIN(AK28,O28-AB28)),O28),AK28) -> 0 | AM28: =AK28*($G$7/12) -> 104245.67 | AN28: =FORECAST(B28, $AM$2:$AY$2,$AM$1:$AY$1) -> 0.030684712 | AO28: =Q28+R28 -> 113333.33 | AP28: =Q28*B28 -> 1051143.8 | AQ28: =1/(1+(AN28+$CB$5)/12)^$B28 -> 0.95561149 | AR28: =T28+U28 -> 1516021.6 | AS28: =T28*A28 -> 19913861 | AT28: =1/(1+(AN28+$BV$5)/12)^$B28 -> 0.95561385 | AU28: =W28+X28 -> 58333.333 | AV28: =W28*A28 -> 0 | AW28: =1/(1+(AN28+$BW$5)/12)^$B28 -> 0.95592028 | AX28: =IF(Y29>Y28,0,Z28+AA28) -> 0 | AY28: =A28*Z28 -> 0 | AZ28: =1/(1+(AN28+$BZ$5)/12)^$B28 -> 0.96837945 | BA28: =AC28+AD28 -> 83333.333 | BB28: =AC28*A28 -> 0 | BC28: =1/(1+(AN28+$CA$5)/12)^$B28 -> 0.95646888 | BD28: =AF28+AG28 -> 456578.15 | BE28: =AF28*A28 -> 5302723.4 | BF28: =1/(1+(AN28+$BU$5)/12)^$B28 -> 0.95593451 | BG28: =AI28+AJ28 -> 58125 | BH28: =AI28*A28 -> 0 | BI28: =1/(1+(AN28+$BX$5)/12)^$B28 -> 0.95706882 | BJ28: =IF(AK29>AK28,0,AL28+AM28) -> 0 | BK28: =A28*AL28 -> 0 | BL28: =1/(1+(AN28+$BY$5)/12)^$B28 -> 0.95768067 | BM28: =AO28+AR28+AU28+AX28+BA28+BD28+BG28+BJ28 -> 2285724.7 | BN28: =M28*B28 -> 16189699 | BO28: =1/(1+(AN28+$CC$5)/12)^$B28 -> 0.95662835
A29: 17 | B29: 12 | C29: =P29+S29+V29+Y29+AB29+AE29+AH29+AK29 -> 1.9387234e+08 | D29: =C29-E29 -> 0 | E29: =E28-H28-K28 -> 1.9387234e+08 | F29: =PMT($K$13/12,$K$12-B29+1,-E29,0) -> 1393451.6 | G29: =E29*$K$13/12 -> 899244.54 | H29: =F29-G29 -> 494207.08 | I29: =IF(A29<=(30-(240-$K$8)),((A29+(240-$K$7))/30)*$K$6,$K$6)*($K$5/100) -> 0.06222 | J29: =1-(1-I29)^(1/12) -> 0.0053390214 | K29: =(E29-H29)*J29 -> 1032450 | L29: =K29+H29+G29 -> 2425901.6 | M29: =L29-G29 -> 1526657.1 | N29: =M29*$M$4 -> 343775.08 | O29: =M29*$M$5 -> 1182882 | P29: =P28-Q28 -> 4170394.9 | Q29: =MIN(IF(S29>O29,0,MIN(P29,O29-S29))+IF(P29>0,MIN(AA29,P29)),P29) -> 95956.688 | R29: =P29*($G$10/12) -> 17376.646 | S29: =S28-T28 -> 63892651 | T29: =MIN(IF(S29>O29,O29,S29)+IF(S29>0,AM29,0),S29) -> 1287562 | U29: =S29*($G$4/12) -> 266219.38 | V29: =V28-W28 -> 14000000 | W29: =IF(T29+P29<=O29+AM29+AA29,MIN(V29,O29-Q29+AA29-T29+AM29),0) -> 0 | X29: =V29*($G$5/12) -> 58333.333 | Y29: =IF(V28>O28,(IF(V28>AA28+O28+AM28,Y28+AA28,Y28+AA28-((AA28+O28+AM28)-V28))),Y28-Z28) -> 23029605 | Z29: =MIN(IF(V29>O29,0,MIN(Y29,O29-V29))+IF(AM28>V28,AM28,0),Y29) -> 0 | AA29: =Y29*($G$8/12) -> 95956.688 | AB29: =AB28-AC28 -> 20000000 | AC29: =MIN(IF(Y29>O29,0,MIN(AB29,O29+AM29-Y29))) -> 0 | AD29: =AB29*($G$9/12) -> 83333.333 | AE29: =AE28-AF28 -> 29706483 | AF29: =IF(AE29>N29,N29,AE29) -> 343775.08 | AG29: =AE29*($G$3/12) -> 123777.01 | AH29: =AH28-AI28 -> 13950000 | AI29: =IF(AE29>N29,0,MIN(AH29,N29-AE29)) -> 0 | AJ29: =AH29*($G$6/12) -> 58125 | AK29: =IF(AL28=0,AK28+AM28,AK28-AL28) -> 25123206 | AL29: =MIN(IF(AB29>0,IF(AB29>O29,0,MIN(AK29,O29-AB29)),O29),AK29) -> 0 | AM29: =AK29*($G$7/12) -> 104680.02 | AN29: =FORECAST(B29, $AM$2:$AY$2,$AM$1:$AY$1) -> 0.030700823 | AO29: =Q29+R29 -> 113333.33 | AP29: =Q29*B29 -> 1151480.3 | AQ29: =1/(1+(AN29+$CB$5)/12)^$B29 -> 0.95165994 | AR29: =T29+U29 -> 1553781.4 | AS29: =T29*A29 -> 21888554 | AT29: =1/(1+(AN29+$BV$5)/12)^$B29 -> 0.95166251 | AU29: =W29+X29 -> 58333.333 | AV29: =W29*A29 -> 0 | AW29: =1/(1+(AN29+$BW$5)/12)^$B29 -> 0.95199542 | AX29: =IF(Y30>Y29,0,Z29+AA29) -> 0 | AY29: =A29*Z29 -> 0 | AZ29: =1/(1+(AN29+$BZ$5)/12)^$B29 -> 0.96553941 | BA29: =AC29+AD29 -> 83333.333 | BB29: =AC29*A29 -> 0 | BC29: =1/(1+(AN29+$CA$5)/12)^$B29 -> 0.95259145 | BD29: =AF29+AG29 -> 467552.09 | BE29: =AF29*A29 -> 5844176.3 | BF29: =1/(1+(AN29+$BU$5)/12)^$B29 -> 0.95201088 | BG29: =AI29+AJ29 -> 58125 | BH29: =AI29*A29 -> 0 | BI29: =1/(1+(AN29+$BX$5)/12)^$B29 -> 0.9532433 | BJ29: =IF(AK30>AK29,0,AL29+AM29) -> 0 | BK29: =A29*AL29 -> 0 | BL29: =1/(1+(AN29+$BY$5)/12)^$B29 -> 0.95390812 | BM29: =AO29+AR29+AU29+AX29+BA29+BD29+BG29+BJ29 -> 2334458.5 | BN29: =M29*B29 -> 18319885 | BO29: =1/(1+(AN29+$CC$5)/12)^$B29 -> 0.95276471
A30: 18 | B30: 13 | C30: =P30+S30+V30+Y30+AB30+AE30+AH30+AK30 -> 1.9234568e+08 | D30: =C30-E30 -> 0 | E30: =E29-H29-K29 -> 1.9234568e+08 | F30: =PMT($K$13/12,$K$12-B30+1,-E30,0) -> 1386011.9 | G30: =E30*$K$13/12 -> 892163.39 | H30: =F30-G30 -> 493848.56 | I30: =IF(A30<=(30-(240-$K$8)),((A30+(240-$K$7))/30)*$K$6,$K$6)*($K$5/100) -> 0.06588 | J30: =1-(1-I30)^(1/12) -> 0.0056631013 | K30: =(E30-H30)*J30 -> 1086476.4 | L30: =K30+H30+G30 -> 2472488.3 | M30: =L30-G30 -> 1580324.9 | N30: =M30*$M$4 -> 355860.09 | O30: =M30*$M$5 -> 1224464.8 | P30: =P29-Q29 -> 4074438.2 | Q30: =MIN(IF(S30>O30,0,MIN(P30,O30-S30))+IF(P30>0,MIN(AA30,P30)),P30) -> 96356.507 | R30: =P30*($G$10/12) -> 16976.826 | S30: =S29-T29 -> 62605089 | T30: =MIN(IF(S30>O30,O30,S30)+IF(S30>0,AM30,0),S30) -> 1329581 | U30: =S30*($G$4/12) -> 260854.54 | V30: =V29-W29 -> 14000000 | W30: =IF(T30+P30<=O30+AM30+AA30,MIN(V30,O30-Q30+AA30-T30+AM30),0) -> 0 | X30: =V30*($G$5/12) -> 58333.333 | Y30: =IF(V29>O29,(IF(V29>AA29+O29+AM29,Y29+AA29,Y29+AA29-((AA29+O29+AM29)-V29))),Y29-Z29) -> 23125562 | Z30: =MIN(IF(V30>O30,0,MIN(Y30,O30-V30))+IF(AM29>V29,AM29,0),Y30) -> 0 | AA30: =Y30*($G$8/12) -> 96356.507 | AB30: =AB29-AC29 -> 20000000 | AC30: =MIN(IF(Y30>O30,0,MIN(AB30,O30+AM30-Y30))) -> 0 | AD30: =AB30*($G$9/12) -> 83333.333 | AE30: =AE29-AF29 -> 29362708 | AF30: =IF(AE30>N30,N30,AE30) -> 355860.09 | AG30: =AE30*($G$3/12) -> 122344.62 | AH30: =AH29-AI29 -> 13950000 | AI30: =IF(AE30>N30,0,MIN(AH30,N30-AE30)) -> 0 | AJ30: =AH30*($G$6/12) -> 58125 | AK30: =IF(AL29=0,AK29+AM29,AK29-AL29) -> 25227886 | AL30: =MIN(IF(AB30>0,IF(AB30>O30,0,MIN(AK30,O30-AB30)),O30),AK30) -> 0 | AM30: =AK30*($G$7/12) -> 105116.19 | AN30: =FORECAST(B30, $AM$2:$AY$2,$AM$1:$AY$1) -> 0.030716934 | AO30: =Q30+R30 -> 113333.33 | AP30: =Q30*B30 -> 1252634.6 | AQ30: =1/(1+(AN30+$CB$5)/12)^$B30 -> 0.94772221 | AR30: =T30+U30 -> 1590435.6 | AS30: =T30*A30 -> 23932458 | AT30: =1/(1+(AN30+$BV$5)/12)^$B30 -> 0.94772498 | AU30: =W30+X30 -> 58333.333 | AV30: =W30*A30 -> 0 | AW30: =1/(1+(AN30+$BW$5)/12)^$B30 -> 0.94808414 | AX30: =IF(Y31>Y30,0,Z30+AA30) -> 0 | AY30: =A30*Z30 -> 0 | AZ30: =1/(1+(AN30+$BZ$5)/12)^$B30 -> 0.96270511 | BA30: =AC30+AD30 -> 83333.333 | BB30: =AC30*A30 -> 0 | BC30: =1/(1+(AN30+$CA$5)/12)^$B30 -> 0.94872721 | BD30: =AF30+AG30 -> 478204.71 | BE30: =AF30*A30 -> 6405481.7 | BF30: =1/(1+(AN30+$BU$5)/12)^$B30 -> 0.94810082 | BG30: =AI30+AJ30 -> 58125 | BH30: =AI30*A30 -> 0 | BI30: =1/(1+(AN30+$BX$5)/12)^$B30 -> 0.94943053 | BJ30: =IF(AK31>AK30,0,AL30+AM30) -> 0 | BK30: =A30*AL30 -> 0 | BL30: =1/(1+(AN30+$BY$5)/12)^$B30 -> 0.95014789 | BM30: =AO30+AR30+AU30+AX30+BA30+BD30+BG30+BJ30 -> 2381765.3 | BN30: =M30*B30 -> 20544224 | BO30: =1/(1+(AN30+$CC$5)/12)^$B30 -> 0.94891414
... A69: 57 | B69: 52 | C69: =P69+S69+V69+Y69+AB69+AE69+AH69+AK69 -> 1.20086e+08 | D69: =C69-E69 -> -1.937151e-07 | E69: =E68-H68-K68 -> 1.20086e+08 | F69: =PMT($K$13/12,$K$12-B69+1,-E69,0) -> 971706.5 | G69: =E69*$K$13/12 -> 556998.91 | H69: =F69-G69 -> 414707.59 | I69: =IF(A69<=(30-(240-$K$8)),((A69+(240-$K$7))/30)*$K$6,$K$6)*($K$5/100) -> 0.1098 | J69: =1-(1-I69)^(1/12) -> 0.0096456067 | K69: =(E69-H69)*J69 -> 1154302.2 | L69: =K69+H69+G69 -> 2126008.8 | M69: =L69-G69 -> 1569009.8 | N69: =M69*$M$4 -> 353312.14 | O69: =M69*$M$5 -> 1215697.7 | P69: =P68-Q68 -> 3155.0812 | Q69: =MIN(IF(S69>O69,0,MIN(P69,O69-S69))+IF(P69>0,MIN(AA69,P69)),P69) -> 3155.0812 | R69: =P69*($G$10/12) -> 13.146172 | S69: =S68-T68 -> 2175559.8 | T69: =MIN(IF(S69>O69,O69,S69)+IF(S69>0,AM69,0),S69) -> 1339319.7 | U69: =S69*($G$4/12) -> 9064.8324 | V69: =V68-W68 -> 14000000 | W69: =IF(T69+P69<=O69+AM69+AA69,MIN(V69,O69-Q69+AA69-T69+AM69),0) -> 110165.11 | X69: =V69*($G$5/12) -> 58333.333 | Y69: =IF(V68>O68,(IF(V68>AA68+O68+AM68,Y68+AA68,Y68+AA68-((AA68+O68+AM68)-V68))),Y68-Z68) -> 27196845 | Z69: =MIN(IF(V69>O69,0,MIN(Y69,O69-V69))+IF(AM68>V68,AM68,0),Y69) -> 0 | AA69: =Y69*($G$8/12) -> 113320.19 | AB69: =AB68-AC68 -> 20000000 | AC69: =MIN(IF(Y69>O69,0,MIN(AB69,O69+AM69-Y69))) -> 0 | AD69: =AB69*($G$9/12) -> 83333.333 | AE69: =AE68-AF68 -> 13091158 | AF69: =IF(AE69>N69,N69,AE69) -> 353312.14 | AG69: =AE69*($G$3/12) -> 54546.492 | AH69: =AH68-AI68 -> 13950000 | AI69: =IF(AE69>N69,0,MIN(AH69,N69-AE69)) -> 0 | AJ69: =AH69*($G$6/12) -> 58125 | AK69: =IF(AL68=0,AK68+AM68,AK68-AL68) -> 29669285 | AL69: =MIN(IF(AB69>0,IF(AB69>O69,0,MIN(AK69,O69-AB69)),O69),AK69) -> 0 | AM69: =AK69*($G$7/12) -> 123622.02 | AN69: =FORECAST(B69, $AM$2:$AY$2,$AM$1:$AY$1) -> 0.031345254 | AO69: =Q69+R69 -> 3168.2274 | AP69: =Q69*B69 -> 164064.22 | AQ69: =1/(1+(AN69+$CB$5)/12)^$B69 -> 0.8045382 | AR69: =T69+U69 -> 1348384.6 | AS69: =T69*A69 -> 76341224 | AT69: =1/(1+(AN69+$BV$5)/12)^$B69 -> 0.80454761 | AU69: =W69+X69 -> 168498.44 | AV69: =W69*A69 -> 6279411 | AW69: =1/(1+(AN69+$BW$5)/12)^$B69 -> 0.80576783 | AX69: =IF(Y70>Y69,0,Z69+AA69) -> 0 | AY69: =A69*Z69 -> 0 | AZ69: =1/(1+(AN69+$BZ$5)/12)^$B69 -> 0.85663169 | BA69: =AC69+AD69 -> 83333.333 | BB69: =AC69*A69 -> 0 | BC69: =1/(1+(AN69+$CA$5)/12)^$B69 -> 0.8079561 | BD69: =AF69+AG69 -> 407858.64 | BE69: =AF69*A69 -> 20138792 | BF69: =1/(1+(AN69+$BU$5)/12)^$B69 -> 0.80582456 | BG69: =AI69+AJ69 -> 58125 | BH69: =AI69*A69 -> 0 | BI69: =1/(1+(AN69+$BX$5)/12)^$B69 -> 0.81035449 | BJ69: =IF(AK70>AK69,0,AL69+AM69) -> 0 | BK69: =A69*AL69 -> 0 | BL69: =1/(1+(AN69+$BY$5)/12)^$B69 -> 0.81280626 | BM69: =AO69+AR69+AU69+AX69+BA69+BD69+BG69+BJ69 -> 2069368.2 | BN69: =M69*B69 -> 81588512 | BO69: =1/(1+(AN69+$CC$5)/12)^$B69 -> 0.80859304
A70: 58 | B70: 53 | C70: =P70+S70+V70+Y70+AB70+AE70+AH70+AK70 -> 1.1851699e+08 | D70: =C70-E70 -> -1.7881393e-07 | E70: =E69-H69-K69 -> 1.1851699e+08 | F70: =PMT($K$13/12,$K$12-B70+1,-E70,0) -> 962333.81 | G70: =E70*$K$13/12 -> 549721.32 | H70: =F70-G70 -> 412612.49 | I70: =IF(A70<=(30-(240-$K$8)),((A70+(240-$K$7))/30)*$K$6,$K$6)*($K$5/100) -> 0.1098 | J70: =1-(1-I70)^(1/12) -> 0.0096456067 | K70: =(E70-H70)*J70 -> 1139188.4 | L70: =K70+H70+G70 -> 2101522.2 | M70: =L70-G70 -> 1551800.9 | N70: =M70*$M$4 -> 349437 | O70: =M70*$M$5 -> 1202363.9 | P70: =P69-Q69 -> 0 | Q70: =MIN(IF(S70>O70,0,MIN(P70,O70-S70))+IF(P70>0,MIN(AA70,P70)),P70) -> 0 | R70: =P70*($G$10/12) -> 0 | S70: =S69-T69 -> 836240.05 | T70: =MIN(IF(S70>O70,O70,S70)+IF(S70>0,AM70,0),S70) -> 836240.05 | U70: =S70*($G$4/12) -> 3484.3335 | V70: =V69-W69 -> 13889835 | W70: =IF(T70+P70<=O70+AM70,MIN(V70,O70-Q70+AA70-T70+AM70),0) -> 604053.31 | X70: =V70*($G$5/12) -> 57874.312 | Y70: =IF(V69>O69,(IF(V69>AA69+O69+AM69,Y69+AA69,Y69+AA69-((AA69+O69+AM69)-V69))),Y69-Z69) -> 27310165 | Z70: =MIN(IF(V70>O70,0,MIN(Y70,O70-V70))+IF(AM69>V69,AM69,0),Y70) -> 0 | AA70: =Y70*($G$8/12) -> 113792.35 | AB70: =AB69-AC69 -> 20000000 | AC70: =MIN(IF(Y70>O70,0,MIN(AB70,O70+AM70-Y70))) -> 0 | AD70: =AB70*($G$9/12) -> 83333.333 | AE70: =AE69-AF69 -> 12737846 | AF70: =IF(AE70>N70,N70,AE70) -> 349437 | AG70: =AE70*($G$3/12) -> 53074.358 | AH70: =AH69-AI69 -> 13950000 | AI70: =IF(AE70>N70,0,MIN(AH70,N70-AE70)) -> 0 | AJ70: =AH70*($G$6/12) -> 58125 | AK70: =IF(AL69=0,AK69+AM69,AK69-AL69) -> 29792907 | AL70: =MIN(IF(AB70>0,IF(AB70>O70,0,MIN(AK70,O70-AB70)),O70),AK70) -> 0 | AM70: =AK70*($G$7/12) -> 124137.11 | AN70: =FORECAST(B70, $AM$2:$AY$2,$AM$1:$AY$1) -> 0.031361365 | AO70: =Q70+R70 -> 0 | AP70: =Q70*B70 -> 0 | AQ70: =1/(1+(AN70+$CB$5)/12)^$B70 -> 0.80112353 | AR70: =T70+U70 -> 839724.38 | AS70: =T70*A70 -> 48501923 | AT70: =1/(1+(AN70+$BV$5)/12)^$B70 -> 0.80113308 | AU70: =W70+X70 -> 661927.62 | AV70: =W70*A70 -> 35035092 | AW70: =1/(1+(AN70+$BW$5)/12)^$B70 -> 0.8023715 | AX70: =IF(Y71>Y70,0,Z70+AA70) -> 0 | AY70: =A70*Z70 -> 0 | AZ70: =1/(1+(AN70+$BZ$5)/12)^$B70 -> 0.85402563 | BA70: =AC70+AD70 -> 83333.333 | BB70: =AC70*A70 -> 0 | BC70: =1/(1+(AN70+$CA$5)/12)^$B70 -> 0.80459251 | BD70: =AF70+AG70 -> 402511.36 | BE70: =AF70*A70 -> 20267346 | BF70: =1/(1+(AN70+$BU$5)/12)^$B70 -> 0.80242908 | BG70: =AI70+AJ70 -> 58125 | BH70: =AI70*A70 -> 0 | BI70: =1/(1+(AN70+$BX$5)/12)^$B70 -> 0.80702691 | BJ70: =IF(AK71>AK70,0,AL70+AM70) -> 0 | BK70: =A70*AL70 -> 0 | BL70: =1/(1+(AN70+$BY$5)/12)^$B70 -> 0.80951563 | BM70: =AO70+AR70+AU70+AX70+BA70+BD70+BG70+BJ70 -> 2045621.7 | BN70: =M70*B70 -> 82245447 | BO70: =1/(1+(AN70+$CC$5)/12)^$B70 -> 0.805239
A71: 59 | B71: 54 | C71: =P71+S71+V71+Y71+AB71+AE71+AH71+AK71 -> 1.1696519e+08 | D71: =C71-E71 -> -1.7881393e-07 | E71: =E70-H70-K70 -> 1.1696519e+08 | F71: =PMT($K$13/12,$K$12-B71+1,-E71,0) -> 953051.51 | G71: =E71*$K$13/12 -> 542523.55 | H71: =F71-G71 -> 410527.96 | I71: =IF(A71<=(30-(240-$K$8)),((A71+(240-$K$7))/30)*$K$6,$K$6)*($K$5/100) -> 0.1098 | J71: =1-(1-I71)^(1/12) -> 0.0096456067 | K71: =(E71-H71)*J71 -> 1124240.5 | L71: =K71+H71+G71 -> 2077292 | M71: =L71-G71 -> 1534768.4 | N71: =M71*$M$4 -> 345601.6 | O71: =M71*$M$5 -> 1189166.8 | P71: =P70-Q70 -> 0 | Q71: =MIN(IF(S71>O71,0,MIN(P71,O71-S71))+IF(P71>0,MIN(AA71,P71)),P71) -> 0 | R71: =P71*($G$10/12) -> 0 | S71: =S70-T70 -> 0 | T71: =MIN(IF(S71>O71,O71,S71)+IF(S71>0,AM71,0),S71) -> 0 | U71: =S71*($G$4/12) -> 0 | V71: =V70-W70 -> 13285782 | W71: =IF(T71+P71<=O71+AM71,MIN(V71,O71-Q71+AA71-T71+AM71),0) -> 1428087.7 | X71: =V71*($G$5/12) -> 55357.423 | Y71: =IF(V70>O70,(IF(V70>AA70+O70+AM70,Y70+AA70,Y70+AA70-((AA70+O70+AM70)-V70))),Y70-Z70) -> 27423957 | Z71: =MIN(IF(V71>O71,0,MIN(Y71,O71-V71))+IF(AM70>V70,AM70,0),Y71) -> 0 | AA71: =Y71*($G$8/12) -> 114266.49 | AB71: =AB70-AC70 -> 20000000 | AC71: =MIN(IF(Y71>O71,0,MIN(AB71,O71+AM71-Y71))) -> 0 | AD71: =AB71*($G$9/12) -> 83333.333 | AE71: =AE70-AF70 -> 12388409 | AF71: =IF(AE71>N71,N71,AE71) -> 345601.6 | AG71: =AE71*($G$3/12) -> 51618.371 | AH71: =AH70-AI70 -> 13950000 | AI71: =IF(AE71>N71,0,MIN(AH71,N71-AE71)) -> 0 | AJ71: =AH71*($G$6/12) -> 58125 | AK71: =IF(AL70=0,AK70+AM70,AK70-AL70) -> 29917045 | AL71: =MIN(IF(AB71>0,IF(AB71>O71,0,MIN(AK71,O71-AB71)),O71),AK71) -> 0 | AM71: =AK71*($G$7/12) -> 124654.35 | AN71: =FORECAST(B71, $AM$2:$AY$2,$AM$1:$AY$1) -> 0.031377476 | AO71: =Q71+R71 -> 0 | AP71: =Q71*B71 -> 0 | AQ71: =1/(1+(AN71+$CB$5)/12)^$B71 -> 0.79772121 | AR71: =T71+U71 -> 0 | AS71: =T71*A71 -> 0 | AT71: =1/(1+(AN71+$BV$5)/12)^$B71 -> 0.7977309 | AU71: =W71+X71 -> 1483445.1 | AV71: =W71*A71 -> 84257171 | AW71: =1/(1+(AN71+$BW$5)/12)^$B71 -> 0.79898735 | AX71: =IF(Y72>Y71,0,Z71+AA71) -> 0 | AY71: =A71*Z71 -> 0 | AZ71: =1/(1+(AN71+$BZ$5)/12)^$B71 -> 0.85142522 | BA71: =AC71+AD71 -> 83333.333 | BB71: =AC71*A71 -> 0 | BC71: =1/(1+(AN71+$CA$5)/12)^$B71 -> 0.80124077 | BD71: =AF71+AG71 -> 397219.97 | BE71: =AF71*A71 -> 20390495 | BF71: =1/(1+(AN71+$BU$5)/12)^$B71 -> 0.79904577 | BG71: =AI71+AJ71 -> 58125 | BH71: =AI71*A71 -> 0 | BI71: =1/(1+(AN71+$BX$5)/12)^$B71 -> 0.80371084 | BJ71: =IF(AK72>AK71,0,AL71+AM71) -> 0 | BK71: =A71*AL71 -> 0 | BL71: =1/(1+(AN71+$BY$5)/12)^$B71 -> 0.80623617 | BM71: =AO71+AR71+AU71+AX71+BA71+BD71+BG71+BJ71 -> 2022123.4 | BN71: =M71*B71 -> 82877494 | BO71: =1/(1+(AN71+$CC$5)/12)^$B71 -> 0.80189672
A72: 60 | B72: 55 | C72: =P72+S72+V72+Y72+AB72+AE72+AH72+AK72 -> 1.1543042e+08 | D72: =C72-E72 -> -1.7881393e-07 | E72: =E71-H71-K71 -> 1.1543042e+08 | F72: =PMT($K$13/12,$K$12-B72+1,-E72,0) -> 943858.75 | G72: =E72*$K$13/12 -> 535404.78 | H72: =F72-G72 -> 408453.97 | I72: =IF(A72<=(30-(240-$K$8)),((A72+(240-$K$7))/30)*$K$6,$K$6)*($K$5/100) -> 0.1098 | J72: =1-(1-I72)^(1/12) -> 0.0096456067 | K72: =(E72-H72)*J72 -> 1109456.7 | L72: =K72+H72+G72 -> 2053315.4 | M72: =L72-G72 -> 1517910.7 | N72: =M72*$M$4 -> 341805.55 | O72: =M72*$M$5 -> 1176105.1 | P72: =P71-Q71 -> 0 | Q72: =MIN(IF(S72>O72,0,MIN(P72,O72-S72))+IF(P72>0,MIN(AA72,P72)),P72) -> 0 | R72: =P72*($G$10/12) -> 0 | S72: =S71-T71 -> 0 | T72: =MIN(IF(S72>O72,O72,S72)+IF(S72>0,AM72,0),S72) -> 0 | U72: =S72*($G$4/12) -> 0 | V72: =V71-W71 -> 11857694 | W72: =IF(T72+P72<=O72+AM72,MIN(V72,O72-Q72+AA72-T72+AM72),0) -> 1416021.5 | X72: =V72*($G$5/12) -> 49407.058 | Y72: =IF(V71>O71,(IF(V71>AA71+O71+AM71,Y71+AA71,Y71+AA71-((AA71+O71+AM71)-V71))),Y71-Z71) -> 27538224 | Z72: =MIN(IF(V72>O72,0,MIN(Y72,O72-V72))+IF(AM71>V71,AM71,0),Y72) -> 0 | AA72: =Y72*($G$8/12) -> 114742.6 | AB72: =AB71-AC71 -> 20000000 | AC72: =MIN(IF(Y72>O72,0,MIN(AB72,O72+AM72-Y72))) -> 0 | AD72: =AB72*($G$9/12) -> 83333.333 | AE72: =AE71-AF71 -> 12042807 | AF72: =IF(AE72>N72,N72,AE72) -> 341805.55 | AG72: =AE72*($G$3/12) -> 50178.364 | AH72: =AH71-AI71 -> 13950000 | AI72: =IF(AE72>N72,0,MIN(AH72,N72-AE72)) -> 0 | AJ72: =AH72*($G$6/12) -> 58125 | AK72: =IF(AL71=0,AK71+AM71,AK71-AL71) -> 30041699 | AL72: =MIN(IF(AB72>0,IF(AB72>O72,0,MIN(AK72,O72-AB72)),O72),AK72) -> 0 | AM72: =AK72*($G$7/12) -> 125173.75 | AN72: =FORECAST(B72, $AM$2:$AY$2,$AM$1:$AY$1) -> 0.031393587 | AO72: =Q72+R72 -> 0 | AP72: =Q72*B72 -> 0 | AQ72: =1/(1+(AN72+$CB$5)/12)^$B72 -> 0.79433123 | AR72: =T72+U72 -> 0 | AS72: =T72*A72 -> 0 | AT72: =1/(1+(AN72+$BV$5)/12)^$B72 -> 0.79434105 | AU72: =W72+X72 -> 1465428.5 | AV72: =W72*A72 -> 84961287 | AW72: =1/(1+(AN72+$BW$5)/12)^$B72 -> 0.79561535 | AX72: =IF(Y73>Y72,0,Z72+AA72) -> 0 | AY72: =A72*Z72 -> 0 | AZ72: =1/(1+(AN72+$BZ$5)/12)^$B72 -> 0.84883046 | BA72: =AC72+AD72 -> 83333.333 | BB72: =AC72*A72 -> 0 | BC72: =1/(1+(AN72+$CA$5)/12)^$B72 -> 0.79790087 | BD72: =AF72+AG72 -> 391983.91 | BE72: =AF72*A72 -> 20508333 | BF72: =1/(1+(AN72+$BU$5)/12)^$B72 -> 0.7956746 | BG72: =AI72+AJ72 -> 58125 | BH72: =AI72*A72 -> 0 | BI72: =1/(1+(AN72+$BX$5)/12)^$B72 -> 0.80040626 | BJ72: =IF(AK73>AK72,0,AL72+AM72) -> 0 | BK72: =A72*AL72 -> 0 | BL72: =1/(1+(AN72+$BY$5)/12)^$B72 -> 0.80296785 | BM72: =AO72+AR72+AU72+AX72+BA72+BD72+BG72+BJ72 -> 1998870.8 | BN72: =M72*B72 -> 83485086 | BO72: =1/(1+(AN72+$CC$5)/12)^$B72 -> 0.79856619
A73: 61 | B73: 56 | C73: =P73+S73+V73+Y73+AB73+AE73+AH73+AK73 -> 1.1391251e+08 | D73: =C73-E73 -> -1.7881393e-07 | E73: =E72-H72-K72 -> 1.1391251e+08 | F73: =PMT($K$13/12,$K$12-B73+1,-E73,0) -> 934754.66 | G73: =E73*$K$13/12 -> 528364.21 | H73: =F73-G73 -> 406390.45 | I73: =IF(A73<=(30-(240-$K$8)),((A73+(240-$K$7))/30)*$K$6,$K$6)*($K$5/100) -> 0.1098 | J73: =1-(1-I73)^(1/12) -> 0.0096456067 | K73: =(E73-H73)*J73 -> 1094835.4 | L73: =K73+H73+G73 -> 2029590.1 | M73: =L73-G73 -> 1501225.9 | N73: =M73*$M$4 -> 338048.44 | O73: =M73*$M$5 -> 1163177.4 | P73: =P72-Q72 -> 0 | Q73: =MIN(IF(S73>O73,0,MIN(P73,O73-S73))+IF(P73>0,MIN(AA73,P73)),P73) -> 0 | R73: =P73*($G$10/12) -> 0 | S73: =S72-T72 -> 0 | T73: =MIN(IF(S73>O73,O73,S73)+IF(S73>0,AM73,0),S73) -> 0 | U73: =S73*($G$4/12) -> 0 | V73: =V72-W72 -> 10441672 | W73: =IF(T73+P73<=O73+AM73,MIN(V73,O73-Q73+AA73-T73+AM73),0) -> 1404093.4 | X73: =V73*($G$5/12) -> 43506.969 | Y73: =IF(V72>O72,(IF(V72>AA72+O72+AM72,Y72+AA72,Y72+AA72-((AA72+O72+AM72)-V72))),Y72-Z72) -> 27652967 | Z73: =MIN(IF(V73>O73,0,MIN(Y73,O73-V73))+IF(AM72>V72,AM72,0),Y73) -> 0 | AA73: =Y73*($G$8/12) -> 115220.69 | AB73: =AB72-AC72 -> 20000000 | AC73: =MIN(IF(Y73>O73,0,MIN(AB73,O73+AM73-Y73))) -> 0 | AD73: =AB73*($G$9/12) -> 83333.333 | AE73: =AE72-AF72 -> 11701002 | AF73: =IF(AE73>N73,N73,AE73) -> 338048.44 | AG73: =AE73*($G$3/12) -> 48754.174 | AH73: =AH72-AI72 -> 13950000 | AI73: =IF(AE73>N73,0,MIN(AH73,N73-AE73)) -> 0 | AJ73: =AH73*($G$6/12) -> 58125 | AK73: =IF(AL72=0,AK72+AM72,AK72-AL72) -> 30166873 | AL73: =MIN(IF(AB73>0,IF(AB73>O73,0,MIN(AK73,O73-AB73)),O73),AK73) -> 0 | AM73: =AK73*($G$7/12) -> 125695.3 | AN73: =FORECAST(B73, $AM$2:$AY$2,$AM$1:$AY$1) -> 0.031409697 | AO73: =Q73+R73 -> 0 | AP73: =Q73*B73 -> 0 | AQ73: =1/(1+(AN73+$CB$5)/12)^$B73 -> 0.79095353 | AR73: =T73+U73 -> 0 | AS73: =T73*A73 -> 0 | AT73: =1/(1+(AN73+$BV$5)/12)^$B73 -> 0.79096349 | AU73: =W73+X73 -> 1447600.4 | AV73: =W73*A73 -> 85649699 | AW73: =1/(1+(AN73+$BW$5)/12)^$B73 -> 0.79225546 | AX73: =IF(Y74>Y73,0,Z73+AA73) -> 0 | AY73: =A73*Z73 -> 0 | AZ73: =1/(1+(AN73+$BZ$5)/12)^$B73 -> 0.84624133 | BA73: =AC73+AD73 -> 83333.333 | BB73: =AC73*A73 -> 0 | BC73: =1/(1+(AN73+$CA$5)/12)^$B73 -> 0.79457276 | BD73: =AF73+AG73 -> 386802.62 | BE73: =AF73*A73 -> 20620955 | BF73: =1/(1+(AN73+$BU$5)/12)^$B73 -> 0.79231553 | BG73: =AI73+AJ73 -> 58125 | BH73: =AI73*A73 -> 0 | BI73: =1/(1+(AN73+$BX$5)/12)^$B73 -> 0.79711314 | BJ73: =IF(AK74>AK73,0,AL73+AM73) -> 0 | BK73: =A73*AL73 -> 0 | BL73: =1/(1+(AN73+$BY$5)/12)^$B73 -> 0.79971064 | BM73: =AO73+AR73+AU73+AX73+BA73+BD73+BG73+BJ73 -> 1975861.3 | BN73: =M73*B73 -> 84068649 | BO73: =1/(1+(AN73+$CC$5)/12)^$B73 -> 0.79524735
A74: 62 | B74: 57 | C74: =P74+S74+V74+Y74+AB74+AE74+AH74+AK74 -> 1.1241129e+08 | D74: =C74-E74 -> -1.937151e-07 | E74: =E73-H73-K73 -> 1.1241129e+08 | F74: =PMT($K$13/12,$K$12-B74+1,-E74,0) -> 925738.39 | G74: =E74*$K$13/12 -> 521401.02 | H74: =F74-G74 -> 404337.36 | I74: =IF(A74<=(30-(240-$K$8)),((A74+(240-$K$7))/30)*$K$6,$K$6)*($K$5/100) -> 0.1098 | J74: =1-(1-I74)^(1/12) -> 0.0096456067 | K74: =(E74-H74)*J74 -> 1080375 | L74: =K74+H74+G74 -> 2006113.4 | M74: =L74-G74 -> 1484712.4 | N74: =M74*$M$4 -> 334329.9 | O74: =M74*$M$5 -> 1150382.5 | P74: =P73-Q73 -> 0 | Q74: =MIN(IF(S74>O74,0,MIN(P74,O74-S74))+IF(P74>0,MIN(AA74,P74)),P74) -> 0 | R74: =P74*($G$10/12) -> 0 | S74: =S73-T73 -> 0 | T74: =MIN(IF(S74>O74,O74,S74)+IF(S74>0,AM74,0),S74) -> 0 | U74: =S74*($G$4/12) -> 0 | V74: =V73-W73 -> 9037579.1 | W74: =IF(T74+P74<=O74+AM74,MIN(V74,O74-Q74+AA74-T74+AM74),0) -> 1392302.3 | X74: =V74*($G$5/12) -> 37656.579 | Y74: =IF(V73>O73,(IF(V73>AA73+O73+AM73,Y73+AA73,Y73+AA73-((AA73+O73+AM73)-V73))),Y73-Z73) -> 27768187 | Z74: =MIN(IF(V74>O74,0,MIN(Y74,O74-V74))+IF(AM73>V73,AM73,0),Y74) -> 0 | AA74: =Y74*($G$8/12) -> 115700.78 | AB74: =AB73-AC73 -> 20000000 | AC74: =MIN(IF(Y74>O74,0,MIN(AB74,O74+AM74-Y74))) -> 0 | AD74: =AB74*($G$9/12) -> 83333.333 | AE74: =AE73-AF73 -> 11362953 | AF74: =IF(AE74>N74,N74,AE74) -> 334329.9 | AG74: =AE74*($G$3/12) -> 47345.639 | AH74: =AH73-AI73 -> 13950000 | AI74: =IF(AE74>N74,0,MIN(AH74,N74-AE74)) -> 0 | AJ74: =AH74*($G$6/12) -> 58125 | AK74: =IF(AL73=0,AK73+AM73,AK73-AL73) -> 30292568 | AL74: =MIN(IF(AB74>0,IF(AB74>O74,0,MIN(AK74,O74-AB74)),O74),AK74) -> 0 | AM74: =AK74*($G$7/12) -> 126219.03 | AN74: =FORECAST(B74, $AM$2:$AY$2,$AM$1:$AY$1) -> 0.031425808 | AO74: =Q74+R74 -> 0 | AP74: =Q74*B74 -> 0 | AQ74: =1/(1+(AN74+$CB$5)/12)^$B74 -> 0.78758809 | AR74: =T74+U74 -> 0 | AS74: =T74*A74 -> 0 | AT74: =1/(1+(AN74+$BV$5)/12)^$B74 -> 0.78759819 | AU74: =W74+X74 -> 1429958.8 | AV74: =W74*A74 -> 86322740 | AW74: =1/(1+(AN74+$BW$5)/12)^$B74 -> 0.78890764 | AX74: =IF(Y75>Y74,0,Z74+AA74) -> 0 | AY74: =A74*Z74 -> 0 | AZ74: =1/(1+(AN74+$BZ$5)/12)^$B74 -> 0.84365785 | BA74: =AC74+AD74 -> 83333.333 | BB74: =AC74*A74 -> 0 | BC74: =1/(1+(AN74+$CA$5)/12)^$B74 -> 0.79125642 | BD74: =AF74+AG74 -> 381675.54 | BE74: =AF74*A74 -> 20728454 | BF74: =1/(1+(AN74+$BU$5)/12)^$B74 -> 0.78896853 | BG74: =AI74+AJ74 -> 58125 | BH74: =AI74*A74 -> 0 | BI74: =1/(1+(AN74+$BX$5)/12)^$B74 -> 0.79383144 | BJ74: =IF(AK75>AK74,0,AL74+AM74) -> 0 | BK74: =A74*AL74 -> 0 | BL74: =1/(1+(AN74+$BY$5)/12)^$B74 -> 0.79646452 | BM74: =AO74+AR74+AU74+AX74+BA74+BD74+BG74+BJ74 -> 1953092.7 | BN74: =M74*B74 -> 84628604 | BO74: =1/(1+(AN74+$CC$5)/12)^$B74 -> 0.7919402
A75: 63 | B75: 58 | C75: =P75+S75+V75+Y75+AB75+AE75+AH75+AK75 -> 1.1092658e+08 | D75: =C75-E75 -> -1.937151e-07 | E75: =E74-H74-K74 -> 1.1092658e+08 | F75: =PMT($K$13/12,$K$12-B75+1,-E75,0) -> 916809.08 | G75: =E75*$K$13/12 -> 514514.43 | H75: =F75-G75 -> 402294.65 | I75: =IF(A75<=(30-(240-$K$8)),((A75+(240-$K$7))/30)*$K$6,$K$6)*($K$5/100) -> 0.1098 | J75: =1-(1-I75)^(1/12) -> 0.0096456067 | K75: =(E75-H75)*J75 -> 1066073.7 | L75: =K75+H75+G75 -> 1982882.8 | M75: =L75-G75 -> 1468368.4 | N75: =M75*$M$4 -> 330649.54 | O75: =M75*$M$5 -> 1137718.8 | P75: =P74-Q74 -> 0 | Q75: =MIN(IF(S75>O75,0,MIN(P75,O75-S75))+IF(P75>0,MIN(AA75,P75)),P75) -> 0 | R75: =P75*($G$10/12) -> 0 | S75: =S74-T74 -> 0 | T75: =MIN(IF(S75>O75,O75,S75)+IF(S75>0,AM75,0),S75) -> 0 | U75: =S75*($G$4/12) -> 0 | V75: =V74-W74 -> 7645276.8 | W75: =IF(T75+P75<=O75+AM75,MIN(V75,O75-Q75+AA75-T75+AM75),0) -> 1380646.7 | X75: =V75*($G$5/12) -> 31855.32 | Y75: =IF(V74>O74,(IF(V74>AA74+O74+AM74,Y74+AA74,Y74+AA74-((AA74+O74+AM74)-V74))),Y74-Z74) -> 27883888 | Z75: =MIN(IF(V75>O75,0,MIN(Y75,O75-V75))+IF(AM74>V74,AM74,0),Y75) -> 0 | AA75: =Y75*($G$8/12) -> 116182.87 | AB75: =AB74-AC74 -> 20000000 | AC75: =MIN(IF(Y75>O75,0,MIN(AB75,O75+AM75-Y75))) -> 0 | AD75: =AB75*($G$9/12) -> 83333.333 | AE75: =AE74-AF74 -> 11028623 | AF75: =IF(AE75>N75,N75,AE75) -> 330649.54 | AG75: =AE75*($G$3/12) -> 45952.598 | AH75: =AH74-AI74 -> 13950000 | AI75: =IF(AE75>N75,0,MIN(AH75,N75-AE75)) -> 0 | AJ75: =AH75*($G$6/12) -> 58125 | AK75: =IF(AL74=0,AK74+AM74,AK74-AL74) -> 30418787 | AL75: =MIN(IF(AB75>0,IF(AB75>O75,0,MIN(AK75,O75-AB75)),O75),AK75) -> 0 | AM75: =AK75*($G$7/12) -> 126744.95 | AN75: =FORECAST(B75, $AM$2:$AY$2,$AM$1:$AY$1) -> 0.031441919 | AO75: =Q75+R75 -> 0 | AP75: =Q75*B75 -> 0 | AQ75: =1/(1+(AN75+$CB$5)/12)^$B75 -> 0.78423487 | AR75: =T75+U75 -> 0 | AS75: =T75*A75 -> 0 | AT75: =1/(1+(AN75+$BV$5)/12)^$B75 -> 0.7842451 | AU75: =W75+X75 -> 1412502 | AV75: =W75*A75 -> 86980740 | AW75: =1/(1+(AN75+$BW$5)/12)^$B75 -> 0.78557188 | AX75: =IF(Y76>Y75,0,Z75+AA75) -> 0 | AY75: =A75*Z75 -> 0 | AZ75: =1/(1+(AN75+$BZ$5)/12)^$B75 -> 0.84108 | BA75: =AC75+AD75 -> 83333.333 | BB75: =AC75*A75 -> 0 | BC75: =1/(1+(AN75+$CA$5)/12)^$B75 -> 0.78795182 | BD75: =AF75+AG75 -> 376602.14 | BE75: =AF75*A75 -> 20830921 | BF75: =1/(1+(AN75+$BU$5)/12)^$B75 -> 0.78563357 | BG75: =AI75+AJ75 -> 58125 | BH75: =AI75*A75 -> 0 | BI75: =1/(1+(AN75+$BX$5)/12)^$B75 -> 0.79056113 | BJ75: =IF(AK76>AK75,0,AL75+AM75) -> 0 | BK75: =A75*AL75 -> 0 | BL75: =1/(1+(AN75+$BY$5)/12)^$B75 -> 0.79322944 | BM75: =AO75+AR75+AU75+AX75+BA75+BD75+BG75+BJ75 -> 1930562.5 | BN75: =M75*B75 -> 85165366 | BO75: =1/(1+(AN75+$CC$5)/12)^$B75 -> 0.78864469
A76: 64 | B76: 59 | C76: =P76+S76+V76+Y76+AB76+AE76+AH76+AK76 -> 1.0945821e+08 | D76: =C76-E76 -> -1.937151e-07 | E76: =E75-H75-K75 -> 1.0945821e+08 | F76: =PMT($K$13/12,$K$12-B76+1,-E76,0) -> 907965.9 | G76: =E76*$K$13/12 -> 507703.65 | H76: =F76-G76 -> 400262.25 | I76: =IF(A76<=(30-(240-$K$8)),((A76+(240-$K$7))/30)*$K$6,$K$6)*($K$5/100) -> 0.1098 | J76: =1-(1-I76)^(1/12) -> 0.0096456067 | K76: =(E76-H76)*J76 -> 1051930 | L76: =K76+H76+G76 -> 1959895.9 | M76: =L76-G76 -> 1452192.3 | N76: =M76*$M$4 -> 327006.98 | O76: =M76*$M$5 -> 1125185.3 | P76: =P75-Q75 -> 0 | Q76: =MIN(IF(S76>O76,0,MIN(P76,O76-S76))+IF(P76>0,MIN(AA76,P76)),P76) -> 0 | R76: =P76*($G$10/12) -> 0 | S76: =S75-T75 -> 0 | T76: =MIN(IF(S76>O76,O76,S76)+IF(S76>0,AM76,0),S76) -> 0 | U76: =S76*($G$4/12) -> 0 | V76: =V75-W75 -> 6264630.1 | W76: =IF(T76+P76<=O76+AM76,MIN(V76,O76-Q76+AA76-T76+AM76),0) -> 1369125.3 | X76: =V76*($G$5/12) -> 26102.626 | Y76: =IF(V75>O75,(IF(V75>AA75+O75+AM75,Y75+AA75,Y75+AA75-((AA75+O75+AM75)-V75))),Y75-Z75) -> 28000071 | Z76: =MIN(IF(V76>O76,0,MIN(Y76,O76-V76))+IF(AM75>V75,AM75,0),Y76) -> 0 | AA76: =Y76*($G$8/12) -> 116666.96 | AB76: =AB75-AC75 -> 20000000 | AC76: =MIN(IF(Y76>O76,0,MIN(AB76,O76+AM76-Y76))) -> 0 | AD76: =AB76*($G$9/12) -> 83333.333 | AE76: =AE75-AF75 -> 10697974 | AF76: =IF(AE76>N76,N76,AE76) -> 327006.98 | AG76: =AE76*($G$3/12) -> 44574.891 | AH76: =AH75-AI75 -> 13950000 | AI76: =IF(AE76>N76,0,MIN(AH76,N76-AE76)) -> 0 | AJ76: =AH76*($G$6/12) -> 58125 | AK76: =IF(AL75=0,AK75+AM75,AK75-AL75) -> 30545532 | AL76: =MIN(IF(AB76>0,IF(AB76>O76,0,MIN(AK76,O76-AB76)),O76),AK76) -> 0 | AM76: =AK76*($G$7/12) -> 127273.05 | AN76: =FORECAST(B76, $AM$2:$AY$2,$AM$1:$AY$1) -> 0.03145803 | AO76: =Q76+R76 -> 0 | AP76: =Q76*B76 -> 0 | AQ76: =1/(1+(AN76+$CB$5)/12)^$B76 -> 0.78089384 | AR76: =T76+U76 -> 0 | AS76: =T76*A76 -> 0 | AT76: =1/(1+(AN76+$BV$5)/12)^$B76 -> 0.7809042 | AU76: =W76+X76 -> 1395227.9 | AV76: =W76*A76 -> 87624020 | AW76: =1/(1+(AN76+$BW$5)/12)^$B76 -> 0.78224813 | AX76: =IF(Y77>Y76,0,Z76+AA76) -> 0 | AY76: =A76*Z76 -> 0 | AZ76: =1/(1+(AN76+$BZ$5)/12)^$B76 -> 0.83850779 | BA76: =AC76+AD76 -> 83333.333 | BB76: =AC76*A76 -> 0 | BC76: =1/(1+(AN76+$CA$5)/12)^$B76 -> 0.78465891 | BD76: =AF76+AG76 -> 371581.87 | BE76: =AF76*A76 -> 20928447 | BF76: =1/(1+(AN76+$BU$5)/12)^$B76 -> 0.78231061 | BG76: =AI76+AJ76 -> 58125 | BH76: =AI76*A76 -> 0 | BI76: =1/(1+(AN76+$BX$5)/12)^$B76 -> 0.7873022 | BJ76: =IF(AK77>AK76,0,AL76+AM76) -> 0 | BK76: =A76*AL76 -> 0 | BL76: =1/(1+(AN76+$BY$5)/12)^$B76 -> 0.7900054 | BM76: =AO76+AR76+AU76+AX76+BA76+BD76+BG76+BJ76 -> 1908268.2 | BN76: =M76*B76 -> 85679345 | BO76: =1/(1+(AN76+$CC$5)/12)^$B76 -> 0.78536079
A77: 65 | B77: 60 | C77: =P77+S77+V77+Y77+AB77+AE77+AH77+AK77 -> 1.0800601e+08 | D77: =C77-E77 -> -1.937151e-07 | E77: =E76-H76-K76 -> 1.0800601e+08 | F77: =PMT($K$13/12,$K$12-B77+1,-E77,0) -> 899208.02 | G77: =E77*$K$13/12 -> 500967.9 | H77: =F77-G77 -> 398240.12 | I77: =IF(A77<=(30-(240-$K$8)),((A77+(240-$K$7))/30)*$K$6,$K$6)*($K$5/100) -> 0.1098 | J77: =1-(1-I77)^(1/12) -> 0.0096456067 | K77: =(E77-H77)*J77 -> 1037942.3 | L77: =K77+H77+G77 -> 1937150.3 | M77: =L77-G77 -> 1436182.4 | N77: =M77*$M$4 -> 323401.85 | O77: =M77*$M$5 -> 1112780.5 | P77: =P76-Q76 -> 0 | Q77: =MIN(IF(S77>O77,0,MIN(P77,O77-S77))+IF(P77>0,MIN(AA77,P77)),P77) -> 0 | R77: =P77*($G$10/12) -> 0 | S77: =S76-T76 -> 0 | T77: =MIN(IF(S77>O77,O77,S77)+IF(S77>0,AM77,0),S77) -> 0 | U77: =S77*($G$4/12) -> 0 | V77: =V76-W76 -> 4895504.8 | W77: =IF(T77+P77<=O77+AM77,MIN(V77,O77-Q77+AA77-T77+AM77),0) -> 1357737 | X77: =V77*($G$5/12) -> 20397.937 | Y77: =IF(V76>O76,(IF(V76>AA76+O76+AM76,Y76+AA76,Y76+AA76-((AA76+O76+AM76)-V76))),Y76-Z76) -> 28116738 | Z77: =MIN(IF(V77>O77,0,MIN(Y77,O77-V77))+IF(AM76>V76,AM76,0),Y77) -> 0 | AA77: =Y77*($G$8/12) -> 117153.07 | AB77: =AB76-AC76 -> 20000000 | AC77: =MIN(IF(Y77>O77,0,MIN(AB77,O77+AM77-Y77))) -> 0 | AD77: =AB77*($G$9/12) -> 83333.333 | AE77: =AE76-AF76 -> 10370967 | AF77: =IF(AE77>N77,N77,AE77) -> 323401.85 | AG77: =AE77*($G$3/12) -> 43212.362 | AH77: =AH76-AI76 -> 13950000 | AI77: =IF(AE77>N77,0,MIN(AH77,N77-AE77)) -> 0 | AJ77: =AH77*($G$6/12) -> 58125 | AK77: =IF(AL76=0,AK76+AM76,AK76-AL76) -> 30672805 | AL77: =MIN(IF(AB77>0,IF(AB77>O77,0,MIN(AK77,O77-AB77)),O77),AK77) -> 0 | AM77: =AK77*($G$7/12) -> 127803.35 | AN77: =FORECAST(B77, $AM$2:$AY$2,$AM$1:$AY$1) -> 0.03147414 | AO77: =Q77+R77 -> 0 | AP77: =Q77*B77 -> 0 | AQ77: =1/(1+(AN77+$CB$5)/12)^$B77 -> 0.77756497 | AR77: =T77+U77 -> 0 | AS77: =T77*A77 -> 0 | AT77: =1/(1+(AN77+$BV$5)/12)^$B77 -> 0.77757546 | AU77: =W77+X77 -> 1378134.9 | AV77: =W77*A77 -> 88252903 | AW77: =1/(1+(AN77+$BW$5)/12)^$B77 -> 0.77893635 | AX77: =IF(Y78>Y77,0,Z77+AA77) -> 0 | AY77: =A77*Z77 -> 0 | AZ77: =1/(1+(AN77+$BZ$5)/12)^$B77 -> 0.8359412 | BA77: =AC77+AD77 -> 83333.333 | BB77: =AC77*A77 -> 0 | BC77: =1/(1+(AN77+$CA$5)/12)^$B77 -> 0.78137768 | BD77: =AF77+AG77 -> 366614.21 | BE77: =AF77*A77 -> 21021120 | BF77: =1/(1+(AN77+$BU$5)/12)^$B77 -> 0.77899963 | BG77: =AI77+AJ77 -> 58125 | BH77: =AI77*A77 -> 0 | BI77: =1/(1+(AN77+$BX$5)/12)^$B77 -> 0.7840546 | BJ77: =IF(AK78>AK77,0,AL77+AM77) -> 0 | BK77: =A77*AL77 -> 0 | BL77: =1/(1+(AN77+$BY$5)/12)^$B77 -> 0.78679235 | BM77: =AO77+AR77+AU77+AX77+BA77+BD77+BG77+BJ77 -> 1886207.4 | BN77: =M77*B77 -> 86170943 | BO77: =1/(1+(AN77+$CC$5)/12)^$B77 -> 0.78208847
A78: 66 | B78: 61 | C78: =P78+S78+V78+Y78+AB78+AE78+AH78+AK78 -> 1.0656983e+08 | D78: =C78-E78 -> -1.7881393e-07 | E78: =E77-H77-K77 -> 1.0656983e+08 | F78: =PMT($K$13/12,$K$12-B78+1,-E78,0) -> 890534.61 | G78: =E78*$K$13/12 -> 494306.4 | H78: =F78-G78 -> 396228.2 | I78: =IF(A78<=(30-(240-$K$8)),((A78+(240-$K$7))/30)*$K$6,$K$6)*($K$5/100) -> 0.1098 | J78: =1-(1-I78)^(1/12) -> 0.0096456067 | K78: =(E78-H78)*J78 -> 1024108.8 | L78: =K78+H78+G78 -> 1914643.4 | M78: =L78-G78 -> 1420337 | N78: =M78*$M$4 -> 319833.76 | O78: =M78*$M$5 -> 1100503.3 | P78: =P77-Q77 -> 0 | Q78: =MIN(IF(S78>O78,0,MIN(P78,O78-S78))+IF(P78>0,MIN(AA78,P78)),P78) -> 0 | R78: =P78*($G$10/12) -> 0 | S78: =S77-T77 -> 0 | T78: =MIN(IF(S78>O78,O78,S78)+IF(S78>0,AM78,0),S78) -> 0 | U78: =S78*($G$4/12) -> 0 | V78: =V77-W77 -> 3537767.8 | W78: =IF(T78+P78<=O78+AM78,MIN(V78,O78-Q78+AA78-T78+AM78),0) -> 1346480.3 | X78: =V78*($G$5/12) -> 14740.699 | Y78: =IF(V77>O77,(IF(V77>AA77+O77+AM77,Y77+AA77,Y77+AA77-((AA77+O77+AM77)-V77))),Y77-Z77) -> 28233891 | Z78: =MIN(IF(V78>O78,0,MIN(Y78,O78-V78))+IF(AM77>V77,AM77,0),Y78) -> 0 | AA78: =Y78*($G$8/12) -> 117641.21 | AB78: =AB77-AC77 -> 20000000 | AC78: =MIN(IF(Y78>O78,0,MIN(AB78,O78+AM78-Y78))) -> 0 | AD78: =AB78*($G$9/12) -> 83333.333 | AE78: =AE77-AF77 -> 10047565 | AF78: =IF(AE78>N78,N78,AE78) -> 319833.76 | AG78: =AE78*($G$3/12) -> 41864.855 | AH78: =AH77-AI77 -> 13950000 | AI78: =IF(AE78>N78,0,MIN(AH78,N78-AE78)) -> 0 | AJ78: =AH78*($G$6/12) -> 58125 | AK78: =IF(AL77=0,AK77+AM77,AK77-AL77) -> 30800608 | AL78: =MIN(IF(AB78>0,IF(AB78>O78,0,MIN(AK78,O78-AB78)),O78),AK78) -> 0 | AM78: =AK78*($G$7/12) -> 128335.87 | AN78: =FORECAST(B78, $AM$2:$AY$2,$AM$1:$AY$1) -> 0.031490251 | AO78: =Q78+R78 -> 0 | AP78: =Q78*B78 -> 0 | AQ78: =1/(1+(AN78+$CB$5)/12)^$B78 -> 0.77424821 | AR78: =T78+U78 -> 0 | AS78: =T78*A78 -> 0 | AT78: =1/(1+(AN78+$BV$5)/12)^$B78 -> 0.77425884 | AU78: =W78+X78 -> 1361221 | AV78: =W78*A78 -> 88867703 | AW78: =1/(1+(AN78+$BW$5)/12)^$B78 -> 0.77563653 | AX78: =IF(Y79>Y78,0,Z78+AA78) -> 0 | AY78: =A78*Z78 -> 0 | AZ78: =1/(1+(AN78+$BZ$5)/12)^$B78 -> 0.83338024 | BA78: =AC78+AD78 -> 83333.333 | BB78: =AC78*A78 -> 0 | BC78: =1/(1+(AN78+$CA$5)/12)^$B78 -> 0.77810809 | BD78: =AF78+AG78 -> 361698.62 | BE78: =AF78*A78 -> 21109028 | BF78: =1/(1+(AN78+$BU$5)/12)^$B78 -> 0.77570059 | BG78: =AI78+AJ78 -> 58125 | BH78: =AI78*A78 -> 0 | BI78: =1/(1+(AN78+$BX$5)/12)^$B78 -> 0.78081831 | BJ78: =IF(AK79>AK78,0,AL78+AM78) -> 0 | BK78: =A78*AL78 -> 0 | BL78: =1/(1+(AN78+$BY$5)/12)^$B78 -> 0.78359028 | BM78: =AO78+AR78+AU78+AX78+BA78+BD78+BG78+BJ78 -> 1864378 | BN78: =M78*B78 -> 86640559 | BO78: =1/(1+(AN78+$CC$5)/12)^$B78 -> 0.77882771
A79: 67 | B79: 62 | C79: =P79+S79+V79+Y79+AB79+AE79+AH79+AK79 -> 1.051495e+08 | D79: =C79-E79 -> -1.937151e-07 | E79: =E78-H78-K78 -> 1.051495e+08 | F79: =PMT($K$13/12,$K$12-B79+1,-E79,0) -> 881944.86 | G79: =E79*$K$13/12 -> 487718.41 | H79: =F79-G79 -> 394226.45 | I79: =IF(A79<=(30-(240-$K$8)),((A79+(240-$K$7))/30)*$K$6,$K$6)*($K$5/100) -> 0.1098 | J79: =1-(1-I79)^(1/12) -> 0.0096456067 | K79: =(E79-H79)*J79 -> 1010428.1 | L79: =K79+H79+G79 -> 1892373 | M79: =L79-G79 -> 1404654.6 | N79: =M79*$M$4 -> 316302.36 | O79: =M79*$M$5 -> 1088352.2 | P79: =P78-Q78 -> 0 | Q79: =MIN(IF(S79>O79,0,MIN(P79,O79-S79))+IF(P79>0,MIN(AA79,P79)),P79) -> 0 | R79: =P79*($G$10/12) -> 0 | S79: =S78-T78 -> 0 | T79: =MIN(IF(S79>O79,O79,S79)+IF(S79>0,AM79,0),S79) -> 0 | U79: =S79*($G$4/12) -> 0 | V79: =V78-W78 -> 2191287.5 | W79: =IF(T79+P79<=O79+AM79,MIN(V79,O79-Q79+AA79-T79+AM79),0) -> 1335354.2 | X79: =V79*($G$5/12) -> 9130.3645 | Y79: =IF(V78>O78,(IF(V78>AA78+O78+AM78,Y78+AA78,Y78+AA78-((AA78+O78+AM78)-V78))),Y78-Z78) -> 28351532 | Z79: =MIN(IF(V79>O79,0,MIN(Y79,O79-V79))+IF(AM78>V78,AM78,0),Y79) -> 0 | AA79: =Y79*($G$8/12) -> 118131.38 | AB79: =AB78-AC78 -> 20000000 | AC79: =MIN(IF(Y79>O79,0,MIN(AB79,O79+AM79-Y79))) -> 0 | AD79: =AB79*($G$9/12) -> 83333.333 | AE79: =AE78-AF78 -> 9727731.3 | AF79: =IF(AE79>N79,N79,AE79) -> 316302.36 | AG79: =AE79*($G$3/12) -> 40532.214 | AH79: =AH78-AI78 -> 13950000 | AI79: =IF(AE79>N79,0,MIN(AH79,N79-AE79)) -> 0 | AJ79: =AH79*($G$6/12) -> 58125 | AK79: =IF(AL78=0,AK78+AM78,AK78-AL78) -> 30928944 | AL79: =MIN(IF(AB79>0,IF(AB79>O79,0,MIN(AK79,O79-AB79)),O79),AK79) -> 0 | AM79: =AK79*($G$7/12) -> 128870.6 | AN79: =FORECAST(B79, $AM$2:$AY$2,$AM$1:$AY$1) -> 0.031506362 | AO79: =Q79+R79 -> 0 | AP79: =Q79*B79 -> 0 | AQ79: =1/(1+(AN79+$CB$5)/12)^$B79 -> 0.77094355 | AR79: =T79+U79 -> 0 | AS79: =T79*A79 -> 0 | AT79: =1/(1+(AN79+$BV$5)/12)^$B79 -> 0.7709543 | AU79: =W79+X79 -> 1344484.6 | AV79: =W79*A79 -> 89468731 | AW79: =1/(1+(AN79+$BW$5)/12)^$B79 -> 0.77234861 | AX79: =IF(Y80>Y79,0,Z79+AA79) -> 0 | AY79: =A79*Z79 -> 0 | AZ79: =1/(1+(AN79+$BZ$5)/12)^$B79 -> 0.8308249 | BA79: =AC79+AD79 -> 83333.333 | BB79: =AC79*A79 -> 0 | BC79: =1/(1+(AN79+$CA$5)/12)^$B79 -> 0.77485011 | BD79: =AF79+AG79 -> 356834.58 | BE79: =AF79*A79 -> 21192258 | BF79: =1/(1+(AN79+$BU$5)/12)^$B79 -> 0.77241345 | BG79: =AI79+AJ79 -> 58125 | BH79: =AI79*A79 -> 0 | BI79: =1/(1+(AN79+$BX$5)/12)^$B79 -> 0.7775933 | BJ79: =IF(AK80>AK79,0,AL79+AM79) -> 0 | BK79: =A79*AL79 -> 0 | BL79: =1/(1+(AN79+$BY$5)/12)^$B79 -> 0.78039915 | BM79: =AO79+AR79+AU79+AX79+BA79+BD79+BG79+BJ79 -> 1842777.5 | BN79: =M79*B79 -> 87088584 | BO79: =1/(1+(AN79+$CC$5)/12)^$B79 -> 0.77557847
A80: 68 | B80: 63 | C80: =P80+S80+V80+Y80+AB80+AE80+AH80+AK80 -> 1.0374484e+08 | D80: =C80-E80 -> -1.7881393e-07 | E80: =E79-H79-K79 -> 1.0374484e+08 | F80: =PMT($K$13/12,$K$12-B80+1,-E80,0) -> 873437.97 | G80: =E80*$K$13/12 -> 481203.15 | H80: =F80-G80 -> 392234.82 | I80: =IF(A80<=(30-(240-$K$8)),((A80+(240-$K$7))/30)*$K$6,$K$6)*($K$5/100) -> 0.1098 | J80: =1-(1-I80)^(1/12) -> 0.0096456067 | K80: =(E80-H80)*J80 -> 996898.58 | L80: =K80+H80+G80 -> 1870336.6 | M80: =L80-G80 -> 1389133.4 | N80: =M80*$M$4 -> 312807.28 | O80: =M80*$M$5 -> 1076326.1 | P80: =P79-Q79 -> 0 | Q80: =MIN(IF(S80>O80,0,MIN(P80,O80-S80))+IF(P80>0,MIN(AA80,P80)),P80) -> 0 | R80: =P80*($G$10/12) -> 0 | S80: =S79-T79 -> 0 | T80: =MIN(IF(S80>O80,O80,S80)+IF(S80>0,AM80,0),S80) -> 0 | U80: =S80*($G$4/12) -> 0 | V80: =V79-W79 -> 855933.29 | W80: =IF(T80+P80<=O80+AM80,MIN(V80,O80-Q80+AA80-T80+AM80),0) -> 855933.29 | X80: =V80*($G$5/12) -> 3566.3887 | Y80: =IF(V79>O79,(IF(V79>AA79+O79+AM79,Y79+AA79,Y79+AA79-((AA79+O79+AM79)-V79))),Y79-Z79) -> 28469664 | Z80: =MIN(IF(V80>O80,0,MIN(Y80,O80-V80))+IF(AM79>V79,AM79,0),Y80) -> 220392.83 | AA80: =Y80*($G$8/12) -> 118623.6 | AB80: =AB79-AC79 -> 20000000 | AC80: =MIN(IF(Y80>O80,0,MIN(AB80,O80+AM80-Y80))) -> 0 | AD80: =AB80*($G$9/12) -> 83333.333 | AE80: =AE79-AF79 -> 9411429 | AF80: =IF(AE80>N80,N80,AE80) -> 312807.28 | AG80: =AE80*($G$3/12) -> 39214.287 | AH80: =AH79-AI79 -> 13950000 | AI80: =IF(AE80>N80,0,MIN(AH80,N80-AE80)) -> 0 | AJ80: =AH80*($G$6/12) -> 58125 | AK80: =IF(AL79=0,AK79+AM79,AK79-AL79) -> 31057815 | AL80: =MIN(IF(AB80>0,IF(AB80>O80,0,MIN(AK80,O80-AB80)),O80),AK80) -> 0 | AM80: =AK80*($G$7/12) -> 129407.56 | AN80: =FORECAST(B80, $AM$2:$AY$2,$AM$1:$AY$1) -> 0.031522473 | AO80: =Q80+R80 -> 0 | AP80: =Q80*B80 -> 0 | AQ80: =1/(1+(AN80+$CB$5)/12)^$B80 -> 0.76765093 | AR80: =T80+U80 -> 0 | AS80: =T80*A80 -> 0 | AT80: =1/(1+(AN80+$BV$5)/12)^$B80 -> 0.76766181 | AU80: =W80+X80 -> 859499.68 | AV80: =W80*A80 -> 58203464 | AW80: =1/(1+(AN80+$BW$5)/12)^$B80 -> 0.76907258 | AX80: =IF(Y81>Y80,0,Z80+AA80) -> 339016.43 | AY80: =A80*Z80 -> 14986712 | AZ80: =1/(1+(AN80+$BZ$5)/12)^$B80 -> 0.82827518 | BA80: =AC80+AD80 -> 83333.333 | BB80: =AC80*A80 -> 0 | BC80: =1/(1+(AN80+$CA$5)/12)^$B80 -> 0.77160371 | BD80: =AF80+AG80 -> 352021.57 | BE80: =AF80*A80 -> 21270895 | BF80: =1/(1+(AN80+$BU$5)/12)^$B80 -> 0.76913818 | BG80: =AI80+AJ80 -> 58125 | BH80: =AI80*A80 -> 0 | BI80: =1/(1+(AN80+$BX$5)/12)^$B80 -> 0.77437954 | BJ80: =IF(AK81>AK80,0,AL80+AM80) -> 0 | BK80: =A80*AL80 -> 0 | BL80: =1/(1+(AN80+$BY$5)/12)^$B80 -> 0.77721894 | BM80: =AO80+AR80+AU80+AX80+BA80+BD80+BG80+BJ80 -> 1691996 | BN80: =M80*B80 -> 87515404 | BO80: =1/(1+(AN80+$CC$5)/12)^$B80 -> 0.77234072
A81: 69 | B81: 64 | C81: =P81+S81+V81+Y81+AB81+AE81+AH81+AK81 -> 1.0248511e+08 | D81: =C81-E81 -> 129407.56 | E81: =E80-H80-K80 -> 1.0235571e+08 | F81: =PMT($K$13/12,$K$12-B81+1,-E81,0) -> 865013.13 | G81: =E81*$K$13/12 -> 474759.89 | H81: =F81-G81 -> 390253.24 | I81: =IF(A81<=(30-(240-$K$8)),((A81+(240-$K$7))/30)*$K$6,$K$6)*($K$5/100) -> 0.1098 | J81: =1-(1-I81)^(1/12) -> 0.0096456067 | K81: =(E81-H81)*J81 -> 983518.66 | L81: =K81+H81+G81 -> 1848531.8 | M81: =L81-G81 -> 1373771.9 | N81: =M81*$M$4 -> 309348.15 | O81: =M81*$M$5 -> 1064423.8 | P81: =P80-Q80 -> 0 | Q81: =MIN(IF(S81>O81,0,MIN(P81,O81-S81))+IF(P81>0,MIN(AA81,P81)),P81) -> 0 | R81: =P81*($G$10/12) -> 0 | S81: =S80-T80 -> 0 | T81: =MIN(IF(S81>O81,O81,S81)+IF(S81>0,AM81,0),S81) -> 0 | U81: =S81*($G$4/12) -> 0 | V81: =V80-W80 -> 0 | W81: =IF(T81+P81<=O81+AM81,MIN(V81,O81-Q81+AA81-T81+AM81),0) -> 0 | X81: =V81*($G$5/12) -> 0 | Y81: =IF(V80>O80,(IF(V80>AA80+O80+AM80,Y80+AA80,Y80+AA80-((AA80+O80+AM80)-V80))),Y80-Z80) -> 28249271 | Z81: =MIN(IF(V81>O81,0,MIN(Y81,O81-V81))+IF(AM80>V80,AM80,0),Y81) -> 1064423.8 | AA81: =Y81*($G$8/12) -> 117705.29 | AB81: =AB80-AC80 -> 20000000 | AC81: =MIN(IF(Y81>O81,0,MIN(AB81,O81+AM81-Y81))) -> 0 | AD81: =AB81*($G$9/12) -> 83333.333 | AE81: =AE80-AF80 -> 9098621.7 | AF81: =IF(AE81>N81,N81,AE81) -> 309348.15 | AG81: =AE81*($G$3/12) -> 37910.924 | AH81: =AH80-AI80 -> 13950000 | AI81: =IF(AE81>N81,0,MIN(AH81,N81-AE81)) -> 0 | AJ81: =AH81*($G$6/12) -> 58125 | AK81: =IF(AL80=0,AK80+AM80,AK80-AL80) -> 31187222 | AL81: =MIN(IF(AB81>0,IF(AB81>O81,0,MIN(AK81,O81-AB81)),O81),AK81) -> 0 | AM81: =AK81*($G$7/12) -> 129946.76 | AN81: =FORECAST(B81, $AM$2:$AY$2,$AM$1:$AY$1) -> 0.031538584 | AO81: =Q81+R81 -> 0 | AP81: =Q81*B81 -> 0 | AQ81: =1/(1+(AN81+$CB$5)/12)^$B81 -> 0.76437034 | AR81: =T81+U81 -> 0 | AS81: =T81*A81 -> 0 | AT81: =1/(1+(AN81+$BV$5)/12)^$B81 -> 0.76438134 | AU81: =W81+X81 -> 0 | AV81: =W81*A81 -> 0 | AW81: =1/(1+(AN81+$BW$5)/12)^$B81 -> 0.7658084 | AX81: =IF(Y82>Y81,0,Z81+AA81) -> 1182129 | AY81: =A81*Z81 -> 73445239 | AZ81: =1/(1+(AN81+$BZ$5)/12)^$B81 -> 0.82573107 | BA81: =AC81+AD81 -> 83333.333 | BB81: =AC81*A81 -> 0 | BC81: =1/(1+(AN81+$CA$5)/12)^$B81 -> 0.76836885 | BD81: =AF81+AG81 -> 347259.08 | BE81: =AF81*A81 -> 21345023 | BF81: =1/(1+(AN81+$BU$5)/12)^$B81 -> 0.76587476 | BG81: =AI81+AJ81 -> 58125 | BH81: =AI81*A81 -> 0 | BI81: =1/(1+(AN81+$BX$5)/12)^$B81 -> 0.771177 | BJ81: =IF(AK82>AK81,0,AL81+AM81) -> 0 | BK81: =A81*AL81 -> 0 | BL81: =1/(1+(AN81+$BY$5)/12)^$B81 -> 0.77404962 | BM81: =AO81+AR81+AU81+AX81+BA81+BD81+BG81+BJ81 -> 1670846.5 | BN81: =M81*B81 -> 87921402 | BO81: =1/(1+(AN81+$CC$5)/12)^$B81 -> 0.76911442
... A252: 240 | B252: 235 | C252: =P252+S252+V252+Y252+AB252+AE252+AH252+AK252 -> 437728.12 | D252: =C252-E252 -> 273589.37 | E252: =E251-H251-K251 -> 164138.75 | F252: =PMT($K$13/12,$K$12-B252+1,-E252,0) -> 164900.08 | G252: =E252*$K$13/12 -> 761.33022 | H252: =F252-G252 -> 164138.75 | I252: =IF(A252<=(30-(240-$K$8)),((A252+(240-$K$7))/30)*$K$6,$K$6)*($K$5/100) -> 0.1098 | J252: =1-(1-I252)^(1/12) -> 0.0096456067 | K252: =(E252-H252)*J252 -> 2.807241e-13 | L252: =K252+H252+G252 -> 164900.08 | M252: =L252-G252 -> 164138.75 | N252: =M252*$M$4 -> 36961.025 | O252: =M252*$M$5 -> 127177.72 | P252: =P251-Q251 -> 0 | Q252: =MIN(IF(S252>O252,0,MIN(P252,O252-S252))+IF(P252>0,MIN(AA252,P252)),P252) -> 0 | R252: =P252*($G$10/12) -> 0 | S252: =S251-T251 -> 0 | T252: =MIN(IF(S252>O252,O252,S252)+IF(S252>0,AM252,0),S252) -> 0 | U252: =S252*($G$4/12) -> 0 | V252: =V251-W251 -> 0 | W252: =IF(T252+P252<=O252+AM252,MIN(V252,O252-Q252+AA252-T252+AM252),0) -> 0 | X252: =V252*($G$5/12) -> 0 | Y252: =IF(V251>O251,(IF(V251>AA251+O251+AM251,Y251+AA251,Y251+AA251-((AA251+O251+AM251)-V251))),Y251-Z251) -> 0 | Z252: =MIN(IF(V252>O252,0,MIN(Y252,O252-V252))+IF(AM251>V251,AM251,0),Y252) -> 0 | AA252: =Y252*($G$8/12) -> 0 | AB252: =AB251-AC251 -> 0 | AC252: =MIN(IF(Y252>O252,0,MIN(AB252,O252+AM252-Y252))) -> 0 | AD252: =AB252*($G$9/12) -> 0 | AE252: =AE251-AF251 -> 0 | AF252: =IF(AE252>N252,N252,AE252) -> 0 | AG252: =AE252*($G$3/12) -> 0 | AH252: =AH251-AI251 -> 36961.025 | AI252: =IF(AE252>N252,0,MIN(AH252,N252-AE252)) -> 36961.025 | AJ252: =AH252*($G$6/12) -> 154.00427 | AK252: =IF(AL251=0,AK251+AM251,AK251-AL251) -> 400767.09 | AL252: =MIN(IF(AB252>0,IF(AB252>O252,0,MIN(AK252,O252-AB252)),O252),AK252) -> 127177.72 | AM252: =AK252*($G$7/12) -> 1669.8629 | AN252: =FORECAST(B252, $AM$2:$AY$2,$AM$1:$AY$1) -> 0.034293527 | AO252: =Q252+R252 -> 0 | AP252: =Q252*B252 -> 0 | AQ252: =1/(1+(AN252+$CB$5)/12)^$B252 -> 0.35332669 | AR252: =T252+U252 -> 0 | AS252: =T252*A252 -> 0 | AT252: =1/(1+(AN252+$BV$5)/12)^$B252 -> 0.35334536 | AU252: =W252+X252 -> 0 | AV252: =W252*A252 -> 0 | AW252: =1/(1+(AN252+$BW$5)/12)^$B252 -> 0.35577311 | AX252: =IF(Y253>Y252,0,Z252+AA252) -> 0 | AY252: =A252*Z252 -> 0 | AZ252: =1/(1+(AN252+$BZ$5)/12)^$B252 -> 0.46911994 | BA252: =AC252+AD252 -> 0 | BB252: =AC252*A252 -> 0 | BC252: =1/(1+(AN252+$CA$5)/12)^$B252 -> 0.36015939 | BD252: =AF252+AG252 -> 0 | BE252: =AF252*A252 -> 0 | BF252: =1/(1+(AN252+$BU$5)/12)^$B252 -> 0.3558863 | BG252: =AI252+AJ252 -> 37115.029 | BH252: =AI252*A252 -> 8870646 | BI252: =1/(1+(AN252+$BX$5)/12)^$B252 -> 0.3650151 | BJ252: =IF(AK253>AK252,0,AL252+AM252) -> 128847.58 | BK252: =A252*AL252 -> 30522653 | BL252: =1/(1+(AN252+$BY$5)/12)^$B252 -> 0.3700314 | BM252: =AO252+AR252+AU252+AX252+BA252+BD252+BG252+BJ252 -> 165962.61 | BN252: =M252*B252 -> 38572605 | BO252: =1/(1+(AN252+$CC$5)/12)^$B252 -> 0.36144399
AJ253: Z(accrual) | AK253: =AK252-AL252 -> 273589.37

Sheet Flatter Yield Curve
A1: Zoom | AB1: Months | AC1: Starting balance | AD1: payment | AE1: interest+Servicing | AF1: principal | AG1: remaining balance | AL1: Date | AM1: 1 | AN1: 2 | AO1: 3 | AP1: 4 | AQ1: 6 | AR1: 12 | AS1: 24 | AT1: 36 | AU1: 60 | AV1: 84 | AW1: 120 | AX1: 240 | AY1: 360 | BA1: Weighted Average Life Sensitivity Analysis
E2: Traunches | F2: Par Amount | G2: Coupon Rate | H2: WAL Calc | AB2: 1 | AC2: =F11 -> 206500000 | AD2: =PMT($K$4/12,$K$7-AB2+1,-AC2) -> 1428195.9 | AE2: =AC2*$K$4/12 -> 957815.83 | AF2: =AD2-AE2 -> 470380.09 | AG2: =AC2-AF2 -> 2.0602962e+08 | AI2: Traunches | AJ2: WAL | AL2: Half as steep | AM2: =0.0163+AO8 -> 0.0233 | AN2: =FORECAST(AN1,$AN$11:$AO$11,$AN$10:$AO$10) -> 0.023338997 | AO2: =FORECAST(AO1,$AN$11:$AO$11,$AN$10:$AO$10) -> 0.023377994 | AP2: =FORECAST(AP1,$AN$11:$AO$11,$AN$10:$AO$10) -> 0.023416992 | AQ2: =FORECAST(AQ1,$AN$11:$AO$11,$AN$10:$AO$10) -> 0.023494986 | AR2: =FORECAST(AR1,$AN$11:$AO$11,$AN$10:$AO$10) -> 0.023728969 | AS2: =FORECAST(AS1,$AN$11:$AO$11,$AN$10:$AO$10) -> 0.024196936 | AT2: =FORECAST(AT1,$AN$11:$AO$11,$AN$10:$AO$10) -> 0.024664903 | AU2: =FORECAST(AU1,$AN$11:$AO$11,$AN$10:$AO$10) -> 0.025600836 | ... AX2: =FORECAST(AX1,$AN$11:$AO$11,$AN$10:$AO$10) -> 0.032620334 | AY2: =0.0443-AO8 -> 0.0373 | BA2: PSA Speed | BB2: Tranche CA | BC2: PSA Speed | BD2: Tranche CG | BE2: PSA Speed | BF2: Tranche CM | BG2: PSA Speed | BH2: Tranche CY | BI2: PSA Speed | BJ2: Tranche CZ | BK2: PSA Speed | BL2: Tranche GZ | BM2: PSA Speed | BN2: Tranche TC | BO2: PSA Speed | BP2: Tranche VE | BQ2: PSA Speed | BR2: Collateral | BU2: CA | BV2: CG | BW2: CM | BX2: CY | BY2: CZ | BZ2: GZ | CA2: TC | CB2: VE | CC2: Collateral
E3: CA | F3: 32550000 | G3: 0.05 | H3: =F3*G3 -> 1627500 | J3: Assumptions | L3: Asset Principal Amount | AB3: 2 | AC3: =AG2 -> 2.0602962e+08 | AD3: =PMT($K$4/12,$K$7-AB3+1,-AC3) -> 1428195.9 | AE3: =AC3*$K$4/12 -> 955634.05 | AF3: =AD3-AE3 -> 472561.87 | AG3: =AC3-AF3 -> 2.0555706e+08 | AI3: CA | AJ3: =SUM(BE18:BE252)/(12*F3) -> 4.2294642 | AL3: 39689 | AM3: 0.0163 | AN3: N/A | AO3: 0.0172 | AP3: N/A | AQ3: 0.0197 | AR3: 0.0217 | AS3: 0.0236 | AT3: 0.026 | AU3: 0.031 | AV3: 0.0345 | AW3: 0.0383 | AX3: 0.0447 | AY3: 0.0443 | BA3: 0 | BB3: =AJ3 -> 4.2294642 | BC3: 0 | BD3: =AJ4 -> 2.7577516 | BE3: 0 | BF3: =AJ5 -> 5.2415728 | BG3: 0 | BH3: =AJ6 -> 12.803596 | BI3: 0 | BJ3: =AJ7 -> 13.623822 | BK3: 0 | BL3: =AJ8 -> 6.7645783 | BM3: 0 | BN3: =AJ9 -> 8.8796982 | BO3: 0 | BP3: =AJ10 -> 2.2429547 | BQ3: 0 | BR3: =AJ11 -> 6.3850369 | BT3: Value | BU3: =SUMPRODUCT(BD$18:BD$252,BF$18:BF$252) -> 32550000 | BV3: =SUMPRODUCT(AR$18:AR$252,AT$18:AT$252) -> 74800000 | BW3: =SUMPRODUCT(AU$18:AU$252,AW$18:AW$252) -> 14000000 | BX3: =SUMPRODUCT(BG$18:BG$252,BI$18:BI$252) -> 13950000 | BY3: =SUMPRODUCT(BL$18:BL$252,BJ$18:BJ$252) -> 24000000 | BZ3: =SUMPRODUCT(AX$18:AX$252,AZ$18:AZ$252) -> 24000000 | CA3: =SUMPRODUCT(BA$18:BA$252,BC$18:BC$252) -> 20000000 | CB3: =SUMPRODUCT(AO$18:AO$252,AQ$18:AQ$252) -> 5200000 | CC3: =SUMPRODUCT(BM$18:BM$252,BO$18:BO$252) -> 2.065e+08
E4: CG | F4: 74800000 | G4: 0.05 | H4: =F4*G4 -> 3740000 | J4: WAC | K4: =5.566% -> 0.05566 | L4: CA & CY | M4: 0.2251816 | N4: GROUP A | AB4: 3 | AC4: =AG3 -> 2.0555706e+08 | AD4: =PMT($K$4/12,$K$7-AB4+1,-AC4) -> 1428195.9 | AE4: =AC4*$K$4/12 -> 953442.15 | AF4: =AD4-AE4 -> 474753.77 | AG4: =AC4-AF4 -> 2.050823e+08 | AI4: CG | AJ4: =SUM(AS18:AS252)/(12*F4) -> 2.7577516 | BA4: 100 | BB4: 5.6659899 | BC4: 100 | BD4: 3.5120336 | BE4: 100 | BF4: 6.6123424 | BG4: 100 | BH4: 15.400692 | BI4: 100 | BJ4: 15.711021 | BK4: 100 | BL4: 8.7081094 | BM4: 100 | BN4: 11.202441 | BO4: 100 | BP4: 2.2429547 | BQ4: 100 | BR4: 8.1697338 | BT4: Difference | BU4: =BU3-F3 -> 0 | BV4: =BV3-F4 -> 8.7469816e-06 | BW4: =BW3-F5 -> 0.0002346877 | BX4: =BX3-F6 -> 4.0549785e-06 | BY4: =BY3-F7 -> 1.3411045e-07 | BZ4: =BZ3-F7 -> 1.0404736e-05 | CA4: =CA3-F9 -> 7.0780516e-08 | CB4: =CB3-F10 -> 5.205255e-05 | CC4: =CC3-F11 -> 0
E5: CM | F5: 14000000 | G5: 0.05 | H5: =F5*G5 -> 700000 | J5: PSA | K5: 183 | L5: CG, VE, CM, GZ,TC &CZ | M5: 0.7748184 | N5: GROUP B | AB5: 4 | AC5: =AG4 -> 2.050823e+08 | AD5: =PMT($K$4/12,$K$7-AB5+1,-AC5) -> 1428195.9 | AE5: =AC5*$K$4/12 -> 951240.09 | AF5: =AD5-AE5 -> 476955.84 | AG5: =AC5-AF5 -> 2.0460535e+08 | AI5: CM | AJ5: =SUM(AV18:AV252)/(12*F5) -> 5.2415728 | BA5: 183 | BB5: 4.2294642 | BC5: 183 | BD5: 2.7577516 | BE5: 183 | BF5: 5.2415728 | BG5: 183 | BH5: 12.803596 | BI5: 183 | BJ5: 13.623822 | BK5: 183 | BL5: 6.7645783 | BM5: 183 | BN5: 8.8796982 | BO5: 183 | BP5: 2.2429547 | BQ5: 183 | BR5: 6.3850369 | BT5: X* | BU5: 0.024528739 | BV5: 0.025417296 | BW5: 0.02456712 | BX5: 0.021393673 | BY5: 0.02017482 | BZ5: 0.0099139265 | CA5: 0.023046558 | CB5: 0.025423847 | CC5: 0.022756985
E6: CY | F6: 13950000 | G6: 0.05 | H6: =F6*G6 -> 697500 | J6: CPR | K6: 0.06 | AB6: 5 | AC6: =AG5 -> 2.0460535e+08 | AD6: =PMT($K$4/12,$K$7-AB6+1,-AC6) -> 1428195.9 | AE6: =AC6*$K$4/12 -> 949027.81 | AF6: =AD6-AE6 -> 479168.12 | AG6: =AC6-AF6 -> 2.0412618e+08 | AI6: CY | AJ6: =SUM(BH18:BH252)/(12*F6) -> 12.803596 | AO6: =AY3-AM3 -> 0.028 | BA6: 300 | BB6: 3.2045167 | BC6: 300 | BD6: 2.2238214 | BE6: 300 | BF6: 4.0695959 | BG6: 300 | BH6: 9.8504401 | BI6: 300 | BJ6: 10.938476 | BK6: 300 | BL6: 5.1646061 | BM6: 300 | BN6: 6.7897131 | BO6: 300 | BP6: 2.1231628 | BQ6: 300 | BR6: 4.781627
E7: CZ | F7: 24000000 | G7: 0.05 | H7: =F7*G7 -> 1200000 | J7: Term (m) | K7: 240 | AI7: CZ | AJ7: =SUM(BK18:BK252)/(12*AL12) -> 13.623822 | AO7: =AO6/2 -> 0.014 | BA7: 400 | BB7: 2.7191159 | BC7: 400 | BD7: 1.9634823 | BE7: 400 | BF7: 3.472098 | BG7: 400 | BH7: 8.0637162 | BI7: 400 | BJ7: 9.1532973 | BK7: 400 | BL7: 4.3320606 | BM7: 400 | BN7: 5.6467827 | BO7: 400 | BP7: 1.9474084 | BQ7: 400 | BR7: 3.9058293
E8: GZ | F8: 22000000 | G8: 0.05 | H8: =F8*G8 -> 1100000 | J8: Term to Maturity | K8: 235 | AI8: GZ | AJ8: =SUM(AY18:AY252)/(12*AL11) -> 6.7645783 | AO8: =AO7/2 -> 0.007
E9: TC | F9: 20000000 | G9: 0.05 | H9: =F9*G9 -> 1000000 | AI9: TC | AJ9: =SUM(BB18:BB252)/(12*F9) -> 8.8796982
E10: VE | F10: 5200000 | G10: 0.05 | H10: =F10*G10 -> 260000 | K10: Assets | AI10: VE | AJ10: =SUM(AP18:AP252)/(12*F10) -> 2.2429547 | AN10: =AM1 -> 1 | AO10: =AY1 -> 360 | BT10: x
E11: The Assets | F11: =SUM(F3:F10) -> 206500000 | G11: 0.05 | H11: =SUM(H3:H10) -> 10325000 | J11: Balance | K11: 206500000 | AI11: Collateral | AJ11: =SUM(BN18:BN252)/(12*F11) -> 6.3850369 | AK11: Max GZ | AL11: =MAX(Y18:Y252) -> 28469664 | AN11: =AM2 -> 0.0233 | AO11: =AY2 -> 0.0373 | BT11: PSA Speed | BU11: Tranche CA | BV11: Tranche CG | BW11: Tranche CM | BX11: Tranche CY | BY11: Tranche CZ | BZ11: Tranche GZ | CA11: Tranche TC | CB11: Tranche VE | CC11: Collateral
J12: Term | K12: 235 | AK12: Max CZ | AL12: =MAX(AK18:AK252) -> 38394299 | BT12: 0 | BU12: =BU5 -> 0.024528739 | BV12: =BV5 -> 0.025417296 | BW12: =BW5 -> 0.02456712 | BX12: =BX5 -> 0.021393673 | BY12: =BY5 -> 0.02017482 | BZ12: =BZ5 -> 0.0099139265 | CA12: =CA5 -> 0.023046558 | CB12: =CB5 -> 0.025423847 | CC12: =CC5 -> 0.022756985
J13: WACC | K13: 0.05566 | Q13: Principal Check | T13: Principal Check | W13: Principal Check | Z13: Principal Check | AC13: Principal Check | AF13: Principal Check | AI13: Principal Check | AL13: Principal Check | BT13: 100 | BU13: ='PSA 100 vs X'!BU5 -> 0.02192039 | BV13: ='PSA 100 vs X'!BV5 -> 0.024446806 | BW13: ='PSA 100 vs X'!BW5 -> 0.022364026 | BX13: ='PSA 100 vs X'!BX5 -> 0.015325083 | BY13: ='PSA 100 vs X'!BY5 -> 0.013014966 | BZ13: ='PSA 100 vs X'!BZ5 -> 0.0094330705 | CA13: ='PSA 100 vs X'!CA5 -> 0.018586373 | CB13: ='PSA 100 vs X'!CB5 -> 0.025358489 | CC13: ='PSA 100 vs X'!CC5 -> 0.018573832
Q14: =SUM(Q18:Q252) -> 5200000 | T14: =SUM(T18:T252) -> 74800000 | W14: =SUM(W18:W252) -> 14000000 | Z14: =SUM(Z18:Z252) -> 28469664 | AC14: =SUM(AC18:AC252) -> 20000000 | AF14: =SUM(AF18:AF252) -> 32550000 | AI14: =SUM(AI18:AI252) -> 13950000 | AL14: =SUM(AL18:AL252) -> 38120709 | BT14: 183 | BU14: {='PSA 183 on X'!BU5:CC5} -> 0.023516729 | BV14: 0.025345018 | BW14: 0.023591729 | BX14: 0.017086336 | BY14: 0.014918714 | BZ14: 0.00807609 | CA14: 0.020458943 | CB14: 0.025358489 | CC14: 0.020014572
BT15: 300 | BU15: {='PSA 300 vs X'!BU5:CC5} -> 0.02475377 | BV15: 0.025986937 | BW15: 0.024644633 | BX15: 0.019234935 | BY15: 0.017050756 | BZ15: 0.0050007568 | CA15: 0.022223415 | CB15: 0.025575242 | CC15: 0.021548058
N16: Asset Prinicpal Amount | Q16: Tranche VE | T16: Tranche CG | W16: Tranche CM | Z16: Tranche GZ | AC16: Tranche TC | AF16: Tranche CA | AH16: Tranche CY | AK16: Tranche CZ | AN16: Treasury | AP16: Tranche VE | AS16: Tranche CG | AV16: Tranche CM | AY16: Tranche GZ | BB16: Tranche TC | BE16: Tranche CA | BG16: Tranche CY | BJ16: Tranche CZ | BM16: Collateral | BT16: 400 | BU16: {='PSA 400 on X'!BU5:CC5} -> 0.025355313 | BV16: 0.026294327 | BW16: 0.02519042 | BX16: 0.020661746 | BY16: 0.018584184 | BZ16: 0.001909631 | CA16: 0.023220943 | CB16: 0.025850064 | CC16: 0.022559104
A17: CPR Month | B17: Month | C17: Principal | E17: Asset Principal | F17: Payment | G17: Interest+Servicing | H17: Principal | I17: CPR | J17: SMM | K17: Prepayment | L17: Total Collateral CF | M17: Excess CF | N17: Group A | O17: Group B | P17: Balance | Q17: Principal2 | R17: Interest | S17: Balance5 | T17: Principal6 | U17: Interest7 | V17: Balance8 | W17: Principal9 | X17: Interest | Y17: Balance11 | Z17: Principal12 | AA17: Interest(Z) | AB17: Balance14 | AC17: Principal15 | AD17: Interest16 | AE17: Balance20 | AF17: Principal21 | AG17: Interest22 | AH17: Balance202 | AI17: Principal213 | AJ17: Interest224 | AK17: Balance3 | AL17: Principal4 | AM17: Interest(Z) | AN17: Yield Curve | AO17: Cash Flow | AP17: Average life | AQ17: Discount Factor | AR17: Cash Flow | AS17: Average life | AT17: Discount Factor | AU17: Cash Flow | AV17: Average life | AW17: Discount Factor | AX17: Cash Flow | AY17: Average life | AZ17: Discount Factor | BA17: Cash Flow | BB17: Average life | BC17: Discount Factor | BD17: Cash Flow | BE17: Average life | BF17: Discount Factor | BG17: Cash Flow | BH17: Average life | BI17: Discount Factor | BJ17: Cash Flow | BK17: Average life | BL17: Discount Factor | BM17: Cash Flow | BN17: Average life | BO17: Discount Factor
A18: 6 | B18: 1 | C18: =P18+S18+V18+Y18+AB18+AE18+AH18+AK18 -> 206500000 | D18: =C18-E18 -> 0 | E18: =$F$11 -> 206500000 | F18: =PMT($K$13/12,$K$12-B18+1,-E18,0) -> 1444804.7 | G18: =E18*$K$13/12 -> 957815.83 | H18: =F18-G18 -> 486988.84 | I18: =IF(A18<=(30-(240-$K$8)),((A18+(240-$K$7))/30)*$K$6,$K$6)*($K$5/100) -> 0.02196 | J18: =1-(1-I18)^(1/12) -> 0.0018486816 | K18: =(E18-H18)*J18 -> 380852.46 | L18: =K18+H18+G18 -> 1825657.1 | M18: =L18-G18 -> 867841.3 | N18: =M18*$M$4 -> 195421.89 | O18: =M18*$M$5 -> 672419.41 | P18: =$F$10 -> 5200000 | Q18: =MIN(IF(S18>O18,0,MIN(P18,O18-S18))+IF(P18>0,MIN(AA18,P18)),P18) -> 91666.667 | R18: =P18*($G$10/12) -> 21666.667 | S18: =$F$4 -> 74800000 | T18: =MIN(IF(S18>O18,O18,S18)+IF(S18>0,AM18,0),S18) -> 772419.41 | U18: =S18*($G$4/12) -> 311666.67 | V18: =$F$5 -> 14000000 | W18: =IF(T18+P18<=O18+AM18+AA18,MIN(V18,O18-Q18+AA18-T18+AM18),0) -> 0 | X18: =V18*($G$5/12) -> 58333.333 | Y18: =$F$8 -> 22000000 | Z18: =IF(V18>O18,0,MIN(Y18,O18-V18)) -> 0 | AA18: =Y18*($G$8/12) -> 91666.667 | AB18: =F9 -> 20000000 | AC18: =MIN(IF(Y18>O18,0,MIN(AB18,O18+AM18-Y18))) -> 0 | AD18: =AB18*($G$9/12) -> 83333.333 | AE18: =F3 -> 32550000 | AF18: =IF(AE18>N18,N18,AE18) -> 195421.89 | AG18: =AE18*($G$3/12) -> 135625 | AH18: =F6 -> 13950000 | AI18: =IF(AE18>N18,0,MIN(AH18,N18-AE18)) -> 0 | AJ18: =AH18*($G$6/12) -> 58125 | AK18: =F7 -> 24000000 | AL18: =IF(AB18>0,IF(AB18>O18,0,MIN(AK18,O18-AB18)),O18) -> 0 | AM18: =AK18*($G$7/12) -> 100000 | AN18: =FORECAST(B18, $AM$2:$AY$2,$AM$1:$AY$1) -> 0.0233 | AO18: =Q18+R18 -> 113333.33 | AP18: =Q18*B18 -> 91666.667 | AQ18: =1/(1+(AN18+$CB$5)/12)^$B18 -> 0.9959561 | AR18: =T18+U18 -> 1084086.1 | AS18: =T18*A18 -> 4634516.4 | AT18: =1/(1+(AN18+$BV$5)/12)^$B18 -> 0.99595664 | AU18: =W18+X18 -> 58333.333 | AV18: =W18*A18 -> 0 | AW18: =1/(1+(AN18+$BW$5)/12)^$B18 -> 0.99602692 | AX18: =IF(Y19>Y18,0,Z18+AA18) -> 0 | AY18: =A18*Z18 -> 0 | AZ18: =1/(1+(AN18+$BZ$5)/12)^$B18 -> 0.99723981 | BA18: =AC18+AD18 -> 83333.333 | BB18: =AC18*A18 -> 0 | BC18: =1/(1+(AN18+$CA$5)/12)^$B18 -> 0.99615265 | BD18: =AF18+AG18 -> 331046.89 | BE18: =AF18*A18 -> 1172531.3 | BF18: =1/(1+(AN18+$BU$5)/12)^$B18 -> 0.99603009 | BG18: =AI18+AJ18 -> 58125 | BH18: =AI18*A18 -> 0 | BI18: =1/(1+(AN18+$BX$5)/12)^$B18 -> 0.99628935 | BJ18: =IF(AK19>AK18,0,AL18+AM18) -> 0 | BK18: =A18*AL18 -> 0 | BL18: =1/(1+(AN18+$BY$5)/12)^$B18 -> 0.99639018 | BM18: =AO18+AR18+AU18+AX18+BA18+BD18+BG18+BJ18 -> 1728258 | BN18: =M18*B18 -> 867841.3 | BO18: =1/(1+(AN18+$CC$5)/12)^$B18 -> 0.99617659
A19: 7 | B19: 2 | C19: =P19+S19+V19+Y19+AB19+AE19+AH19+AK19 -> 2.0563216e+08 | D19: =C19-E19 -> 0 | E19: =E18-H18-K18 -> 2.0563216e+08 | F19: =PMT($K$13/12,$K$12-B19+1,-E19,0) -> 1442133.7 | G19: =E19*$K$13/12 -> 953790.5 | H19: =F19-G19 -> 488343.19 | I19: =IF(A19<=(30-(240-$K$8)),((A19+(240-$K$7))/30)*$K$6,$K$6)*($K$5/100) -> 0.02562 | J19: =1-(1-I19)^(1/12) -> 0.0021604884 | K19: =(E19-H19)*J19 -> 443210.84 | L19: =K19+H19+G19 -> 1885344.5 | M19: =L19-G19 -> 931554.03 | N19: =M19*$M$4 -> 209768.83 | O19: =M19*$M$5 -> 721785.2 | P19: =P18-Q18 -> 5108333.3 | Q19: =MIN(IF(S19>O19,0,MIN(P19,O19-S19))+IF(P19>0,MIN(AA19,P19)),P19) -> 92048.611 | R19: =P19*($G$10/12) -> 21284.722 | S19: =S18-T18 -> 74027581 | T19: =MIN(IF(S19>O19,O19,S19)+IF(S19>0,AM19,0),S19) -> 822201.87 | U19: =S19*($G$4/12) -> 308448.25 | V19: =V18-W18 -> 14000000 | W19: =IF(T19+P19<=O19+AM19+AA19,MIN(V19,O19-Q19+AA19-T19+AM19),0) -> 0 | X19: =V19*($G$5/12) -> 58333.333 | Y19: =IF(V18>O18,(IF(V18>AA18+O18+AM18,Y18+AA18,Y18+AA18-((AA18+O18+AM18)-V18))),Y18-Z18) -> 22091667 | Z19: =MIN(IF(V19>O19,0,MIN(Y19,O19-V19))+IF(AM18>V18,AM18,0),Y19) -> 0 | AA19: =Y19*($G$8/12) -> 92048.611 | AB19: =AB18-AC18 -> 20000000 | AC19: =MIN(IF(Y19>O19,0,MIN(AB19,O19+AM19-Y19))) -> 0 | AD19: =AB19*($G$9/12) -> 83333.333 | AE19: =AE18-AF18 -> 32354578 | AF19: =IF(AE19>N19,N19,AE19) -> 209768.83 | AG19: =AE19*($G$3/12) -> 134810.74 | AH19: =AH18-AI18 -> 13950000 | AI19: =IF(AE19>N19,0,MIN(AH19,N19-AE19)) -> 0 | AJ19: =AH19*($G$6/12) -> 58125 | AK19: =IF(AL18=0,AK18+AM18,AK18-AL18) -> 24100000 | AL19: =MIN(IF(AB19>0,IF(AB19>O19,0,MIN(AK19,O19-AB19)),O19),AK19) -> 0 | AM19: =AK19*($G$7/12) -> 100416.67 | AN19: =FORECAST(B19, $AM$2:$AY$2,$AM$1:$AY$1) -> 0.023338997 | AO19: =Q19+R19 -> 113333.33 | AP19: =Q19*B19 -> 184097.22 | AQ19: =1/(1+(AN19+$CB$5)/12)^$B19 -> 0.99192213 | AR19: =T19+U19 -> 1130650.1 | AS19: =T19*A19 -> 5755413.1 | AT19: =1/(1+(AN19+$BV$5)/12)^$B19 -> 0.99192321 | AU19: =W19+X19 -> 58333.333 | AV19: =W19*A19 -> 0 | AW19: =1/(1+(AN19+$BW$5)/12)^$B19 -> 0.99206321 | AX19: =IF(Y20>Y19,0,Z19+AA19) -> 0 | AY19: =A19*Z19 -> 0 | AZ19: =1/(1+(AN19+$BZ$5)/12)^$B19 -> 0.9944808 | BA19: =AC19+AD19 -> 83333.333 | BB19: =AC19*A19 -> 0 | BC19: =1/(1+(AN19+$CA$5)/12)^$B19 -> 0.99231367 | BD19: =AF19+AG19 -> 344579.57 | BE19: =AF19*A19 -> 1468381.8 | BF19: =1/(1+(AN19+$BU$5)/12)^$B19 -> 0.99206953 | BG19: =AI19+AJ19 -> 58125 | BH19: =AI19*A19 -> 0 | BI19: =1/(1+(AN19+$BX$5)/12)^$B19 -> 0.99258604 | BJ19: =IF(AK20>AK19,0,AL19+AM19) -> 0 | BK19: =A19*AL19 -> 0 | BL19: =1/(1+(AN19+$BY$5)/12)^$B19 -> 0.99278695 | BM19: =AO19+AR19+AU19+AX19+BA19+BD19+BG19+BJ19 -> 1788354.7 | BN19: =M19*B19 -> 1863108.1 | BO19: =1/(1+(AN19+$CC$5)/12)^$B19 -> 0.99236138
